Workbook
Name a: #REF!
Name a: #REF!
Name a: #REF!
Name Comment: #REF!
Name Comment: #REF!
Name Comment: #REF!
Name Comment: #REF!
Name CostCode: #REF!
Name CostCode: #REF!
Name CostCode: #REF!
Name CostCode: #REF!
Name CostCode: #REF!
Name CostCode: #REF!
Name d: #REF!
Name d: #REF!
Name d: #REF!
Name d: #REF!
Name d: #REF!
Name d: #REF!
Name d: #REF!
Name d: #REF!
Name d: #REF!
Name d: #REF!
Name d: #REF!
Name DDD: #REF!
Name DDD: #REF!
Name DDD: #REF!
Name DDD: #REF!
Name DDD: #REF!
Name DDD: #REF!
Name DDD: #REF!
Name delete1: #REF!
Name delete1: #REF!
Name delete1: #REF!
Name delete1: #REF!
Name delete1: #REF!
Name delete1: #REF!
Name delete1: #REF!
Name delete1: #REF!
Name delete1: #REF!
Name delete1: #REF!
Name delete1: #REF!
Name EWC: "M00873"
Name GDSGSDG: #REF!
Name GDSGSDG: #REF!
Name GDSGSDG: #REF!
Name GDSGSDG: #REF!
Name GDSGSDG: #REF!
Name GDSGSDG: #REF!
Name GDSGSDG: #REF!
Name GDSGSDG: #REF!
Name GDSGSDG: #REF!
Name GDSGSDG: #REF!
Name ghhghg: #REF!
Name ghhghg: #REF!
Name ghhghg: #REF!
Name ghhghg: #REF!
Name ghhghg: #REF!
Name ghhghg: #REF!
Name ghhghg: #REF!

Sheet Header 
A1: Installation UIC | B1: Installation Name
A2: M67400 | B2: MCB Camp Butler
A3: Tenant UIC | B3: Tenant Name
A4: M29030 | B4: CLB 4
A5: Subordinate UIC 1 | B5: Subordinate Unit 1 Name
A6: =A4 -> M29030 | B6: =B4 -> CLB 4

Sheet UNIT_ROLLUP
A1: BASIC FACILITY REQUIREMENTS UNIT ROLLUP
A3: Installation: | F3: H&S BN MCIPAC MCB CP BUTLER JA | M3: Tenant: | R3: CLB 4
A4: Installation UIC: | F4: M67400 | M4: Tenant UIC: | R4: M29030 | Y4: Planning Area: | AE4: SW
C8: Facilities measured in SF
C9: CCN | F9: Description | U9: Required Area
C10: 14345 | F10: ARMORY | U10: 413
C11: 21451 | F11: AUTO ORGANIZATION SHOP | U11: 2315
C12: 21455 | F12: VEHICLE WASH PLATFORM | U12: 3192
C13: 61072 | F13: BATTALION SQUADRON HEADQUARTERS, MARINE CORPS | U13: 8379
P15: Total = | U15: =SUM(U10:U13) -> 14299
A17: CLB-4 (M29030) has relocated from Camp Foster to Camp Schwab. This BFR consolidates space requirements for CLB-4 and its four subordinate units: Headquarters Company (M29111), Combat Logistics Company Alpha (M29112), Combat Logistics Company Bravo (M29113), and General Support Company (M29114). All four companies are collocated at Camp Schwab under Planning Area SW. Facility requirements are calculated from the FY2026 Table of Organization and Equipment (TO/E) dated 02 February 2026, reflecting 310 total assigned billets. CCNs cover armory storage, automotive organizational maintenance, vehicle wash, and battalion headquarters administrative space.
AF33: 1
A42: TOTAL REQUIREMENT: | H42: =U15 -> 14299 | L42: GSF | AC42: Page | AD42: 1 | AE42: of | AF42: 1 | AG42: TOTAL REQUIREMENT: | AN42: =AS29 -> 0 | AR42: SY | BI42: Page | BJ42: 1 | BK42: of | BL42: =$AF$33 -> 1 | BM42: TOTAL REQUIREMENT: | BT42: =BY29 -> 0 | BX42: SY | CO42: Page | CP42: 1 | CQ42: of | CR42: =$AF$33 -> 1 | CS42: TOTAL REQUIREMENT: | CZ42: =DE29 -> 0 | DD42: SY | DU42: Page | DV42: 1 | DW42: of | DX42: =$AF$33 -> 1 | DY42: TOTAL REQUIREMENT: | EF42: =EK29 -> 0 | EJ42: SY | FA42: Page | FB42: 1 | FC42: of | FD42: =$AF$33 -> 1 | FE42: TOTAL REQUIREMENT: | FL42: =FQ29 -> 0 | FP42: SY | GG42: Page | GH42: 1 | GI42: of | GJ42: =$AF$33 -> 1 | GK42: TOTAL REQUIREMENT: | GR42: =GW29 -> 0 | GV42: SY | HM42: Page | HN42: 1 | HO42: of | HP42: =$AF$33 -> 1 | HQ42: TOTAL REQUIREMENT: | HX42: =IC29 -> 0 | IB42: SY | IS42: Page | IT42: 1 | IU42: of | IV42: =$AF$33 -> 1 | IW42: TOTAL REQUIREMENT: | JD42: =JI29 -> 0 | JH42: SY | JY42: Page | JZ42: 1 | KA42: of | KB42: =$AF$33 -> 1 | KC42: TOTAL REQUIREMENT: | KJ42: =KO29 -> 0 | KN42: SY | LE42: Page | LF42: 1 | LG42: of | LH42: =$AF$33 -> 1 | LI42: TOTAL REQUIREMENT: | LP42: =LU29 -> 0 | LT42: SY | MK42: Page | ML42: 1 | MM42: of | MN42: =$AF$33 -> 1 | MO42: TOTAL REQUIREMENT: | MV42: =NA29 -> 0 | MZ42: SY | NQ42: Page | NR42: 1 | NS42: of | NT42: =$AF$33 -> 1 | NU42: TOTAL REQUIREMENT: | OB42: =OG29 -> 0 | OF42: SY | OW42: Page | OX42: 1 | OY42: of | OZ42: =$AF$33 -> 1 | PA42: TOTAL REQUIREMENT: | PH42: =PM29 -> 0 | PL42: SY | QC42: Page | QD42: 1 | QE42: of | QF42: =$AF$33 -> 1 | QG42: TOTAL REQUIREMENT: | QN42: =QS29 -> 0 | QR42: SY | RI42: Page | RJ42: 1 | RK42: of | RL42: =$AF$33 -> 1 | RM42: TOTAL REQUIREMENT: | RT42: =RY29 -> 0 | RX42: SY | SO42: Page | SP42: 1 | SQ42: of | SR42: =$AF$33 -> 1 | SS42: TOTAL REQUIREMENT: | SZ42: =TE29 -> 0 | TD42: SY | TU42: Page | TV42: 1 | TW42: of | TX42: =$AF$33 -> 1 | TY42: TOTAL REQUIREMENT: | UF42: =UK29 -> 0 | UJ42: SY | VA42: Page | VB42: 1 | VC42: of | VD42: =$AF$33 -> 1 | VE42: TOTAL REQUIREMENT: | VL42: =VQ29 -> 0 | VP42: SY | WG42: Page | WH42: 1 | WI42: of | WJ42: =$AF$33 -> 1 | WK42: TOTAL REQUIREMENT: | WR42: =WW29 -> 0 | WV42: SY | XM42: Page | XN42: 1 | XO42: of | XP42: =$AF$33 -> 1 | XQ42: TOTAL REQUIREMENT: | XX42: =YC29 -> 0 | YB42: SY | YS42: Page | YT42: 1 | YU42: of | YV42: =$AF$33 -> 1 | YW42: TOTAL REQUIREMENT: | ZD42: =ZI29 -> 0 | ZH42: SY | ZY42: Page | ZZ42: 1 | AAA42: of | AAB42: =$AF$33 -> 1 | AAC42: TOTAL REQUIREMENT: | AAJ42: =AAO29 -> 0 | AAN42: SY | ABE42: Page | ABF42: 1 | ABG42: of | ABH42: =$AF$33 -> 1 | ABI42: TOTAL REQUIREMENT: | ABP42: =ABU29 -> 0 | ABT42: SY | ACK42: Page | ACL42: 1 | ACM42: of | ACN42: =$AF$33 -> 1 | ACO42: TOTAL REQUIREMENT: | ACV42: =ADA29 -> 0 | ACZ42: SY | ADQ42: Page | ADR42: 1 | ADS42: of | ADT42: =$AF$33 -> 1 | ADU42: TOTAL REQUIREMENT: | AEB42: =AEG29 -> 0 | AEF42: SY | AEW42: Page | AEX42: 1 | AEY42: of | AEZ42: =$AF$33 -> 1 | AFA42: TOTAL REQUIREMENT: | AFH42: =AFM29 -> 0 | AFL42: SY | AGC42: Page | AGD42: 1 | AGE42: of | AGF42: =$AF$33 -> 1 | AGG42: TOTAL REQUIREMENT: | AGN42: =AGS29 -> 0 | AGR42: SY | AHI42: Page | AHJ42: 1 | AHK42: of | AHL42: =$AF$33 -> 1 | AHM42: TOTAL REQUIREMENT: | AHT42: =AHY29 -> 0 | AHX42: SY | AIO42: Page | AIP42: 1 | AIQ42: of | AIR42: =$AF$33 -> 1 | AIS42: TOTAL REQUIREMENT: | AIZ42: =AJE29 -> 0 | AJD42: SY | AJU42: Page | AJV42: 1 | AJW42: of | AJX42: =$AF$33 -> 1 | AJY42: TOTAL REQUIREMENT: | AKF42: =AKK29 -> 0 | AKJ42: SY | ALA42: Page | ALB42: 1 | ALC42: of | ALD42: =$AF$33 -> 1 | ALE42: TOTAL REQUIREMENT: | ALL42: =ALQ29 -> 0 | ALP42: SY | AMG42: Page | AMH42: 1 | AMI42: of | AMJ42: =$AF$33 -> 1 | AMK42: TOTAL REQUIREMENT: | AMR42: =AMW29 -> 0 | AMV42: SY | ANM42: Page | ANN42: 1 | ANO42: of | ANP42: =$AF$33 -> 1 | ANQ42: TOTAL REQUIREMENT: | ANX42: =AOC29 -> 0 | AOB42: SY | AOS42: Page | AOT42: 1 | AOU42: of | AOV42: =$AF$33 -> 1 | AOW42: TOTAL REQUIREMENT: | APD42: =API29 -> 0 | APH42: SY | APY42: Page | APZ42: 1 | AQA42: of | AQB42: =$AF$33 -> 1 | AQC42: TOTAL REQUIREMENT: | AQJ42: =AQO29 -> 0 | AQN42: SY | ARE42: Page | ARF42: 1 | ARG42: of | ARH42: =$AF$33 -> 1 | ARI42: TOTAL REQUIREMENT: | ARP42: =ARU29 -> 0 | ART42: SY | ASK42: Page | ASL42: 1 | ASM42: of | ASN42: =$AF$33 -> 1 | ASO42: TOTAL REQUIREMENT: | ASV42: =ATA29 -> 0 | ASZ42: SY | ATQ42: Page | ATR42: 1 | ATS42: of | ATT42: =$AF$33 -> 1 | ATU42: TOTAL REQUIREMENT: | AUB42: =AUG29 -> 0 | AUF42: SY | AUW42: Page | AUX42: 1 | AUY42: of | AUZ42: =$AF$33 -> 1 | AVA42: TOTAL REQUIREMENT: | AVH42: =AVM29 -> 0 | AVL42: SY | AWC42: Page | AWD42: 1 | AWE42: of | AWF42: =$AF$33 -> 1 | AWG42: TOTAL REQUIREMENT: | AWN42: =AWS29 -> 0 | AWR42: SY | AXI42: Page | AXJ42: 1 | AXK42: of | AXL42: =$AF$33 -> 1 | AXM42: TOTAL REQUIREMENT: | AXT42: =AXY29 -> 0 | AXX42: SY | AYO42: Page | AYP42: 1 | AYQ42: of | AYR42: =$AF$33 -> 1 | AYS42: TOTAL REQUIREMENT: | AYZ42: =AZE29 -> 0 | AZD42: SY | AZU42: Page | AZV42: 1 | AZW42: of | AZX42: =$AF$33 -> 1 | AZY42: TOTAL REQUIREMENT: | BAF42: =BAK29 -> 0 | BAJ42: SY | BBA42: Page | BBB42: 1 | BBC42: of | BBD42: =$AF$33 -> 1 | BBE42: TOTAL REQUIREMENT: | BBL42: =BBQ29 -> 0 | BBP42: SY | BCG42: Page | BCH42: 1 | BCI42: of | BCJ42: =$AF$33 -> 1 | BCK42: TOTAL REQUIREMENT: | BCR42: =BCW29 -> 0 | BCV42: SY | BDM42: Page | BDN42: 1 | BDO42: of | BDP42: =$AF$33 -> 1 | BDQ42: TOTAL REQUIREMENT: | BDX42: =BEC29 -> 0 | BEB42: SY | BES42: Page | BET42: 1 | BEU42: of | BEV42: =$AF$33 -> 1 | BEW42: TOTAL REQUIREMENT: | BFD42: =BFI29 -> 0 | BFH42: SY | BFY42: Page | BFZ42: 1 | BGA42: of | BGB42: =$AF$33 -> 1 | BGC42: TOTAL REQUIREMENT: | BGJ42: =BGO29 -> 0 | BGN42: SY | BHE42: Page | BHF42: 1 | BHG42: of | BHH42: =$AF$33 -> 1 | BHI42: TOTAL REQUIREMENT: | BHP42: =BHU29 -> 0 | BHT42: SY | BIK42: Page | BIL42: 1 | BIM42: of | BIN42: =$AF$33 -> 1 | BIO42: TOTAL REQUIREMENT: | BIV42: =BJA29 -> 0 | BIZ42: SY | BJQ42: Page | BJR42: 1 | BJS42: of | BJT42: =$AF$33 -> 1 | BJU42: TOTAL REQUIREMENT: | BKB42: =BKG29 -> 0 | BKF42: SY | BKW42: Page | BKX42: 1 | BKY42: of | BKZ42: =$AF$33 -> 1 | BLA42: TOTAL REQUIREMENT: | BLH42: =BLM29 -> 0 | BLL42: SY | BMC42: Page | BMD42: 1 | BME42: of | BMF42: =$AF$33 -> 1 | BMG42: TOTAL REQUIREMENT: | BMN42: =BMS29 -> 0 | BMR42: SY | BNI42: Page | BNJ42: 1 | BNK42: of | BNL42: =$AF$33 -> 1 | BNM42: TOTAL REQUIREMENT: | BNT42: =BNY29 -> 0 | BNX42: SY | BOO42: Page | BOP42: 1 | BOQ42: of | BOR42: =$AF$33 -> 1 | BOS42: TOTAL REQUIREMENT: | BOZ42: =BPE29 -> 0 | BPD42: SY | BPU42: Page | BPV42: 1 | BPW42: of | BPX42: =$AF$33 -> 1 | BPY42: TOTAL REQUIREMENT: | BQF42: =BQK29 -> 0 | BQJ42: SY | BRA42: Page | BRB42: 1 | BRC42: of | BRD42: =$AF$33 -> 1 | BRE42: TOTAL REQUIREMENT: | BRL42: =BRQ29 -> 0 | BRP42: SY | BSG42: Page | BSH42: 1 | BSI42: of | BSJ42: =$AF$33 -> 1 | BSK42: TOTAL REQUIREMENT: | BSR42: =BSW29 -> 0 | BSV42: SY | BTM42: Page | BTN42: 1 | BTO42: of | BTP42: =$AF$33 -> 1 | BTQ42: TOTAL REQUIREMENT: | BTX42: =BUC29 -> 0 | BUB42: SY | BUS42: Page | BUT42: 1 | BUU42: of | BUV42: =$AF$33 -> 1 | BUW42: TOTAL REQUIREMENT: | BVD42: =BVI29 -> 0 | BVH42: SY | BVY42: Page | BVZ42: 1 | BWA42: of | BWB42: =$AF$33 -> 1 | BWC42: TOTAL REQUIREMENT: | BWJ42: =BWO29 -> 0 | BWN42: SY | BXE42: Page | BXF42: 1 | BXG42: of | BXH42: =$AF$33 -> 1 | BXI42: TOTAL REQUIREMENT: | BXP42: =BXU29 -> 0 | BXT42: SY | BYK42: Page | BYL42: 1 | BYM42: of | BYN42: =$AF$33 -> 1 | BYO42: TOTAL REQUIREMENT: | BYV42: =BZA29 -> 0 | BYZ42: SY | BZQ42: Page | BZR42: 1 | BZS42: of | BZT42: =$AF$33 -> 1 | BZU42: TOTAL REQUIREMENT: | CAB42: =CAG29 -> 0 | CAF42: SY | CAW42: Page | CAX42: 1 | CAY42: of | CAZ42: =$AF$33 -> 1 | CBA42: TOTAL REQUIREMENT: | CBH42: =CBM29 -> 0 | CBL42: SY | CCC42: Page | CCD42: 1 | CCE42: of | CCF42: =$AF$33 -> 1 | CCG42: TOTAL REQUIREMENT: | CCN42: =CCS29 -> 0 | CCR42: SY | CDI42: Page | CDJ42: 1 | CDK42: of | CDL42: =$AF$33 -> 1 | CDM42: TOTAL REQUIREMENT: | CDT42: =CDY29 -> 0 | CDX42: SY | CEO42: Page | CEP42: 1 | CEQ42: of | CER42: =$AF$33 -> 1 | CES42: TOTAL REQUIREMENT: | CEZ42: =CFE29 -> 0 | CFD42: SY | CFU42: Page | CFV42: 1 | CFW42: of | CFX42: =$AF$33 -> 1 | CFY42: TOTAL REQUIREMENT: | CGF42: =CGK29 -> 0 | CGJ42: SY | CHA42: Page | CHB42: 1 | CHC42: of | CHD42: =$AF$33 -> 1 | CHE42: TOTAL REQUIREMENT: | CHL42: =CHQ29 -> 0 | CHP42: SY | CIG42: Page | CIH42: 1 | CII42: of | CIJ42: =$AF$33 -> 1 | CIK42: TOTAL REQUIREMENT: | CIR42: =CIW29 -> 0 | CIV42: SY | CJM42: Page | CJN42: 1 | CJO42: of | CJP42: =$AF$33 -> 1 | CJQ42: TOTAL REQUIREMENT: | CJX42: =CKC29 -> 0 | CKB42: SY | CKS42: Page | CKT42: 1 | CKU42: of | CKV42: =$AF$33 -> 1 | CKW42: TOTAL REQUIREMENT: | CLD42: =CLI29 -> 0 | CLH42: SY | CLY42: Page | CLZ42: 1 | CMA42: of | CMB42: =$AF$33 -> 1 | CMC42: TOTAL REQUIREMENT: | CMJ42: =CMO29 -> 0 | CMN42: SY | CNE42: Page | CNF42: 1 | CNG42: of | CNH42: =$AF$33 -> 1 | CNI42: TOTAL REQUIREMENT: | CNP42: =CNU29 -> 0 | CNT42: SY | COK42: Page | COL42: 1 | COM42: of | CON42: =$AF$33 -> 1 | COO42: TOTAL REQUIREMENT: | COV42: =CPA29 -> 0 | COZ42: SY | CPQ42: Page | CPR42: 1 | CPS42: of | CPT42: =$AF$33 -> 1 | CPU42: TOTAL REQUIREMENT: | CQB42: =CQG29 -> 0 | CQF42: SY | CQW42: Page | CQX42: 1 | CQY42: of | CQZ42: =$AF$33 -> 1 | CRA42: TOTAL REQUIREMENT: | CRH42: =CRM29 -> 0 | CRL42: SY | CSC42: Page | CSD42: 1 | CSE42: of | CSF42: =$AF$33 -> 1 | CSG42: TOTAL REQUIREMENT: | CSN42: =CSS29 -> 0 | CSR42: SY | CTI42: Page | CTJ42: 1 | CTK42: of | CTL42: =$AF$33 -> 1 | CTM42: TOTAL REQUIREMENT: | CTT42: =CTY29 -> 0 | CTX42: SY | CUO42: Page | CUP42: 1 | CUQ42: of | CUR42: =$AF$33 -> 1 | CUS42: TOTAL REQUIREMENT: | CUZ42: =CVE29 -> 0 | CVD42: SY | CVU42: Page | CVV42: 1 | CVW42: of | CVX42: =$AF$33 -> 1 | CVY42: TOTAL REQUIREMENT: | CWF42: =CWK29 -> 0 | CWJ42: SY | CXA42: Page | CXB42: 1 | CXC42: of | CXD42: =$AF$33 -> 1 | CXE42: TOTAL REQUIREMENT: | CXL42: =CXQ29 -> 0 | CXP42: SY | CYG42: Page | CYH42: 1 | CYI42: of | CYJ42: =$AF$33 -> 1 | CYK42: TOTAL REQUIREMENT: | CYR42: =CYW29 -> 0 | CYV42: SY | CZM42: Page | CZN42: 1 | CZO42: of | CZP42: =$AF$33 -> 1 | CZQ42: TOTAL REQUIREMENT: | CZX42: =DAC29 -> 0 | DAB42: SY | DAS42: Page | DAT42: 1 | DAU42: of | DAV42: =$AF$33 -> 1 | DAW42: TOTAL REQUIREMENT: | DBD42: =DBI29 -> 0 | DBH42: SY | DBY42: Page | DBZ42: 1 | DCA42: of | DCB42: =$AF$33 -> 1 | DCC42: TOTAL REQUIREMENT: | DCJ42: =DCO29 -> 0 | DCN42: SY | DDE42: Page | DDF42: 1 | DDG42: of | DDH42: =$AF$33 -> 1 | DDI42: TOTAL REQUIREMENT: | DDP42: =DDU29 -> 0 | DDT42: SY | DEK42: Page | DEL42: 1 | DEM42: of | DEN42: =$AF$33 -> 1 | DEO42: TOTAL REQUIREMENT: | DEV42: =DFA29 -> 0 | DEZ42: SY | DFQ42: Page | DFR42: 1 | DFS42: of | DFT42: =$AF$33 -> 1 | DFU42: TOTAL REQUIREMENT: | DGB42: =DGG29 -> 0 | DGF42: SY | DGW42: Page | DGX42: 1 | DGY42: of | DGZ42: =$AF$33 -> 1 | DHA42: TOTAL REQUIREMENT: | DHH42: =DHM29 -> 0 | DHL42: SY | DIC42: Page | DID42: 1 | DIE42: of | DIF42: =$AF$33 -> 1 | DIG42: TOTAL REQUIREMENT: | DIN42: =DIS29 -> 0 | DIR42: SY | DJI42: Page | DJJ42: 1 | DJK42: of | DJL42: =$AF$33 -> 1 | DJM42: TOTAL REQUIREMENT: | DJT42: =DJY29 -> 0 | DJX42: SY | DKO42: Page | DKP42: 1 | DKQ42: of | DKR42: =$AF$33 -> 1 | DKS42: TOTAL REQUIREMENT: | DKZ42: =DLE29 -> 0 | DLD42: SY | DLU42: Page | DLV42: 1 | DLW42: of | DLX42: =$AF$33 -> 1 | DLY42: TOTAL REQUIREMENT: | DMF42: =DMK29 -> 0 | DMJ42: SY | DNA42: Page | DNB42: 1 | DNC42: of | DND42: =$AF$33 -> 1 | DNE42: TOTAL REQUIREMENT: | DNL42: =DNQ29 -> 0 | DNP42: SY | DOG42: Page | DOH42: 1 | DOI42: of | DOJ42: =$AF$33 -> 1 | DOK42: TOTAL REQUIREMENT: | DOR42: =DOW29 -> 0 | DOV42: SY | DPM42: Page | DPN42: 1 | DPO42: of | DPP42: =$AF$33 -> 1 | DPQ42: TOTAL REQUIREMENT: | DPX42: =DQC29 -> 0 | DQB42: SY | DQS42: Page | DQT42: 1 | DQU42: of | DQV42: =$AF$33 -> 1 | DQW42: TOTAL REQUIREMENT: | DRD42: =DRI29 -> 0 | DRH42: SY | DRY42: Page | DRZ42: 1 | DSA42: of | DSB42: =$AF$33 -> 1 | DSC42: TOTAL REQUIREMENT: | DSJ42: =DSO29 -> 0 | DSN42: SY | DTE42: Page | DTF42: 1 | DTG42: of | DTH42: =$AF$33 -> 1 | DTI42: TOTAL REQUIREMENT: | DTP42: =DTU29 -> 0 | DTT42: SY | DUK42: Page | DUL42: 1 | DUM42: of | DUN42: =$AF$33 -> 1 | DUO42: TOTAL REQUIREMENT: | DUV42: =DVA29 -> 0 | DUZ42: SY | DVQ42: Page | DVR42: 1 | DVS42: of | DVT42: =$AF$33 -> 1 | DVU42: TOTAL REQUIREMENT: | DWB42: =DWG29 -> 0 | DWF42: SY | DWW42: Page | DWX42: 1 | DWY42: of | DWZ42: =$AF$33 -> 1 | DXA42: TOTAL REQUIREMENT: | DXH42: =DXM29 -> 0 | DXL42: SY | DYC42: Page | DYD42: 1 | DYE42: of | DYF42: =$AF$33 -> 1 | DYG42: TOTAL REQUIREMENT: | DYN42: =DYS29 -> 0 | DYR42: SY | DZI42: Page | DZJ42: 1 | DZK42: of | DZL42: =$AF$33 -> 1 | DZM42: TOTAL REQUIREMENT: | DZT42: =DZY29 -> 0 | DZX42: SY | EAO42: Page | EAP42: 1 | EAQ42: of | EAR42: =$AF$33 -> 1 | EAS42: TOTAL REQUIREMENT: | EAZ42: =EBE29 -> 0 | EBD42: SY | EBU42: Page | EBV42: 1 | EBW42: of | EBX42: =$AF$33 -> 1 | EBY42: TOTAL REQUIREMENT: | ECF42: =ECK29 -> 0 | ECJ42: SY | EDA42: Page | EDB42: 1 | EDC42: of | EDD42: =$AF$33 -> 1 | EDE42: TOTAL REQUIREMENT: | EDL42: =EDQ29 -> 0 | EDP42: SY | EEG42: Page | EEH42: 1 | EEI42: of | EEJ42: =$AF$33 -> 1 | EEK42: TOTAL REQUIREMENT: | EER42: =EEW29 -> 0 | EEV42: SY | EFM42: Page | EFN42: 1 | EFO42: of | EFP42: =$AF$33 -> 1 | EFQ42: TOTAL REQUIREMENT: | EFX42: =EGC29 -> 0 | EGB42: SY | EGS42: Page | EGT42: 1 | EGU42: of | EGV42: =$AF$33 -> 1 | EGW42: TOTAL REQUIREMENT: | EHD42: =EHI29 -> 0 | EHH42: SY | EHY42: Page | EHZ42: 1 | EIA42: of | EIB42: =$AF$33 -> 1 | EIC42: TOTAL REQUIREMENT: | EIJ42: =EIO29 -> 0 | EIN42: SY | EJE42: Page | EJF42: 1 | EJG42: of | EJH42: =$AF$33 -> 1 | EJI42: TOTAL REQUIREMENT: | EJP42: =EJU29 -> 0 | EJT42: SY | EKK42: Page | EKL42: 1 | EKM42: of | EKN42: =$AF$33 -> 1 | EKO42: TOTAL REQUIREMENT: | EKV42: =ELA29 -> 0 | EKZ42: SY | ELQ42: Page | ELR42: 1 | ELS42: of | ELT42: =$AF$33 -> 1 | ELU42: TOTAL REQUIREMENT: | EMB42: =EMG29 -> 0 | EMF42: SY | EMW42: Page | EMX42: 1 | EMY42: of | EMZ42: =$AF$33 -> 1 | ENA42: TOTAL REQUIREMENT: | ENH42: =ENM29 -> 0 | ENL42: SY | EOC42: Page | EOD42: 1 | EOE42: of | EOF42: =$AF$33 -> 1 | EOG42: TOTAL REQUIREMENT: | EON42: =EOS29 -> 0 | EOR42: SY | EPI42: Page | EPJ42: 1 | EPK42: of | EPL42: =$AF$33 -> 1 | EPM42: TOTAL REQUIREMENT: | EPT42: =EPY29 -> 0 | EPX42: SY | EQO42: Page | EQP42: 1 | EQQ42: of | EQR42: =$AF$33 -> 1 | EQS42: TOTAL REQUIREMENT: | EQZ42: =ERE29 -> 0 | ERD42: SY | ERU42: Page | ERV42: 1 | ERW42: of | ERX42: =$AF$33 -> 1 | ERY42: TOTAL REQUIREMENT: | ESF42: =ESK29 -> 0 | ESJ42: SY | ETA42: Page | ETB42: 1 | ETC42: of | ETD42: =$AF$33 -> 1 | ETE42: TOTAL REQUIREMENT: | ETL42: =ETQ29 -> 0 | ETP42: SY | EUG42: Page | EUH42: 1 | EUI42: of | EUJ42: =$AF$33 -> 1 | EUK42: TOTAL REQUIREMENT: | EUR42: =EUW29 -> 0 | EUV42: SY | EVM42: Page | EVN42: 1 | EVO42: of | EVP42: =$AF$33 -> 1 | EVQ42: TOTAL REQUIREMENT: | EVX42: =EWC29 -> 0 | EWB42: SY | EWS42: Page | EWT42: 1 | EWU42: of | EWV42: =$AF$33 -> 1 | EWW42: TOTAL REQUIREMENT: | EXD42: =EXI29 -> 0 | EXH42: SY | EXY42: Page | EXZ42: 1 | EYA42: of | EYB42: =$AF$33 -> 1 | EYC42: TOTAL REQUIREMENT: | EYJ42: =EYO29 -> 0 | EYN42: SY | EZE42: Page | EZF42: 1 | EZG42: of | EZH42: =$AF$33 -> 1 | EZI42: TOTAL REQUIREMENT: | EZP42: =EZU29 -> 0 | EZT42: SY | FAK42: Page | FAL42: 1 | FAM42: of | FAN42: =$AF$33 -> 1 | FAO42: TOTAL REQUIREMENT: | FAV42: =FBA29 -> 0 | FAZ42: SY | FBQ42: Page | FBR42: 1 | FBS42: of | FBT42: =$AF$33 -> 1 | FBU42: TOTAL REQUIREMENT: | FCB42: =FCG29 -> 0 | FCF42: SY | FCW42: Page | FCX42: 1 | FCY42: of | FCZ42: =$AF$33 -> 1 | FDA42: TOTAL REQUIREMENT: | FDH42: =FDM29 -> 0 | FDL42: SY | FEC42: Page | FED42: 1 | FEE42: of | FEF42: =$AF$33 -> 1 | FEG42: TOTAL REQUIREMENT: | FEN42: =FES29 -> 0 | FER42: SY | FFI42: Page | FFJ42: 1 | FFK42: of | FFL42: =$AF$33 -> 1 | FFM42: TOTAL REQUIREMENT: | FFT42: =FFY29 -> 0 | FFX42: SY | FGO42: Page | FGP42: 1 | FGQ42: of | FGR42: =$AF$33 -> 1 | FGS42: TOTAL REQUIREMENT: | FGZ42: =FHE29 -> 0 | FHD42: SY | FHU42: Page | FHV42: 1 | FHW42: of | FHX42: =$AF$33 -> 1 | FHY42: TOTAL REQUIREMENT: | FIF42: =FIK29 -> 0 | FIJ42: SY | FJA42: Page | FJB42: 1 | FJC42: of | FJD42: =$AF$33 -> 1 | FJE42: TOTAL REQUIREMENT: | FJL42: =FJQ29 -> 0 | FJP42: SY | FKG42: Page | FKH42: 1 | FKI42: of | FKJ42: =$AF$33 -> 1 | FKK42: TOTAL REQUIREMENT: | FKR42: =FKW29 -> 0 | FKV42: SY | FLM42: Page | FLN42: 1 | FLO42: of | FLP42: =$AF$33 -> 1 | FLQ42: TOTAL REQUIREMENT: | FLX42: =FMC29 -> 0 | FMB42: SY | FMS42: Page | FMT42: 1 | FMU42: of | FMV42: =$AF$33 -> 1 | FMW42: TOTAL REQUIREMENT: | FND42: =FNI29 -> 0 | FNH42: SY | FNY42: Page | FNZ42: 1 | FOA42: of | FOB42: =$AF$33 -> 1 | FOC42: TOTAL REQUIREMENT: | FOJ42: =FOO29 -> 0 | FON42: SY | FPE42: Page | FPF42: 1 | FPG42: of | FPH42: =$AF$33 -> 1 | FPI42: TOTAL REQUIREMENT: | FPP42: =FPU29 -> 0 | FPT42: SY | FQK42: Page | FQL42: 1 | FQM42: of | FQN42: =$AF$33 -> 1 | FQO42: TOTAL REQUIREMENT: | FQV42: =FRA29 -> 0 | FQZ42: SY | FRQ42: Page | FRR42: 1 | FRS42: of | FRT42: =$AF$33 -> 1 | FRU42: TOTAL REQUIREMENT: | FSB42: =FSG29 -> 0 | FSF42: SY | FSW42: Page | FSX42: 1 | FSY42: of | FSZ42: =$AF$33 -> 1 | FTA42: TOTAL REQUIREMENT: | FTH42: =FTM29 -> 0 | FTL42: SY | FUC42: Page | FUD42: 1 | FUE42: of | FUF42: =$AF$33 -> 1 | FUG42: TOTAL REQUIREMENT: | FUN42: =FUS29 -> 0 | FUR42: SY | FVI42: Page | FVJ42: 1 | FVK42: of | FVL42: =$AF$33 -> 1 | FVM42: TOTAL REQUIREMENT: | FVT42: =FVY29 -> 0 | FVX42: SY | FWO42: Page | FWP42: 1 | FWQ42: of | FWR42: =$AF$33 -> 1 | FWS42: TOTAL REQUIREMENT: | FWZ42: =FXE29 -> 0 | FXD42: SY | FXU42: Page | FXV42: 1 | FXW42: of | FXX42: =$AF$33 -> 1 | FXY42: TOTAL REQUIREMENT: | FYF42: =FYK29 -> 0 | FYJ42: SY | FZA42: Page | FZB42: 1 | FZC42: of | FZD42: =$AF$33 -> 1 | FZE42: TOTAL REQUIREMENT: | FZL42: =FZQ29 -> 0 | FZP42: SY | GAG42: Page | GAH42: 1 | GAI42: of | GAJ42: =$AF$33 -> 1 | GAK42: TOTAL REQUIREMENT: | GAR42: =GAW29 -> 0 | GAV42: SY | GBM42: Page | GBN42: 1 | GBO42: of | GBP42: =$AF$33 -> 1 | GBQ42: TOTAL REQUIREMENT: | GBX42: =GCC29 -> 0 | GCB42: SY | GCS42: Page | GCT42: 1 | GCU42: of | GCV42: =$AF$33 -> 1 | GCW42: TOTAL REQUIREMENT: | GDD42: =GDI29 -> 0 | GDH42: SY | GDY42: Page | GDZ42: 1 | GEA42: of | GEB42: =$AF$33 -> 1 | GEC42: TOTAL REQUIREMENT: | GEJ42: =GEO29 -> 0 | GEN42: SY | GFE42: Page | GFF42: 1 | GFG42: of | GFH42: =$AF$33 -> 1 | GFI42: TOTAL REQUIREMENT: | GFP42: =GFU29 -> 0 | GFT42: SY | GGK42: Page | GGL42: 1 | GGM42: of | GGN42: =$AF$33 -> 1 | GGO42: TOTAL REQUIREMENT: | GGV42: =GHA29 -> 0 | GGZ42: SY | GHQ42: Page | GHR42: 1 | GHS42: of | GHT42: =$AF$33 -> 1 | GHU42: TOTAL REQUIREMENT: | GIB42: =GIG29 -> 0 | GIF42: SY | GIW42: Page | GIX42: 1 | GIY42: of | GIZ42: =$AF$33 -> 1 | GJA42: TOTAL REQUIREMENT: | GJH42: =GJM29 -> 0 | GJL42: SY | GKC42: Page | GKD42: 1 | GKE42: of | GKF42: =$AF$33 -> 1 | GKG42: TOTAL REQUIREMENT: | GKN42: =GKS29 -> 0 | GKR42: SY | GLI42: Page | GLJ42: 1 | GLK42: of | GLL42: =$AF$33 -> 1 | GLM42: TOTAL REQUIREMENT: | GLT42: =GLY29 -> 0 | GLX42: SY | GMO42: Page | GMP42: 1 | GMQ42: of | GMR42: =$AF$33 -> 1 | GMS42: TOTAL REQUIREMENT: | GMZ42: =GNE29 -> 0 | GND42: SY | GNU42: Page | GNV42: 1 | GNW42: of | GNX42: =$AF$33 -> 1 | GNY42: TOTAL REQUIREMENT: | GOF42: =GOK29 -> 0 | GOJ42: SY | GPA42: Page | GPB42: 1 | GPC42: of | GPD42: =$AF$33 -> 1 | GPE42: TOTAL REQUIREMENT: | GPL42: =GPQ29 -> 0 | GPP42: SY | GQG42: Page | GQH42: 1 | GQI42: of | GQJ42: =$AF$33 -> 1 | GQK42: TOTAL REQUIREMENT: | GQR42: =GQW29 -> 0 | GQV42: SY | GRM42: Page | GRN42: 1 | GRO42: of | GRP42: =$AF$33 -> 1 | GRQ42: TOTAL REQUIREMENT: | GRX42: =GSC29 -> 0 | GSB42: SY | GSS42: Page | GST42: 1 | GSU42: of | GSV42: =$AF$33 -> 1 | GSW42: TOTAL REQUIREMENT: | GTD42: =GTI29 -> 0 | GTH42: SY | GTY42: Page | GTZ42: 1 | GUA42: of | GUB42: =$AF$33 -> 1 | GUC42: TOTAL REQUIREMENT: | GUJ42: =GUO29 -> 0 | GUN42: SY | GVE42: Page | GVF42: 1 | GVG42: of | GVH42: =$AF$33 -> 1 | GVI42: TOTAL REQUIREMENT: | GVP42: =GVU29 -> 0 | GVT42: SY | GWK42: Page | GWL42: 1 | GWM42: of | GWN42: =$AF$33 -> 1 | GWO42: TOTAL REQUIREMENT: | GWV42: =GXA29 -> 0 | GWZ42: SY | GXQ42: Page | GXR42: 1 | GXS42: of | GXT42: =$AF$33 -> 1 | GXU42: TOTAL REQUIREMENT: | GYB42: =GYG29 -> 0 | GYF42: SY | GYW42: Page | GYX42: 1 | GYY42: of | GYZ42: =$AF$33 -> 1 | GZA42: TOTAL REQUIREMENT: | GZH42: =GZM29 -> 0 | GZL42: SY | HAC42: Page | HAD42: 1 | HAE42: of | HAF42: =$AF$33 -> 1 | HAG42: TOTAL REQUIREMENT: | HAN42: =HAS29 -> 0 | HAR42: SY | HBI42: Page | HBJ42: 1 | HBK42: of | HBL42: =$AF$33 -> 1 | HBM42: TOTAL REQUIREMENT: | HBT42: =HBY29 -> 0 | HBX42: SY | HCO42: Page | HCP42: 1 | HCQ42: of | HCR42: =$AF$33 -> 1 | HCS42: TOTAL REQUIREMENT: | HCZ42: =HDE29 -> 0 | HDD42: SY | HDU42: Page | HDV42: 1 | HDW42: of | HDX42: =$AF$33 -> 1 | HDY42: TOTAL REQUIREMENT: | HEF42: =HEK29 -> 0 | HEJ42: SY | HFA42: Page | HFB42: 1 | HFC42: of | HFD42: =$AF$33 -> 1 | HFE42: TOTAL REQUIREMENT: | HFL42: =HFQ29 -> 0 | HFP42: SY | HGG42: Page | HGH42: 1 | HGI42: of | HGJ42: =$AF$33 -> 1 | HGK42: TOTAL REQUIREMENT: | HGR42: =HGW29 -> 0 | HGV42: SY | HHM42: Page | HHN42: 1 | HHO42: of | HHP42: =$AF$33 -> 1 | HHQ42: TOTAL REQUIREMENT: | HHX42: =HIC29 -> 0 | HIB42: SY | HIS42: Page | HIT42: 1 | HIU42: of | HIV42: =$AF$33 -> 1 | HIW42: TOTAL REQUIREMENT: | HJD42: =HJI29 -> 0 | HJH42: SY | HJY42: Page | HJZ42: 1 | HKA42: of | HKB42: =$AF$33 -> 1 | HKC42: TOTAL REQUIREMENT: | HKJ42: =HKO29 -> 0 | HKN42: SY | HLE42: Page | HLF42: 1 | HLG42: of | HLH42: =$AF$33 -> 1 | HLI42: TOTAL REQUIREMENT: | HLP42: =HLU29 -> 0 | HLT42: SY | HMK42: Page | HML42: 1 | HMM42: of | HMN42: =$AF$33 -> 1 | HMO42: TOTAL REQUIREMENT: | HMV42: =HNA29 -> 0 | HMZ42: SY | HNQ42: Page | HNR42: 1 | HNS42: of | HNT42: =$AF$33 -> 1 | HNU42: TOTAL REQUIREMENT: | HOB42: =HOG29 -> 0 | HOF42: SY | HOW42: Page | HOX42: 1 | HOY42: of | HOZ42: =$AF$33 -> 1 | HPA42: TOTAL REQUIREMENT: | HPH42: =HPM29 -> 0 | HPL42: SY | HQC42: Page | HQD42: 1 | HQE42: of | HQF42: =$AF$33 -> 1 | HQG42: TOTAL REQUIREMENT: | HQN42: =HQS29 -> 0 | HQR42: SY | HRI42: Page | HRJ42: 1 | HRK42: of | HRL42: =$AF$33 -> 1 | HRM42: TOTAL REQUIREMENT: | HRT42: =HRY29 -> 0 | HRX42: SY | HSO42: Page | HSP42: 1 | HSQ42: of | HSR42: =$AF$33 -> 1 | HSS42: TOTAL REQUIREMENT: | HSZ42: =HTE29 -> 0 | HTD42: SY | HTU42: Page | HTV42: 1 | HTW42: of | HTX42: =$AF$33 -> 1 | HTY42: TOTAL REQUIREMENT: | HUF42: =HUK29 -> 0 | HUJ42: SY | HVA42: Page | HVB42: 1 | HVC42: of | HVD42: =$AF$33 -> 1 | HVE42: TOTAL REQUIREMENT: | HVL42: =HVQ29 -> 0 | HVP42: SY | HWG42: Page | HWH42: 1 | HWI42: of | HWJ42: =$AF$33 -> 1 | HWK42: TOTAL REQUIREMENT: | HWR42: =HWW29 -> 0 | HWV42: SY | HXM42: Page | HXN42: 1 | HXO42: of | HXP42: =$AF$33 -> 1 | HXQ42: TOTAL REQUIREMENT: | HXX42: =HYC29 -> 0 | HYB42: SY | HYS42: Page | HYT42: 1 | HYU42: of | HYV42: =$AF$33 -> 1 | HYW42: TOTAL REQUIREMENT: | HZD42: =HZI29 -> 0 | HZH42: SY | HZY42: Page | HZZ42: 1 | IAA42: of | IAB42: =$AF$33 -> 1 | IAC42: TOTAL REQUIREMENT: | IAJ42: =IAO29 -> 0 | IAN42: SY | IBE42: Page | IBF42: 1 | IBG42: of | IBH42: =$AF$33 -> 1 | IBI42: TOTAL REQUIREMENT: | IBP42: =IBU29 -> 0 | IBT42: SY | ICK42: Page | ICL42: 1 | ICM42: of | ICN42: =$AF$33 -> 1 | ICO42: TOTAL REQUIREMENT: | ICV42: =IDA29 -> 0 | ICZ42: SY | IDQ42: Page | IDR42: 1 | IDS42: of | IDT42: =$AF$33 -> 1 | IDU42: TOTAL REQUIREMENT: | IEB42: =IEG29 -> 0 | IEF42: SY | IEW42: Page | IEX42: 1 | IEY42: of | IEZ42: =$AF$33 -> 1 | IFA42: TOTAL REQUIREMENT: | IFH42: =IFM29 -> 0 | IFL42: SY | IGC42: Page | IGD42: 1 | IGE42: of | IGF42: =$AF$33 -> 1 | IGG42: TOTAL REQUIREMENT: | IGN42: =IGS29 -> 0 | IGR42: SY | IHI42: Page | IHJ42: 1 | IHK42: of | IHL42: =$AF$33 -> 1 | IHM42: TOTAL REQUIREMENT: | IHT42: =IHY29 -> 0 | IHX42: SY | IIO42: Page | IIP42: 1 | IIQ42: of | IIR42: =$AF$33 -> 1 | IIS42: TOTAL REQUIREMENT: | IIZ42: =IJE29 -> 0 | IJD42: SY | IJU42: Page | IJV42: 1 | IJW42: of | IJX42: =$AF$33 -> 1 | IJY42: TOTAL REQUIREMENT: | IKF42: =IKK29 -> 0 | IKJ42: SY | ILA42: Page | ILB42: 1 | ILC42: of | ILD42: =$AF$33 -> 1 | ILE42: TOTAL REQUIREMENT: | ILL42: =ILQ29 -> 0 | ILP42: SY | IMG42: Page | IMH42: 1 | IMI42: of | IMJ42: =$AF$33 -> 1 | IMK42: TOTAL REQUIREMENT: | IMR42: =IMW29 -> 0 | IMV42: SY | INM42: Page | INN42: 1 | INO42: of | INP42: =$AF$33 -> 1 | INQ42: TOTAL REQUIREMENT: | INX42: =IOC29 -> 0 | IOB42: SY | IOS42: Page | IOT42: 1 | IOU42: of | IOV42: =$AF$33 -> 1 | IOW42: TOTAL REQUIREMENT: | IPD42: =IPI29 -> 0 | IPH42: SY | IPY42: Page | IPZ42: 1 | IQA42: of | IQB42: =$AF$33 -> 1 | IQC42: TOTAL REQUIREMENT: | IQJ42: =IQO29 -> 0 | IQN42: SY | IRE42: Page | IRF42: 1 | IRG42: of | IRH42: =$AF$33 -> 1 | IRI42: TOTAL REQUIREMENT: | IRP42: =IRU29 -> 0 | IRT42: SY | ISK42: Page | ISL42: 1 | ISM42: of | ISN42: =$AF$33 -> 1 | ISO42: TOTAL REQUIREMENT: | ISV42: =ITA29 -> 0 | ISZ42: SY | ITQ42: Page | ITR42: 1 | ITS42: of | ITT42: =$AF$33 -> 1 | ITU42: TOTAL REQUIREMENT: | IUB42: =IUG29 -> 0 | IUF42: SY | IUW42: Page | IUX42: 1 | IUY42: of | IUZ42: =$AF$33 -> 1 | IVA42: TOTAL REQUIREMENT: | IVH42: =IVM29 -> 0 | IVL42: SY | IWC42: Page | IWD42: 1 | IWE42: of | IWF42: =$AF$33 -> 1 | IWG42: TOTAL REQUIREMENT: | IWN42: =IWS29 -> 0 | IWR42: SY | IXI42: Page | IXJ42: 1 | IXK42: of | IXL42: =$AF$33 -> 1 | IXM42: TOTAL REQUIREMENT: | IXT42: =IXY29 -> 0 | IXX42: SY | IYO42: Page | IYP42: 1 | IYQ42: of | IYR42: =$AF$33 -> 1 | IYS42: TOTAL REQUIREMENT: | IYZ42: =IZE29 -> 0 | IZD42: SY | IZU42: Page | IZV42: 1 | IZW42: of | IZX42: =$AF$33 -> 1 | IZY42: TOTAL REQUIREMENT: | JAF42: =JAK29 -> 0 | JAJ42: SY | JBA42: Page | JBB42: 1 | JBC42: of | JBD42: =$AF$33 -> 1 | JBE42: TOTAL REQUIREMENT: | JBL42: =JBQ29 -> 0 | JBP42: SY | JCG42: Page | JCH42: 1 | JCI42: of | JCJ42: =$AF$33 -> 1 | JCK42: TOTAL REQUIREMENT: | JCR42: =JCW29 -> 0 | JCV42: SY | JDM42: Page | JDN42: 1 | JDO42: of | JDP42: =$AF$33 -> 1 | JDQ42: TOTAL REQUIREMENT: | JDX42: =JEC29 -> 0 | JEB42: SY | JES42: Page | JET42: 1 | JEU42: of | JEV42: =$AF$33 -> 1 | JEW42: TOTAL REQUIREMENT: | JFD42: =JFI29 -> 0 | JFH42: SY | JFY42: Page | JFZ42: 1 | JGA42: of | JGB42: =$AF$33 -> 1 | JGC42: TOTAL REQUIREMENT: | JGJ42: =JGO29 -> 0 | JGN42: SY | JHE42: Page | JHF42: 1 | JHG42: of | JHH42: =$AF$33 -> 1 | JHI42: TOTAL REQUIREMENT: | JHP42: =JHU29 -> 0 | JHT42: SY | JIK42: Page | JIL42: 1 | JIM42: of | JIN42: =$AF$33 -> 1 | JIO42: TOTAL REQUIREMENT: | JIV42: =JJA29 -> 0 | JIZ42: SY | JJQ42: Page | JJR42: 1 | JJS42: of | JJT42: =$AF$33 -> 1 | JJU42: TOTAL REQUIREMENT: | JKB42: =JKG29 -> 0 | JKF42: SY | JKW42: Page | JKX42: 1 | JKY42: of | JKZ42: =$AF$33 -> 1 | JLA42: TOTAL REQUIREMENT: | JLH42: =JLM29 -> 0 | JLL42: SY | JMC42: Page | JMD42: 1 | JME42: of | JMF42: =$AF$33 -> 1 | JMG42: TOTAL REQUIREMENT: | JMN42: =JMS29 -> 0 | JMR42: SY | JNI42: Page | JNJ42: 1 | JNK42: of | JNL42: =$AF$33 -> 1 | JNM42: TOTAL REQUIREMENT: | JNT42: =JNY29 -> 0 | JNX42: SY | JOO42: Page | JOP42: 1 | JOQ42: of | JOR42: =$AF$33 -> 1 | JOS42: TOTAL REQUIREMENT: | JOZ42: =JPE29 -> 0 | JPD42: SY | JPU42: Page | JPV42: 1 | JPW42: of | JPX42: =$AF$33 -> 1 | JPY42: TOTAL REQUIREMENT: | JQF42: =JQK29 -> 0 | JQJ42: SY | JRA42: Page | JRB42: 1 | JRC42: of | JRD42: =$AF$33 -> 1 | JRE42: TOTAL REQUIREMENT: | JRL42: =JRQ29 -> 0 | JRP42: SY | JSG42: Page | JSH42: 1 | JSI42: of | JSJ42: =$AF$33 -> 1 | JSK42: TOTAL REQUIREMENT: | JSR42: =JSW29 -> 0 | JSV42: SY | JTM42: Page | JTN42: 1 | JTO42: of | JTP42: =$AF$33 -> 1 | JTQ42: TOTAL REQUIREMENT: | JTX42: =JUC29 -> 0 | JUB42: SY | JUS42: Page | JUT42: 1 | JUU42: of | JUV42: =$AF$33 -> 1 | JUW42: TOTAL REQUIREMENT: | JVD42: =JVI29 -> 0 | JVH42: SY | JVY42: Page | JVZ42: 1 | JWA42: of | JWB42: =$AF$33 -> 1 | JWC42: TOTAL REQUIREMENT: | JWJ42: =JWO29 -> 0 | JWN42: SY | JXE42: Page | JXF42: 1 | JXG42: of | JXH42: =$AF$33 -> 1 | JXI42: TOTAL REQUIREMENT: | JXP42: =JXU29 -> 0 | JXT42: SY | JYK42: Page | JYL42: 1 | JYM42: of | JYN42: =$AF$33 -> 1 | JYO42: TOTAL REQUIREMENT: | JYV42: =JZA29 -> 0 | JYZ42: SY | JZQ42: Page | JZR42: 1 | JZS42: of | JZT42: =$AF$33 -> 1 | JZU42: TOTAL REQUIREMENT: | KAB42: =KAG29 -> 0 | KAF42: SY | KAW42: Page | KAX42: 1 | KAY42: of | KAZ42: =$AF$33 -> 1 | KBA42: TOTAL REQUIREMENT: | KBH42: =KBM29 -> 0 | KBL42: SY | KCC42: Page | KCD42: 1 | KCE42: of | KCF42: =$AF$33 -> 1 | KCG42: TOTAL REQUIREMENT: | KCN42: =KCS29 -> 0 | KCR42: SY | KDI42: Page | KDJ42: 1 | KDK42: of | KDL42: =$AF$33 -> 1 | KDM42: TOTAL REQUIREMENT: | KDT42: =KDY29 -> 0 | KDX42: SY | KEO42: Page | KEP42: 1 | KEQ42: of | KER42: =$AF$33 -> 1 | KES42: TOTAL REQUIREMENT: | KEZ42: =KFE29 -> 0 | KFD42: SY | KFU42: Page | KFV42: 1 | KFW42: of | KFX42: =$AF$33 -> 1 | KFY42: TOTAL REQUIREMENT: | KGF42: =KGK29 -> 0 | KGJ42: SY | KHA42: Page | KHB42: 1 | KHC42: of | KHD42: =$AF$33 -> 1 | KHE42: TOTAL REQUIREMENT: | KHL42: =KHQ29 -> 0 | KHP42: SY | KIG42: Page | KIH42: 1 | KII42: of | KIJ42: =$AF$33 -> 1 | KIK42: TOTAL REQUIREMENT: | KIR42: =KIW29 -> 0 | KIV42: SY | KJM42: Page | KJN42: 1 | KJO42: of | KJP42: =$AF$33 -> 1 | KJQ42: TOTAL REQUIREMENT: | KJX42: =KKC29 -> 0 | KKB42: SY | KKS42: Page | KKT42: 1 | KKU42: of | KKV42: =$AF$33 -> 1 | KKW42: TOTAL REQUIREMENT: | KLD42: =KLI29 -> 0 | KLH42: SY | KLY42: Page | KLZ42: 1 | KMA42: of | KMB42: =$AF$33 -> 1 | KMC42: TOTAL REQUIREMENT: | KMJ42: =KMO29 -> 0 | KMN42: SY | KNE42: Page | KNF42: 1 | KNG42: of | KNH42: =$AF$33 -> 1 | KNI42: TOTAL REQUIREMENT: | KNP42: =KNU29 -> 0 | KNT42: SY | KOK42: Page | KOL42: 1 | KOM42: of | KON42: =$AF$33 -> 1 | KOO42: TOTAL REQUIREMENT: | KOV42: =KPA29 -> 0 | KOZ42: SY | KPQ42: Page | KPR42: 1 | KPS42: of | KPT42: =$AF$33 -> 1 | KPU42: TOTAL REQUIREMENT: | KQB42: =KQG29 -> 0 | KQF42: SY | KQW42: Page | KQX42: 1 | KQY42: of | KQZ42: =$AF$33 -> 1 | KRA42: TOTAL REQUIREMENT: | KRH42: =KRM29 -> 0 | KRL42: SY | KSC42: Page | KSD42: 1 | KSE42: of | KSF42: =$AF$33 -> 1 | KSG42: TOTAL REQUIREMENT: | KSN42: =KSS29 -> 0 | KSR42: SY | KTI42: Page | KTJ42: 1 | KTK42: of | KTL42: =$AF$33 -> 1 | KTM42: TOTAL REQUIREMENT: | KTT42: =KTY29 -> 0 | KTX42: SY | KUO42: Page | KUP42: 1 | KUQ42: of | KUR42: =$AF$33 -> 1 | KUS42: TOTAL REQUIREMENT: | KUZ42: =KVE29 -> 0 | KVD42: SY | KVU42: Page | KVV42: 1 | KVW42: of | KVX42: =$AF$33 -> 1 | KVY42: TOTAL REQUIREMENT: | KWF42: =KWK29 -> 0 | KWJ42: SY | KXA42: Page | KXB42: 1 | KXC42: of | KXD42: =$AF$33 -> 1 | KXE42: TOTAL REQUIREMENT: | KXL42: =KXQ29 -> 0 | KXP42: SY | KYG42: Page | KYH42: 1 | KYI42: of | KYJ42: =$AF$33 -> 1 | KYK42: TOTAL REQUIREMENT: | KYR42: =KYW29 -> 0 | KYV42: SY | KZM42: Page | KZN42: 1 | KZO42: of | KZP42: =$AF$33 -> 1 | KZQ42: TOTAL REQUIREMENT: | KZX42: =LAC29 -> 0 | LAB42: SY | LAS42: Page | LAT42: 1 | LAU42: of | LAV42: =$AF$33 -> 1 | LAW42: TOTAL REQUIREMENT: | LBD42: =LBI29 -> 0 | LBH42: SY | LBY42: Page | LBZ42: 1 | LCA42: of | LCB42: =$AF$33 -> 1 | LCC42: TOTAL REQUIREMENT: | LCJ42: =LCO29 -> 0 | LCN42: SY | LDE42: Page | LDF42: 1 | LDG42: of | LDH42: =$AF$33 -> 1 | LDI42: TOTAL REQUIREMENT: | LDP42: =LDU29 -> 0 | LDT42: SY | LEK42: Page | LEL42: 1 | LEM42: of | LEN42: =$AF$33 -> 1 | LEO42: TOTAL REQUIREMENT: | LEV42: =LFA29 -> 0 | LEZ42: SY | LFQ42: Page | LFR42: 1 | LFS42: of | LFT42: =$AF$33 -> 1 | LFU42: TOTAL REQUIREMENT: | LGB42: =LGG29 -> 0 | LGF42: SY | LGW42: Page | LGX42: 1 | LGY42: of | LGZ42: =$AF$33 -> 1 | LHA42: TOTAL REQUIREMENT: | LHH42: =LHM29 -> 0 | LHL42: SY | LIC42: Page | LID42: 1 | LIE42: of | LIF42: =$AF$33 -> 1 | LIG42: TOTAL REQUIREMENT: | LIN42: =LIS29 -> 0 | LIR42: SY | LJI42: Page | LJJ42: 1 | LJK42: of | LJL42: =$AF$33 -> 1 | LJM42: TOTAL REQUIREMENT: | LJT42: =LJY29 -> 0 | LJX42: SY | LKO42: Page | LKP42: 1 | LKQ42: of | LKR42: =$AF$33 -> 1 | LKS42: TOTAL REQUIREMENT: | LKZ42: =LLE29 -> 0 | LLD42: SY | LLU42: Page | LLV42: 1 | LLW42: of | LLX42: =$AF$33 -> 1 | LLY42: TOTAL REQUIREMENT: | LMF42: =LMK29 -> 0 | LMJ42: SY | LNA42: Page | LNB42: 1 | LNC42: of | LND42: =$AF$33 -> 1 | LNE42: TOTAL REQUIREMENT: | LNL42: =LNQ29 -> 0 | LNP42: SY | LOG42: Page | LOH42: 1 | LOI42: of | LOJ42: =$AF$33 -> 1 | LOK42: TOTAL REQUIREMENT: | LOR42: =LOW29 -> 0 | LOV42: SY | LPM42: Page | LPN42: 1 | LPO42: of | LPP42: =$AF$33 -> 1 | LPQ42: TOTAL REQUIREMENT: | LPX42: =LQC29 -> 0 | LQB42: SY | LQS42: Page | LQT42: 1 | LQU42: of | LQV42: =$AF$33 -> 1 | LQW42: TOTAL REQUIREMENT: | LRD42: =LRI29 -> 0 | LRH42: SY | LRY42: Page | LRZ42: 1 | LSA42: of | LSB42: =$AF$33 -> 1 | LSC42: TOTAL REQUIREMENT: | LSJ42: =LSO29 -> 0 | LSN42: SY | LTE42: Page | LTF42: 1 | LTG42: of | LTH42: =$AF$33 -> 1 | LTI42: TOTAL REQUIREMENT: | LTP42: =LTU29 -> 0 | LTT42: SY | LUK42: Page | LUL42: 1 | LUM42: of | LUN42: =$AF$33 -> 1 | LUO42: TOTAL REQUIREMENT: | LUV42: =LVA29 -> 0 | LUZ42: SY | LVQ42: Page | LVR42: 1 | LVS42: of | LVT42: =$AF$33 -> 1 | LVU42: TOTAL REQUIREMENT: | LWB42: =LWG29 -> 0 | LWF42: SY | LWW42: Page | LWX42: 1 | LWY42: of | LWZ42: =$AF$33 -> 1 | LXA42: TOTAL REQUIREMENT: | LXH42: =LXM29 -> 0 | LXL42: SY | LYC42: Page | LYD42: 1 | LYE42: of | LYF42: =$AF$33 -> 1 | LYG42: TOTAL REQUIREMENT: | LYN42: =LYS29 -> 0 | LYR42: SY | LZI42: Page | LZJ42: 1 | LZK42: of | LZL42: =$AF$33 -> 1 | LZM42: TOTAL REQUIREMENT: | LZT42: =LZY29 -> 0 | LZX42: SY | MAO42: Page | MAP42: 1 | MAQ42: of | MAR42: =$AF$33 -> 1 | MAS42: TOTAL REQUIREMENT: | MAZ42: =MBE29 -> 0 | MBD42: SY | MBU42: Page | MBV42: 1 | MBW42: of | MBX42: =$AF$33 -> 1 | MBY42: TOTAL REQUIREMENT: | MCF42: =MCK29 -> 0 | MCJ42: SY | MDA42: Page | MDB42: 1 | MDC42: of | MDD42: =$AF$33 -> 1 | MDE42: TOTAL REQUIREMENT: | MDL42: =MDQ29 -> 0 | MDP42: SY | MEG42: Page | MEH42: 1 | MEI42: of | MEJ42: =$AF$33 -> 1 | MEK42: TOTAL REQUIREMENT: | MER42: =MEW29 -> 0 | MEV42: SY | MFM42: Page | MFN42: 1 | MFO42: of | MFP42: =$AF$33 -> 1 | MFQ42: TOTAL REQUIREMENT: | MFX42: =MGC29 -> 0 | MGB42: SY | MGS42: Page | MGT42: 1 | MGU42: of | MGV42: =$AF$33 -> 1 | MGW42: TOTAL REQUIREMENT: | MHD42: =MHI29 -> 0 | MHH42: SY | MHY42: Page | MHZ42: 1 | MIA42: of | MIB42: =$AF$33 -> 1 | MIC42: TOTAL REQUIREMENT: | MIJ42: =MIO29 -> 0 | MIN42: SY | MJE42: Page | MJF42: 1 | MJG42: of | MJH42: =$AF$33 -> 1 | MJI42: TOTAL REQUIREMENT: | MJP42: =MJU29 -> 0 | MJT42: SY | MKK42: Page | MKL42: 1 | MKM42: of | MKN42: =$AF$33 -> 1 | MKO42: TOTAL REQUIREMENT: | MKV42: =MLA29 -> 0 | MKZ42: SY | MLQ42: Page | MLR42: 1 | MLS42: of | MLT42: =$AF$33 -> 1 | MLU42: TOTAL REQUIREMENT: | MMB42: =MMG29 -> 0 | MMF42: SY | MMW42: Page | MMX42: 1 | MMY42: of | MMZ42: =$AF$33 -> 1 | MNA42: TOTAL REQUIREMENT: | MNH42: =MNM29 -> 0 | MNL42: SY | MOC42: Page | MOD42: 1 | MOE42: of | MOF42: =$AF$33 -> 1 | MOG42: TOTAL REQUIREMENT: | MON42: =MOS29 -> 0 | MOR42: SY | MPI42: Page | MPJ42: 1 | MPK42: of | MPL42: =$AF$33 -> 1 | MPM42: TOTAL REQUIREMENT: | MPT42: =MPY29 -> 0 | MPX42: SY | MQO42: Page | MQP42: 1 | MQQ42: of | MQR42: =$AF$33 -> 1 | MQS42: TOTAL REQUIREMENT: | MQZ42: =MRE29 -> 0 | MRD42: SY | MRU42: Page | MRV42: 1 | MRW42: of | MRX42: =$AF$33 -> 1 | MRY42: TOTAL REQUIREMENT: | MSF42: =MSK29 -> 0 | MSJ42: SY | MTA42: Page | MTB42: 1 | MTC42: of | MTD42: =$AF$33 -> 1 | MTE42: TOTAL REQUIREMENT: | MTL42: =MTQ29 -> 0 | MTP42: SY | MUG42: Page | MUH42: 1 | MUI42: of | MUJ42: =$AF$33 -> 1 | MUK42: TOTAL REQUIREMENT: | MUR42: =MUW29 -> 0 | MUV42: SY | MVM42: Page | MVN42: 1 | MVO42: of | MVP42: =$AF$33 -> 1 | MVQ42: TOTAL REQUIREMENT: | MVX42: =MWC29 -> 0 | MWB42: SY | MWS42: Page | MWT42: 1 | MWU42: of | MWV42: =$AF$33 -> 1 | MWW42: TOTAL REQUIREMENT: | MXD42: =MXI29 -> 0 | MXH42: SY | MXY42: Page | MXZ42: 1 | MYA42: of | MYB42: =$AF$33 -> 1 | MYC42: TOTAL REQUIREMENT: | MYJ42: =MYO29 -> 0 | MYN42: SY | MZE42: Page | MZF42: 1 | MZG42: of | MZH42: =$AF$33 -> 1 | MZI42: TOTAL REQUIREMENT: | MZP42: =MZU29 -> 0 | MZT42: SY | NAK42: Page | NAL42: 1 | NAM42: of | NAN42: =$AF$33 -> 1 | NAO42: TOTAL REQUIREMENT: | NAV42: =NBA29 -> 0 | NAZ42: SY | NBQ42: Page | NBR42: 1 | NBS42: of | NBT42: =$AF$33 -> 1 | NBU42: TOTAL REQUIREMENT: | NCB42: =NCG29 -> 0 | NCF42: SY | NCW42: Page | NCX42: 1 | NCY42: of | NCZ42: =$AF$33 -> 1 | NDA42: TOTAL REQUIREMENT: | NDH42: =NDM29 -> 0 | NDL42: SY | NEC42: Page | NED42: 1 | NEE42: of | NEF42: =$AF$33 -> 1 | NEG42: TOTAL REQUIREMENT: | NEN42: =NES29 -> 0 | NER42: SY | NFI42: Page | NFJ42: 1 | NFK42: of | NFL42: =$AF$33 -> 1 | NFM42: TOTAL REQUIREMENT: | NFT42: =NFY29 -> 0 | NFX42: SY | NGO42: Page | NGP42: 1 | NGQ42: of | NGR42: =$AF$33 -> 1 | NGS42: TOTAL REQUIREMENT: | NGZ42: =NHE29 -> 0 | NHD42: SY | NHU42: Page | NHV42: 1 | NHW42: of | NHX42: =$AF$33 -> 1 | NHY42: TOTAL REQUIREMENT: | NIF42: =NIK29 -> 0 | NIJ42: SY | NJA42: Page | NJB42: 1 | NJC42: of | NJD42: =$AF$33 -> 1 | NJE42: TOTAL REQUIREMENT: | NJL42: =NJQ29 -> 0 | NJP42: SY | NKG42: Page | NKH42: 1 | NKI42: of | NKJ42: =$AF$33 -> 1 | NKK42: TOTAL REQUIREMENT: | NKR42: =NKW29 -> 0 | NKV42: SY | NLM42: Page | NLN42: 1 | NLO42: of | NLP42: =$AF$33 -> 1 | NLQ42: TOTAL REQUIREMENT: | NLX42: =NMC29 -> 0 | NMB42: SY | NMS42: Page | NMT42: 1 | NMU42: of | NMV42: =$AF$33 -> 1 | NMW42: TOTAL REQUIREMENT: | NND42: =NNI29 -> 0 | NNH42: SY | NNY42: Page | NNZ42: 1 | NOA42: of | NOB42: =$AF$33 -> 1 | NOC42: TOTAL REQUIREMENT: | NOJ42: =NOO29 -> 0 | NON42: SY | NPE42: Page | NPF42: 1 | NPG42: of | NPH42: =$AF$33 -> 1 | NPI42: TOTAL REQUIREMENT: | NPP42: =NPU29 -> 0 | NPT42: SY | NQK42: Page | NQL42: 1 | NQM42: of | NQN42: =$AF$33 -> 1 | NQO42: TOTAL REQUIREMENT: | NQV42: =NRA29 -> 0 | NQZ42: SY | NRQ42: Page | NRR42: 1 | NRS42: of | NRT42: =$AF$33 -> 1 | NRU42: TOTAL REQUIREMENT: | NSB42: =NSG29 -> 0 | NSF42: SY | NSW42: Page | NSX42: 1 | NSY42: of | NSZ42: =$AF$33 -> 1 | NTA42: TOTAL REQUIREMENT: | NTH42: =NTM29 -> 0 | NTL42: SY | NUC42: Page | NUD42: 1 | NUE42: of | NUF42: =$AF$33 -> 1 | NUG42: TOTAL REQUIREMENT: | NUN42: =NUS29 -> 0 | NUR42: SY | NVI42: Page | NVJ42: 1 | NVK42: of | NVL42: =$AF$33 -> 1 | NVM42: TOTAL REQUIREMENT: | NVT42: =NVY29 -> 0 | NVX42: SY | NWO42: Page | NWP42: 1 | NWQ42: of | NWR42: =$AF$33 -> 1 | NWS42: TOTAL REQUIREMENT: | NWZ42: =NXE29 -> 0 | NXD42: SY | NXU42: Page | NXV42: 1 | NXW42: of | NXX42: =$AF$33 -> 1 | NXY42: TOTAL REQUIREMENT: | NYF42: =NYK29 -> 0 | NYJ42: SY | NZA42: Page | NZB42: 1 | NZC42: of | NZD42: =$AF$33 -> 1 | NZE42: TOTAL REQUIREMENT: | NZL42: =NZQ29 -> 0 | NZP42: SY | OAG42: Page | OAH42: 1 | OAI42: of | OAJ42: =$AF$33 -> 1 | OAK42: TOTAL REQUIREMENT: | OAR42: =OAW29 -> 0 | OAV42: SY | OBM42: Page | OBN42: 1 | OBO42: of | OBP42: =$AF$33 -> 1 | OBQ42: TOTAL REQUIREMENT: | OBX42: =OCC29 -> 0 | OCB42: SY | OCS42: Page | OCT42: 1 | OCU42: of | OCV42: =$AF$33 -> 1 | OCW42: TOTAL REQUIREMENT: | ODD42: =ODI29 -> 0 | ODH42: SY | ODY42: Page | ODZ42: 1 | OEA42: of | OEB42: =$AF$33 -> 1 | OEC42: TOTAL REQUIREMENT: | OEJ42: =OEO29 -> 0 | OEN42: SY | OFE42: Page | OFF42: 1 | OFG42: of | OFH42: =$AF$33 -> 1 | OFI42: TOTAL REQUIREMENT: | OFP42: =OFU29 -> 0 | OFT42: SY | OGK42: Page | OGL42: 1 | OGM42: of | OGN42: =$AF$33 -> 1 | OGO42: TOTAL REQUIREMENT: | OGV42: =OHA29 -> 0 | OGZ42: SY | OHQ42: Page | OHR42: 1 | OHS42: of | OHT42: =$AF$33 -> 1 | OHU42: TOTAL REQUIREMENT: | OIB42: =OIG29 -> 0 | OIF42: SY | OIW42: Page | OIX42: 1 | OIY42: of | OIZ42: =$AF$33 -> 1 | OJA42: TOTAL REQUIREMENT: | OJH42: =OJM29 -> 0 | OJL42: SY | OKC42: Page | OKD42: 1 | OKE42: of | OKF42: =$AF$33 -> 1 | OKG42: TOTAL REQUIREMENT: | OKN42: =OKS29 -> 0 | OKR42: SY | OLI42: Page | OLJ42: 1 | OLK42: of | OLL42: =$AF$33 -> 1 | OLM42: TOTAL REQUIREMENT: | OLT42: =OLY29 -> 0 | OLX42: SY | OMO42: Page | OMP42: 1 | OMQ42: of | OMR42: =$AF$33 -> 1 | OMS42: TOTAL REQUIREMENT: | OMZ42: =ONE29 -> 0 | OND42: SY | ONU42: Page | ONV42: 1 | ONW42: of | ONX42: =$AF$33 -> 1 | ONY42: TOTAL REQUIREMENT: | OOF42: =OOK29 -> 0 | OOJ42: SY | OPA42: Page | OPB42: 1 | OPC42: of | OPD42: =$AF$33 -> 1 | OPE42: TOTAL REQUIREMENT: | OPL42: =OPQ29 -> 0 | OPP42: SY | OQG42: Page | OQH42: 1 | OQI42: of | OQJ42: =$AF$33 -> 1 | OQK42: TOTAL REQUIREMENT: | OQR42: =OQW29 -> 0 | OQV42: SY | ORM42: Page | ORN42: 1 | ORO42: of | ORP42: =$AF$33 -> 1 | ORQ42: TOTAL REQUIREMENT: | ORX42: =OSC29 -> 0 | OSB42: SY | OSS42: Page | OST42: 1 | OSU42: of | OSV42: =$AF$33 -> 1 | OSW42: TOTAL REQUIREMENT: | OTD42: =OTI29 -> 0 | OTH42: SY | OTY42: Page | OTZ42: 1 | OUA42: of | OUB42: =$AF$33 -> 1 | OUC42: TOTAL REQUIREMENT: | OUJ42: =OUO29 -> 0 | OUN42: SY | OVE42: Page | OVF42: 1 | OVG42: of | OVH42: =$AF$33 -> 1 | OVI42: TOTAL REQUIREMENT: | OVP42: =OVU29 -> 0 | OVT42: SY | OWK42: Page | OWL42: 1 | OWM42: of | OWN42: =$AF$33 -> 1 | OWO42: TOTAL REQUIREMENT: | OWV42: =OXA29 -> 0 | OWZ42: SY | OXQ42: Page | OXR42: 1 | OXS42: of | OXT42: =$AF$33 -> 1 | OXU42: TOTAL REQUIREMENT: | OYB42: =OYG29 -> 0 | OYF42: SY | OYW42: Page | OYX42: 1 | OYY42: of | OYZ42: =$AF$33 -> 1 | OZA42: TOTAL REQUIREMENT: | OZH42: =OZM29 -> 0 | OZL42: SY | PAC42: Page | PAD42: 1 | PAE42: of | PAF42: =$AF$33 -> 1 | PAG42: TOTAL REQUIREMENT: | PAN42: =PAS29 -> 0 | PAR42: SY | PBI42: Page | PBJ42: 1 | PBK42: of | PBL42: =$AF$33 -> 1 | PBM42: TOTAL REQUIREMENT: | PBT42: =PBY29 -> 0 | PBX42: SY | PCO42: Page | PCP42: 1 | PCQ42: of | PCR42: =$AF$33 -> 1 | PCS42: TOTAL REQUIREMENT: | PCZ42: =PDE29 -> 0 | PDD42: SY | PDU42: Page | PDV42: 1 | PDW42: of | PDX42: =$AF$33 -> 1 | PDY42: TOTAL REQUIREMENT: | PEF42: =PEK29 -> 0 | PEJ42: SY | PFA42: Page | PFB42: 1 | PFC42: of | PFD42: =$AF$33 -> 1 | PFE42: TOTAL REQUIREMENT: | PFL42: =PFQ29 -> 0 | PFP42: SY | PGG42: Page | PGH42: 1 | PGI42: of | PGJ42: =$AF$33 -> 1 | PGK42: TOTAL REQUIREMENT: | PGR42: =PGW29 -> 0 | PGV42: SY | PHM42: Page | PHN42: 1 | PHO42: of | PHP42: =$AF$33 -> 1 | PHQ42: TOTAL REQUIREMENT: | PHX42: =PIC29 -> 0 | PIB42: SY | PIS42: Page | PIT42: 1 | PIU42: of | PIV42: =$AF$33 -> 1 | PIW42: TOTAL REQUIREMENT: | PJD42: =PJI29 -> 0 | PJH42: SY | PJY42: Page | PJZ42: 1 | PKA42: of | PKB42: =$AF$33 -> 1 | PKC42: TOTAL REQUIREMENT: | PKJ42: =PKO29 -> 0 | PKN42: SY | PLE42: Page | PLF42: 1 | PLG42: of | PLH42: =$AF$33 -> 1 | PLI42: TOTAL REQUIREMENT: | PLP42: =PLU29 -> 0 | PLT42: SY | PMK42: Page | PML42: 1 | PMM42: of | PMN42: =$AF$33 -> 1 | PMO42: TOTAL REQUIREMENT: | PMV42: =PNA29 -> 0 | PMZ42: SY | PNQ42: Page | PNR42: 1 | PNS42: of | PNT42: =$AF$33 -> 1 | PNU42: TOTAL REQUIREMENT: | POB42: =POG29 -> 0 | POF42: SY | POW42: Page | POX42: 1 | POY42: of | POZ42: =$AF$33 -> 1 | PPA42: TOTAL REQUIREMENT: | PPH42: =PPM29 -> 0 | PPL42: SY | PQC42: Page | PQD42: 1 | PQE42: of | PQF42: =$AF$33 -> 1 | PQG42: TOTAL REQUIREMENT: | PQN42: =PQS29 -> 0 | PQR42: SY | PRI42: Page | PRJ42: 1 | PRK42: of | PRL42: =$AF$33 -> 1 | PRM42: TOTAL REQUIREMENT: | PRT42: =PRY29 -> 0 | PRX42: SY | PSO42: Page | PSP42: 1 | PSQ42: of | PSR42: =$AF$33 -> 1 | PSS42: TOTAL REQUIREMENT: | PSZ42: =PTE29 -> 0 | PTD42: SY | PTU42: Page | PTV42: 1 | PTW42: of | PTX42: =$AF$33 -> 1 | PTY42: TOTAL REQUIREMENT: | PUF42: =PUK29 -> 0 | PUJ42: SY | PVA42: Page | PVB42: 1 | PVC42: of | PVD42: =$AF$33 -> 1 | PVE42: TOTAL REQUIREMENT: | PVL42: =PVQ29 -> 0 | PVP42: SY | PWG42: Page | PWH42: 1 | PWI42: of | PWJ42: =$AF$33 -> 1 | PWK42: TOTAL REQUIREMENT: | PWR42: =PWW29 -> 0 | PWV42: SY | PXM42: Page | PXN42: 1 | PXO42: of | PXP42: =$AF$33 -> 1 | PXQ42: TOTAL REQUIREMENT: | PXX42: =PYC29 -> 0 | PYB42: SY | PYS42: Page | PYT42: 1 | PYU42: of | PYV42: =$AF$33 -> 1 | PYW42: TOTAL REQUIREMENT: | PZD42: =PZI29 -> 0 | PZH42: SY | PZY42: Page | PZZ42: 1 | QAA42: of | QAB42: =$AF$33 -> 1 | QAC42: TOTAL REQUIREMENT: | QAJ42: =QAO29 -> 0 | QAN42: SY | QBE42: Page | QBF42: 1 | QBG42: of | QBH42: =$AF$33 -> 1 | QBI42: TOTAL REQUIREMENT: | QBP42: =QBU29 -> 0 | QBT42: SY | QCK42: Page | QCL42: 1 | QCM42: of | QCN42: =$AF$33 -> 1 | QCO42: TOTAL REQUIREMENT: | QCV42: =QDA29 -> 0 | QCZ42: SY | QDQ42: Page | QDR42: 1 | QDS42: of | QDT42: =$AF$33 -> 1 | QDU42: TOTAL REQUIREMENT: | QEB42: =QEG29 -> 0 | QEF42: SY | QEW42: Page | QEX42: 1 | QEY42: of | QEZ42: =$AF$33 -> 1 | QFA42: TOTAL REQUIREMENT: | QFH42: =QFM29 -> 0 | QFL42: SY | QGC42: Page | QGD42: 1 | QGE42: of | QGF42: =$AF$33 -> 1 | QGG42: TOTAL REQUIREMENT: | QGN42: =QGS29 -> 0 | QGR42: SY | QHI42: Page | QHJ42: 1 | QHK42: of | QHL42: =$AF$33 -> 1 | QHM42: TOTAL REQUIREMENT: | QHT42: =QHY29 -> 0 | QHX42: SY | QIO42: Page | QIP42: 1 | QIQ42: of | QIR42: =$AF$33 -> 1 | QIS42: TOTAL REQUIREMENT: | QIZ42: =QJE29 -> 0 | QJD42: SY | QJU42: Page | QJV42: 1 | QJW42: of | QJX42: =$AF$33 -> 1 | QJY42: TOTAL REQUIREMENT: | QKF42: =QKK29 -> 0 | QKJ42: SY | QLA42: Page | QLB42: 1 | QLC42: of | QLD42: =$AF$33 -> 1 | QLE42: TOTAL REQUIREMENT: | QLL42: =QLQ29 -> 0 | QLP42: SY | QMG42: Page | QMH42: 1 | QMI42: of | QMJ42: =$AF$33 -> 1 | QMK42: TOTAL REQUIREMENT: | QMR42: =QMW29 -> 0 | QMV42: SY | QNM42: Page | QNN42: 1 | QNO42: of | QNP42: =$AF$33 -> 1 | QNQ42: TOTAL REQUIREMENT: | QNX42: =QOC29 -> 0 | QOB42: SY | QOS42: Page | QOT42: 1 | QOU42: of | QOV42: =$AF$33 -> 1 | QOW42: TOTAL REQUIREMENT: | QPD42: =QPI29 -> 0 | QPH42: SY | QPY42: Page | QPZ42: 1 | QQA42: of | QQB42: =$AF$33 -> 1 | QQC42: TOTAL REQUIREMENT: | QQJ42: =QQO29 -> 0 | QQN42: SY | QRE42: Page | QRF42: 1 | QRG42: of | QRH42: =$AF$33 -> 1 | QRI42: TOTAL REQUIREMENT: | QRP42: =QRU29 -> 0 | QRT42: SY | QSK42: Page | QSL42: 1 | QSM42: of | QSN42: =$AF$33 -> 1 | QSO42: TOTAL REQUIREMENT: | QSV42: =QTA29 -> 0 | QSZ42: SY | QTQ42: Page | QTR42: 1 | QTS42: of | QTT42: =$AF$33 -> 1 | QTU42: TOTAL REQUIREMENT: | QUB42: =QUG29 -> 0 | QUF42: SY | QUW42: Page | QUX42: 1 | QUY42: of | QUZ42: =$AF$33 -> 1 | QVA42: TOTAL REQUIREMENT: | QVH42: =QVM29 -> 0 | QVL42: SY | QWC42: Page | QWD42: 1 | QWE42: of | QWF42: =$AF$33 -> 1 | QWG42: TOTAL REQUIREMENT: | QWN42: =QWS29 -> 0 | QWR42: SY | QXI42: Page | QXJ42: 1 | QXK42: of | QXL42: =$AF$33 -> 1 | QXM42: TOTAL REQUIREMENT: | QXT42: =QXY29 -> 0 | QXX42: SY | QYO42: Page | QYP42: 1 | QYQ42: of | QYR42: =$AF$33 -> 1 | QYS42: TOTAL REQUIREMENT: | QYZ42: =QZE29 -> 0 | QZD42: SY | QZU42: Page | QZV42: 1 | QZW42: of | QZX42: =$AF$33 -> 1 | QZY42: TOTAL REQUIREMENT: | RAF42: =RAK29 -> 0 | RAJ42: SY | RBA42: Page | RBB42: 1 | RBC42: of | RBD42: =$AF$33 -> 1 | RBE42: TOTAL REQUIREMENT: | RBL42: =RBQ29 -> 0 | RBP42: SY | RCG42: Page | RCH42: 1 | RCI42: of | RCJ42: =$AF$33 -> 1 | RCK42: TOTAL REQUIREMENT: | RCR42: =RCW29 -> 0 | RCV42: SY | RDM42: Page | RDN42: 1 | RDO42: of | RDP42: =$AF$33 -> 1 | RDQ42: TOTAL REQUIREMENT: | RDX42: =REC29 -> 0 | REB42: SY | RES42: Page | RET42: 1 | REU42: of | REV42: =$AF$33 -> 1 | REW42: TOTAL REQUIREMENT: | RFD42: =RFI29 -> 0 | RFH42: SY | RFY42: Page | RFZ42: 1 | RGA42: of | RGB42: =$AF$33 -> 1 | RGC42: TOTAL REQUIREMENT: | RGJ42: =RGO29 -> 0 | RGN42: SY | RHE42: Page | RHF42: 1 | RHG42: of | RHH42: =$AF$33 -> 1 | RHI42: TOTAL REQUIREMENT: | RHP42: =RHU29 -> 0 | RHT42: SY | RIK42: Page | RIL42: 1 | RIM42: of | RIN42: =$AF$33 -> 1 | RIO42: TOTAL REQUIREMENT: | RIV42: =RJA29 -> 0 | RIZ42: SY | RJQ42: Page | RJR42: 1 | RJS42: of | RJT42: =$AF$33 -> 1 | RJU42: TOTAL REQUIREMENT: | RKB42: =RKG29 -> 0 | RKF42: SY | RKW42: Page | RKX42: 1 | RKY42: of | RKZ42: =$AF$33 -> 1 | RLA42: TOTAL REQUIREMENT: | RLH42: =RLM29 -> 0 | RLL42: SY | RMC42: Page | RMD42: 1 | RME42: of | RMF42: =$AF$33 -> 1 | RMG42: TOTAL REQUIREMENT: | RMN42: =RMS29 -> 0 | RMR42: SY | RNI42: Page | RNJ42: 1 | RNK42: of | RNL42: =$AF$33 -> 1 | RNM42: TOTAL REQUIREMENT: | RNT42: =RNY29 -> 0 | RNX42: SY | ROO42: Page | ROP42: 1 | ROQ42: of | ROR42: =$AF$33 -> 1 | ROS42: TOTAL REQUIREMENT: | ROZ42: =RPE29 -> 0 | RPD42: SY | RPU42: Page | RPV42: 1 | RPW42: of | RPX42: =$AF$33 -> 1 | RPY42: TOTAL REQUIREMENT: | RQF42: =RQK29 -> 0 | RQJ42: SY | RRA42: Page | RRB42: 1 | RRC42: of | RRD42: =$AF$33 -> 1 | RRE42: TOTAL REQUIREMENT: | RRL42: =RRQ29 -> 0 | RRP42: SY | RSG42: Page | RSH42: 1 | RSI42: of | RSJ42: =$AF$33 -> 1 | RSK42: TOTAL REQUIREMENT: | RSR42: =RSW29 -> 0 | RSV42: SY | RTM42: Page | RTN42: 1 | RTO42: of | RTP42: =$AF$33 -> 1 | RTQ42: TOTAL REQUIREMENT: | RTX42: =RUC29 -> 0 | RUB42: SY | RUS42: Page | RUT42: 1 | RUU42: of | RUV42: =$AF$33 -> 1 | RUW42: TOTAL REQUIREMENT: | RVD42: =RVI29 -> 0 | RVH42: SY | RVY42: Page | RVZ42: 1 | RWA42: of | RWB42: =$AF$33 -> 1 | RWC42: TOTAL REQUIREMENT: | RWJ42: =RWO29 -> 0 | RWN42: SY | RXE42: Page | RXF42: 1 | RXG42: of | RXH42: =$AF$33 -> 1 | RXI42: TOTAL REQUIREMENT: | RXP42: =RXU29 -> 0 | RXT42: SY | RYK42: Page | RYL42: 1 | RYM42: of | RYN42: =$AF$33 -> 1 | RYO42: TOTAL REQUIREMENT: | RYV42: =RZA29 -> 0 | RYZ42: SY | RZQ42: Page | RZR42: 1 | RZS42: of | RZT42: =$AF$33 -> 1 | RZU42: TOTAL REQUIREMENT: | SAB42: =SAG29 -> 0 | SAF42: SY | SAW42: Page | SAX42: 1 | SAY42: of | SAZ42: =$AF$33 -> 1 | SBA42: TOTAL REQUIREMENT: | SBH42: =SBM29 -> 0 | SBL42: SY | SCC42: Page | SCD42: 1 | SCE42: of | SCF42: =$AF$33 -> 1 | SCG42: TOTAL REQUIREMENT: | SCN42: =SCS29 -> 0 | SCR42: SY | SDI42: Page | SDJ42: 1 | SDK42: of | SDL42: =$AF$33 -> 1 | SDM42: TOTAL REQUIREMENT: | SDT42: =SDY29 -> 0 | SDX42: SY | SEO42: Page | SEP42: 1 | SEQ42: of | SER42: =$AF$33 -> 1 | SES42: TOTAL REQUIREMENT: | SEZ42: =SFE29 -> 0 | SFD42: SY | SFU42: Page | SFV42: 1 | SFW42: of | SFX42: =$AF$33 -> 1 | SFY42: TOTAL REQUIREMENT: | SGF42: =SGK29 -> 0 | SGJ42: SY | SHA42: Page | SHB42: 1 | SHC42: of | SHD42: =$AF$33 -> 1 | SHE42: TOTAL REQUIREMENT: | SHL42: =SHQ29 -> 0 | SHP42: SY | SIG42: Page | SIH42: 1 | SII42: of | SIJ42: =$AF$33 -> 1 | SIK42: TOTAL REQUIREMENT: | SIR42: =SIW29 -> 0 | SIV42: SY | SJM42: Page | SJN42: 1 | SJO42: of | SJP42: =$AF$33 -> 1 | SJQ42: TOTAL REQUIREMENT: | SJX42: =SKC29 -> 0 | SKB42: SY | SKS42: Page | SKT42: 1 | SKU42: of | SKV42: =$AF$33 -> 1 | SKW42: TOTAL REQUIREMENT: | SLD42: =SLI29 -> 0 | SLH42: SY | SLY42: Page | SLZ42: 1 | SMA42: of | SMB42: =$AF$33 -> 1 | SMC42: TOTAL REQUIREMENT: | SMJ42: =SMO29 -> 0 | SMN42: SY | SNE42: Page | SNF42: 1 | SNG42: of | SNH42: =$AF$33 -> 1 | SNI42: TOTAL REQUIREMENT: | SNP42: =SNU29 -> 0 | SNT42: SY | SOK42: Page | SOL42: 1 | SOM42: of | SON42: =$AF$33 -> 1 | SOO42: TOTAL REQUIREMENT: | SOV42: =SPA29 -> 0 | SOZ42: SY | SPQ42: Page | SPR42: 1 | SPS42: of | SPT42: =$AF$33 -> 1 | SPU42: TOTAL REQUIREMENT: | SQB42: =SQG29 -> 0 | SQF42: SY | SQW42: Page | SQX42: 1 | SQY42: of | SQZ42: =$AF$33 -> 1 | SRA42: TOTAL REQUIREMENT: | SRH42: =SRM29 -> 0 | SRL42: SY | SSC42: Page | SSD42: 1 | SSE42: of | SSF42: =$AF$33 -> 1 | SSG42: TOTAL REQUIREMENT: | SSN42: =SSS29 -> 0 | SSR42: SY | STI42: Page | STJ42: 1 | STK42: of | STL42: =$AF$33 -> 1 | STM42: TOTAL REQUIREMENT: | STT42: =STY29 -> 0 | STX42: SY | SUO42: Page | SUP42: 1 | SUQ42: of | SUR42: =$AF$33 -> 1 | SUS42: TOTAL REQUIREMENT: | SUZ42: =SVE29 -> 0 | SVD42: SY | SVU42: Page | SVV42: 1 | SVW42: of | SVX42: =$AF$33 -> 1 | SVY42: TOTAL REQUIREMENT: | SWF42: =SWK29 -> 0 | SWJ42: SY | SXA42: Page | SXB42: 1 | SXC42: of | SXD42: =$AF$33 -> 1 | SXE42: TOTAL REQUIREMENT: | SXL42: =SXQ29 -> 0 | SXP42: SY | SYG42: Page | SYH42: 1 | SYI42: of | SYJ42: =$AF$33 -> 1 | SYK42: TOTAL REQUIREMENT: | SYR42: =SYW29 -> 0 | SYV42: SY | SZM42: Page | SZN42: 1 | SZO42: of | SZP42: =$AF$33 -> 1 | SZQ42: TOTAL REQUIREMENT: | SZX42: =TAC29 -> 0 | TAB42: SY | TAS42: Page | TAT42: 1 | TAU42: of | TAV42: =$AF$33 -> 1 | TAW42: TOTAL REQUIREMENT: | TBD42: =TBI29 -> 0 | TBH42: SY | TBY42: Page | TBZ42: 1 | TCA42: of | TCB42: =$AF$33 -> 1 | TCC42: TOTAL REQUIREMENT: | TCJ42: =TCO29 -> 0 | TCN42: SY | TDE42: Page | TDF42: 1 | TDG42: of | TDH42: =$AF$33 -> 1 | TDI42: TOTAL REQUIREMENT: | TDP42: =TDU29 -> 0 | TDT42: SY | TEK42: Page | TEL42: 1 | TEM42: of | TEN42: =$AF$33 -> 1 | TEO42: TOTAL REQUIREMENT: | TEV42: =TFA29 -> 0 | TEZ42: SY | TFQ42: Page | TFR42: 1 | TFS42: of | TFT42: =$AF$33 -> 1 | TFU42: TOTAL REQUIREMENT: | TGB42: =TGG29 -> 0 | TGF42: SY | TGW42: Page | TGX42: 1 | TGY42: of | TGZ42: =$AF$33 -> 1 | THA42: TOTAL REQUIREMENT: | THH42: =THM29 -> 0 | THL42: SY | TIC42: Page | TID42: 1 | TIE42: of | TIF42: =$AF$33 -> 1 | TIG42: TOTAL REQUIREMENT: | TIN42: =TIS29 -> 0 | TIR42: SY | TJI42: Page | TJJ42: 1 | TJK42: of | TJL42: =$AF$33 -> 1 | TJM42: TOTAL REQUIREMENT: | TJT42: =TJY29 -> 0 | TJX42: SY | TKO42: Page | TKP42: 1 | TKQ42: of | TKR42: =$AF$33 -> 1 | TKS42: TOTAL REQUIREMENT: | TKZ42: =TLE29 -> 0 | TLD42: SY | TLU42: Page | TLV42: 1 | TLW42: of | TLX42: =$AF$33 -> 1 | TLY42: TOTAL REQUIREMENT: | TMF42: =TMK29 -> 0 | TMJ42: SY | TNA42: Page | TNB42: 1 | TNC42: of | TND42: =$AF$33 -> 1 | TNE42: TOTAL REQUIREMENT: | TNL42: =TNQ29 -> 0 | TNP42: SY | TOG42: Page | TOH42: 1 | TOI42: of | TOJ42: =$AF$33 -> 1 | TOK42: TOTAL REQUIREMENT: | TOR42: =TOW29 -> 0 | TOV42: SY | TPM42: Page | TPN42: 1 | TPO42: of | TPP42: =$AF$33 -> 1 | TPQ42: TOTAL REQUIREMENT: | TPX42: =TQC29 -> 0 | TQB42: SY | TQS42: Page | TQT42: 1 | TQU42: of | TQV42: =$AF$33 -> 1 | TQW42: TOTAL REQUIREMENT: | TRD42: =TRI29 -> 0 | TRH42: SY | TRY42: Page | TRZ42: 1 | TSA42: of | TSB42: =$AF$33 -> 1 | TSC42: TOTAL REQUIREMENT: | TSJ42: =TSO29 -> 0 | TSN42: SY | TTE42: Page | TTF42: 1 | TTG42: of | TTH42: =$AF$33 -> 1 | TTI42: TOTAL REQUIREMENT: | TTP42: =TTU29 -> 0 | TTT42: SY | TUK42: Page | TUL42: 1 | TUM42: of | TUN42: =$AF$33 -> 1 | TUO42: TOTAL REQUIREMENT: | TUV42: =TVA29 -> 0 | TUZ42: SY | TVQ42: Page | TVR42: 1 | TVS42: of | TVT42: =$AF$33 -> 1 | TVU42: TOTAL REQUIREMENT: | TWB42: =TWG29 -> 0 | TWF42: SY | TWW42: Page | TWX42: 1 | TWY42: of | TWZ42: =$AF$33 -> 1 | TXA42: TOTAL REQUIREMENT: | TXH42: =TXM29 -> 0 | TXL42: SY | TYC42: Page | TYD42: 1 | TYE42: of | TYF42: =$AF$33 -> 1 | TYG42: TOTAL REQUIREMENT: | TYN42: =TYS29 -> 0 | TYR42: SY | TZI42: Page | TZJ42: 1 | TZK42: of | TZL42: =$AF$33 -> 1 | TZM42: TOTAL REQUIREMENT: | TZT42: =TZY29 -> 0 | TZX42: SY | UAO42: Page | UAP42: 1 | UAQ42: of | UAR42: =$AF$33 -> 1 | UAS42: TOTAL REQUIREMENT: | UAZ42: =UBE29 -> 0 | UBD42: SY | UBU42: Page | UBV42: 1 | UBW42: of | UBX42: =$AF$33 -> 1 | UBY42: TOTAL REQUIREMENT: | UCF42: =UCK29 -> 0 | UCJ42: SY | UDA42: Page | UDB42: 1 | UDC42: of | UDD42: =$AF$33 -> 1 | UDE42: TOTAL REQUIREMENT: | UDL42: =UDQ29 -> 0 | UDP42: SY | UEG42: Page | UEH42: 1 | UEI42: of | UEJ42: =$AF$33 -> 1 | UEK42: TOTAL REQUIREMENT: | UER42: =UEW29 -> 0 | UEV42: SY | UFM42: Page | UFN42: 1 | UFO42: of | UFP42: =$AF$33 -> 1 | UFQ42: TOTAL REQUIREMENT: | UFX42: =UGC29 -> 0 | UGB42: SY | UGS42: Page | UGT42: 1 | UGU42: of | UGV42: =$AF$33 -> 1 | UGW42: TOTAL REQUIREMENT: | UHD42: =UHI29 -> 0 | UHH42: SY | UHY42: Page | UHZ42: 1 | UIA42: of | UIB42: =$AF$33 -> 1 | UIC42: TOTAL REQUIREMENT: | UIJ42: =UIO29 -> 0 | UIN42: SY | UJE42: Page | UJF42: 1 | UJG42: of | UJH42: =$AF$33 -> 1 | UJI42: TOTAL REQUIREMENT: | UJP42: =UJU29 -> 0 | UJT42: SY | UKK42: Page | UKL42: 1 | UKM42: of | UKN42: =$AF$33 -> 1 | UKO42: TOTAL REQUIREMENT: | UKV42: =ULA29 -> 0 | UKZ42: SY | ULQ42: Page | ULR42: 1 | ULS42: of | ULT42: =$AF$33 -> 1 | ULU42: TOTAL REQUIREMENT: | UMB42: =UMG29 -> 0 | UMF42: SY | UMW42: Page | UMX42: 1 | UMY42: of | UMZ42: =$AF$33 -> 1 | UNA42: TOTAL REQUIREMENT: | UNH42: =UNM29 -> 0 | UNL42: SY | UOC42: Page | UOD42: 1 | UOE42: of | UOF42: =$AF$33 -> 1 | UOG42: TOTAL REQUIREMENT: | UON42: =UOS29 -> 0 | UOR42: SY | UPI42: Page | UPJ42: 1 | UPK42: of | UPL42: =$AF$33 -> 1 | UPM42: TOTAL REQUIREMENT: | UPT42: =UPY29 -> 0 | UPX42: SY | UQO42: Page | UQP42: 1 | UQQ42: of | UQR42: =$AF$33 -> 1 | UQS42: TOTAL REQUIREMENT: | UQZ42: =URE29 -> 0 | URD42: SY | URU42: Page | URV42: 1 | URW42: of | URX42: =$AF$33 -> 1 | URY42: TOTAL REQUIREMENT: | USF42: =USK29 -> 0 | USJ42: SY | UTA42: Page | UTB42: 1 | UTC42: of | UTD42: =$AF$33 -> 1 | UTE42: TOTAL REQUIREMENT: | UTL42: =UTQ29 -> 0 | UTP42: SY | UUG42: Page | UUH42: 1 | UUI42: of | UUJ42: =$AF$33 -> 1 | UUK42: TOTAL REQUIREMENT: | UUR42: =UUW29 -> 0 | UUV42: SY | UVM42: Page | UVN42: 1 | UVO42: of | UVP42: =$AF$33 -> 1 | UVQ42: TOTAL REQUIREMENT: | UVX42: =UWC29 -> 0 | UWB42: SY | UWS42: Page | UWT42: 1 | UWU42: of | UWV42: =$AF$33 -> 1 | UWW42: TOTAL REQUIREMENT: | UXD42: =UXI29 -> 0 | UXH42: SY | UXY42: Page | UXZ42: 1 | UYA42: of | UYB42: =$AF$33 -> 1 | UYC42: TOTAL REQUIREMENT: | UYJ42: =UYO29 -> 0 | UYN42: SY | UZE42: Page | UZF42: 1 | UZG42: of | UZH42: =$AF$33 -> 1 | UZI42: TOTAL REQUIREMENT: | UZP42: =UZU29 -> 0 | UZT42: SY | VAK42: Page | VAL42: 1 | VAM42: of | VAN42: =$AF$33 -> 1 | VAO42: TOTAL REQUIREMENT: | VAV42: =VBA29 -> 0 | VAZ42: SY | VBQ42: Page | VBR42: 1 | VBS42: of | VBT42: =$AF$33 -> 1 | VBU42: TOTAL REQUIREMENT: | VCB42: =VCG29 -> 0 | VCF42: SY | VCW42: Page | VCX42: 1 | VCY42: of | VCZ42: =$AF$33 -> 1 | VDA42: TOTAL REQUIREMENT: | VDH42: =VDM29 -> 0 | VDL42: SY | VEC42: Page | VED42: 1 | VEE42: of | VEF42: =$AF$33 -> 1 | VEG42: TOTAL REQUIREMENT: | VEN42: =VES29 -> 0 | VER42: SY | VFI42: Page | VFJ42: 1 | VFK42: of | VFL42: =$AF$33 -> 1 | VFM42: TOTAL REQUIREMENT: | VFT42: =VFY29 -> 0 | VFX42: SY | VGO42: Page | VGP42: 1 | VGQ42: of | VGR42: =$AF$33 -> 1 | VGS42: TOTAL REQUIREMENT: | VGZ42: =VHE29 -> 0 | VHD42: SY | VHU42: Page | VHV42: 1 | VHW42: of | VHX42: =$AF$33 -> 1 | VHY42: TOTAL REQUIREMENT: | VIF42: =VIK29 -> 0 | VIJ42: SY | VJA42: Page | VJB42: 1 | VJC42: of | VJD42: =$AF$33 -> 1 | VJE42: TOTAL REQUIREMENT: | VJL42: =VJQ29 -> 0 | VJP42: SY | VKG42: Page | VKH42: 1 | VKI42: of | VKJ42: =$AF$33 -> 1 | VKK42: TOTAL REQUIREMENT: | VKR42: =VKW29 -> 0 | VKV42: SY | VLM42: Page | VLN42: 1 | VLO42: of | VLP42: =$AF$33 -> 1 | VLQ42: TOTAL REQUIREMENT: | VLX42: =VMC29 -> 0 | VMB42: SY | VMS42: Page | VMT42: 1 | VMU42: of | VMV42: =$AF$33 -> 1 | VMW42: TOTAL REQUIREMENT: | VND42: =VNI29 -> 0 | VNH42: SY | VNY42: Page | VNZ42: 1 | VOA42: of | VOB42: =$AF$33 -> 1 | VOC42: TOTAL REQUIREMENT: | VOJ42: =VOO29 -> 0 | VON42: SY | VPE42: Page | VPF42: 1 | VPG42: of | VPH42: =$AF$33 -> 1 | VPI42: TOTAL REQUIREMENT: | VPP42: =VPU29 -> 0 | VPT42: SY | VQK42: Page | VQL42: 1 | VQM42: of | VQN42: =$AF$33 -> 1 | VQO42: TOTAL REQUIREMENT: | VQV42: =VRA29 -> 0 | VQZ42: SY | VRQ42: Page | VRR42: 1 | VRS42: of | VRT42: =$AF$33 -> 1 | VRU42: TOTAL REQUIREMENT: | VSB42: =VSG29 -> 0 | VSF42: SY | VSW42: Page | VSX42: 1 | VSY42: of | VSZ42: =$AF$33 -> 1 | VTA42: TOTAL REQUIREMENT: | VTH42: =VTM29 -> 0 | VTL42: SY | VUC42: Page | VUD42: 1 | VUE42: of | VUF42: =$AF$33 -> 1 | VUG42: TOTAL REQUIREMENT: | VUN42: =VUS29 -> 0 | VUR42: SY | VVI42: Page | VVJ42: 1 | VVK42: of | VVL42: =$AF$33 -> 1 | VVM42: TOTAL REQUIREMENT: | VVT42: =VVY29 -> 0 | VVX42: SY | VWO42: Page | VWP42: 1 | VWQ42: of | VWR42: =$AF$33 -> 1 | VWS42: TOTAL REQUIREMENT: | VWZ42: =VXE29 -> 0 | VXD42: SY | VXU42: Page | VXV42: 1 | VXW42: of | VXX42: =$AF$33 -> 1 | VXY42: TOTAL REQUIREMENT: | VYF42: =VYK29 -> 0 | VYJ42: SY | VZA42: Page | VZB42: 1 | VZC42: of | VZD42: =$AF$33 -> 1 | VZE42: TOTAL REQUIREMENT: | VZL42: =VZQ29 -> 0 | VZP42: SY | WAG42: Page | WAH42: 1 | WAI42: of | WAJ42: =$AF$33 -> 1 | WAK42: TOTAL REQUIREMENT: | WAR42: =WAW29 -> 0 | WAV42: SY | WBM42: Page | WBN42: 1 | WBO42: of | WBP42: =$AF$33 -> 1 | WBQ42: TOTAL REQUIREMENT: | WBX42: =WCC29 -> 0 | WCB42: SY | WCS42: Page | WCT42: 1 | WCU42: of | WCV42: =$AF$33 -> 1 | WCW42: TOTAL REQUIREMENT: | WDD42: =WDI29 -> 0 | WDH42: SY | WDY42: Page | WDZ42: 1 | WEA42: of | WEB42: =$AF$33 -> 1 | WEC42: TOTAL REQUIREMENT: | WEJ42: =WEO29 -> 0 | WEN42: SY | WFE42: Page | WFF42: 1 | WFG42: of | WFH42: =$AF$33 -> 1 | WFI42: TOTAL REQUIREMENT: | WFP42: =WFU29 -> 0 | WFT42: SY | WGK42: Page | WGL42: 1 | WGM42: of | WGN42: =$AF$33 -> 1 | WGO42: TOTAL REQUIREMENT: | WGV42: =WHA29 -> 0 | WGZ42: SY | WHQ42: Page | WHR42: 1 | WHS42: of | WHT42: =$AF$33 -> 1 | WHU42: TOTAL REQUIREMENT: | WIB42: =WIG29 -> 0 | WIF42: SY | WIW42: Page | WIX42: 1 | WIY42: of | WIZ42: =$AF$33 -> 1 | WJA42: TOTAL REQUIREMENT: | WJH42: =WJM29 -> 0 | WJL42: SY | WKC42: Page | WKD42: 1 | WKE42: of | WKF42: =$AF$33 -> 1 | WKG42: TOTAL REQUIREMENT: | WKN42: =WKS29 -> 0 | WKR42: SY | WLI42: Page | WLJ42: 1 | WLK42: of | WLL42: =$AF$33 -> 1 | WLM42: TOTAL REQUIREMENT: | WLT42: =WLY29 -> 0 | WLX42: SY | WMO42: Page | WMP42: 1 | WMQ42: of | WMR42: =$AF$33 -> 1 | WMS42: TOTAL REQUIREMENT: | WMZ42: =WNE29 -> 0 | WND42: SY | WNU42: Page | WNV42: 1 | WNW42: of | WNX42: =$AF$33 -> 1 | WNY42: TOTAL REQUIREMENT: | WOF42: =WOK29 -> 0 | WOJ42: SY | WPA42: Page | WPB42: 1 | WPC42: of | WPD42: =$AF$33 -> 1 | WPE42: TOTAL REQUIREMENT: | WPL42: =WPQ29 -> 0 | WPP42: SY | WQG42: Page | WQH42: 1 | WQI42: of | WQJ42: =$AF$33 -> 1 | WQK42: TOTAL REQUIREMENT: | WQR42: =WQW29 -> 0 | WQV42: SY | WRM42: Page | WRN42: 1 | WRO42: of | WRP42: =$AF$33 -> 1 | WRQ42: TOTAL REQUIREMENT: | WRX42: =WSC29 -> 0 | WSB42: SY | WSS42: Page | WST42: 1 | WSU42: of | WSV42: =$AF$33 -> 1 | WSW42: TOTAL REQUIREMENT: | WTD42: =WTI29 -> 0 | WTH42: SY | WTY42: Page | WTZ42: 1 | WUA42: of | WUB42: =$AF$33 -> 1 | WUC42: TOTAL REQUIREMENT: | WUJ42: =WUO29 -> 0 | WUN42: SY | WVE42: Page | WVF42: 1 | WVG42: of | WVH42: =$AF$33 -> 1 | WVI42: TOTAL REQUIREMENT: | WVP42: =WVU29 -> 0 | WVT42: SY | WWK42: Page | WWL42: 1 | WWM42: of | WWN42: =$AF$33 -> 1 | WWO42: TOTAL REQUIREMENT: | WWV42: =WXA29 -> 0 | WWZ42: SY | WXQ42: Page | WXR42: 1 | WXS42: of | WXT42: =$AF$33 -> 1 | WXU42: TOTAL REQUIREMENT: | WYB42: =WYG29 -> 0 | WYF42: SY | WYW42: Page | WYX42: 1 | WYY42: of | WYZ42: =$AF$33 -> 1 | WZA42: TOTAL REQUIREMENT: | WZH42: =WZM29 -> 0 | WZL42: SY | XAC42: Page | XAD42: 1 | XAE42: of | XAF42: =$AF$33 -> 1 | XAG42: TOTAL REQUIREMENT: | XAN42: =XAS29 -> 0 | XAR42: SY | XBI42: Page | XBJ42: 1 | XBK42: of | XBL42: =$AF$33 -> 1 | XBM42: TOTAL REQUIREMENT: | XBT42: =XBY29 -> 0 | XBX42: SY | XCO42: Page | XCP42: 1 | XCQ42: of | XCR42: =$AF$33 -> 1 | XCS42: TOTAL REQUIREMENT: | XCZ42: =XDE29 -> 0 | XDD42: SY | XDU42: Page | XDV42: 1 | XDW42: of | XDX42: =$AF$33 -> 1 | XDY42: TOTAL REQUIREMENT: | XEF42: =XEK29 -> 0 | XEJ42: SY | XFA42: Page | XFB42: 1 | XFC42: of | XFD42: =$AF$33 -> 1

Sheet Mission Statement
A1: *** UNCLASSIFIED // FOR OFFICIAL USE ONLY ***
A3: Source: Published | B3: United States Marine Corps | C3: Report Fiscal Year: | D3: 2025
A4: Structure Data current as of: 09/04/2024 | B4: Total Force Structure Management System | C4: Manning Precedence Level: | D4: IIIMEF
A5: Equipment Data Current as of: | B5: Unit TO&E Report | C5: Military Unit Level Code: | D5: HQS
A6: 45571.948
B7: H&S CO CLB 4 CLR 3 3D MLG | C7: Unit Descriptor Code: | D7: T
B8: UNIT 38440 | C8: Unit Type Code: | D8: 9VCBF
C9: SASSY AAC: | D9: SASSY M29030
D10: LONG TERM STORAGE -- DATA CONVERSION INITIAL ACCOUNT
B11: FPO, AP 963734000 | C11: MEF Code: | D11: C
B12: Country: JP | C12: Type Support Code: | D12: C
B13: UIC: M29031
A15: Mission Statement:
A16: AS OF 17 JAN 17 UNIT IDENTIFICATION HEADQUARTERS AND SERVICE COMPANY CODE....SEE ENCL (1) COMBAT LOGISTCS BATTALION X COMBAT LOGISTCS REGIMENT X MARINE LOGISTICS GROUP 1. Promulgation Statement. This is Headquarters and Service Company (H&S Co), Combat Logistics Battalion (CLB), Combat Logistics Regiment X (CLR x), Marine Logistics Group (MLG) mission statement. This mission statement defines the unit?s role and responsibilities in support of the Marine Air Ground Task Force and prescribes the unit?s organizational structure and capabilities in accordance with its tasks that manifests in the unit?s table of organization and equipment. 2. Organization Command Element Company Headquarters Section S-1 Administration Section S-3 Operations Section S-4 Logistics Section S-6 Communications Section Supply Section Medical Section/Battalion Aid Station Maintenance Services Platoon 3. Mission and Tasks a. Mission. Provide command and control, as well as command support functions for the CLB. b. Tasks (1) Provide command support functions, to include internal communications support for the battalion. (2) Provide limited general administration, field-level maintenance, supply, and health services support for the battalion. 4. Concept of Organization. The company is organized to plan, coordinate, and supervise command support functions for the battalion in support of an infantry regiment. 5. Concept of Employment. The company provides the necessary command, control, and support functions to plan, coordinate, and supervise the operations conducted by the CLB. a. Maneuver. The company maneuvers using organic assets to support to the CLB headquarters. b. Intelligence. Intelligence support and products are provided by headquarters company, CLR x, MLG. c. Fires. Organic firepower is limited to individual and crew-served weapons for personal and local security. d. Logistics. The company coordinates tactical logistics support for the battalion. e. Command and Control. The battalion commander directs and controls the battalion. The company commander directs and controls command support functions relating to operations, administration, and tactical logistics for the company. f. Force Protection. Capable of providing personal and local security. 6. Administrative Capabilities. Capable of general and operational administration. Personnel administration is provided by the appropriate consolidated administrative center. 7. Logistics Capabilities a. Maintenance. Capable of field-level maintenance. b. Supply. Capable of organic supply support. c. Transportation. Capable of organic transportation for command and administrative purposes. d. General Engineering. Engineering support is provided by engineer services company, CLB. e. Health Services. Capable of organic first responder health care capability. Dental health care services are provided by dental battalion, MLG. f. Services. Services support is provided by service company, headquarters regiment, MLG. Food service support is provided by food service company, headquarters regiment, MLG. 8. Command and Signal a. Command Relationships. The company commander reports to the CLB commander. b. Communications and Information Systems. Capable of organic communications support. Communications support in excess of organic capability is provided by headquarters company, CLR x, MLG. 9. Supersession. This mission statement supersedes the previous mission statement dated 7 October 2015, and is effective upon receipt. ROBERT S. WALSH Deputy Commandant for Combat Development and Integration UNIT IDENTIFICATION CODE: M28361 HEADQUARTERS AND SERVICE COMPANY CLB-1 CLR-1 M28371 HEADQUARTERS AND SERVICE COMPANY CLB-5 CLR-1 M28342 HEADQUARTERS AND SERVICE COMPANY CLB-7 CLR-1 M27341 HEADQUARTERS AND SERVICE COMPANY CLB-2 CLR-2 M27351 HEADQUARTERS AND SERVICE COMPANY CLB-6 CLR-2 M27361 HEADQUARTERS AND SERVICE COMPANY CLB-8 CLR-2 M29031 HEADQUARTERS AND SERVICE COMPANY CLB-4 CLR-3
A99: 45572 | C99: - 1 - | D99: 0.80916666
A100: *** UNCLASSIFIED // FOR OFFICIAL USE ONLY ***
A102: Source: Published | B102: United States Marine Corps | C102: Report Fiscal Year: | D102: 2025
A103: Structure Data current as of: 09/04/2024 | B103: Total Force Structure Management System | C103: Manning Precedence Level: | D103: IIIMEF
A104: Equipment Data Current as of: | B104: Unit TO&E Report | C104: Military Unit Level Code: | D104: CO
A105: 45567.949
B106: MT CO CLB 4 CLR 3 3D MLG | C106: Unit Descriptor Code: | D106: T
B107: UNIT 38420 | C107: Unit Type Code: | D107: UWLAB
C108: SASSY AAC: | D108: SASSY M29030
D109: LONG TERM STORAGE -- DATA CONVERSION INITIAL ACCOUNT
B110: FPO, AP 963734000 | C110: MEF Code: | D110: C
B111: Country: JP | C111: Type Support Code: | D111: C
B112: UIC: M29044
A114: Mission Statement:
A115: AS OF 17 JAN 17 UNIT IDENTIFICATION TRANSPORTATION SERVICES COMPANY CODE....SEE ENCL (1) COMBAT LOGISTICS BATTALION X COMBAT LOGISTICS REGIMENT X MARINE LOGISTICS GROUP 1. Promulgation Statement. This is transportation services company, combat logistics battalion (CLB), Combat Logistics Regiment X (CLR x), Marine Logistics Group (MLG) mission statement. This mission statement defines the unit?s role and responsibilities in support of the Marine Air Ground Task Force and prescribes the unit?s organizational structure and capabilities in accordance with its tasks that manifests in the unit?s table of organization and equipment. 2. Organization Company Headquarters Motor Transport Platoon (3) Landing Support Platoon 3. Mission and Tasks a. Mission. Provide landing support and medium and heavy-lift motor transport support for an infantry regiment beyond its organic capabilities. b. Tasks (1) Provide distribution of supplies, including bulk liquids, for an infantry regiment. (2) Provide personnel lift capability for an infantry regiment. (3) Provide landing support and port and terminal operations in support of regimental operations. 4. Concept of Organization. The company is organized to plan, coordinate, and supervise the command and transportation support functions for the company in support of regimental operations. 5. Concept of Employment. The company is employed as a unit to provide landing support and motor transport support to an infantry regiment. a. Maneuver. The company maneuvers using organic assets to support CLB operations. b. Intelligence. Intelligence support and products are provided by headquarters company, CLR x, MLG. c. Fires. Organic firepower is limited to individual and crew-served weapons for personal and local security. d. Logistics. Capable of providing landing support and medium- and heavy-lift motor transport support. e. Command and Control. The company commander directs and controls command support functions relating to operations, administration, and tactical logistics for the company. f. Force Protection. Capable of providing personal and local security. 6. Administrative Capabilities. Capable of general and operational administration. Personnel administration is provided by the appropriate consolidated administrative center. 7. Logistics Capabilities a. Maintenance. Field-level maintenance is provided by headquarters and service company, CLB, MLG. b. Supply. Supply support is provided by headquarters and service company, CLB, MLG. c. Transportation. Capable of organic transportation support for command and administrative purposes. d. General Engineering. Engineering support is provided by engineer services company, CLB, MLG. e. Health Services. First responder health care capability is provided by headquarters and service company, CLB, MLG. Dental health care services are provided by dental battalion, MLG. f. Services. Services support is provided by service company, headquarters regiment, MLG. Food service support is provided by food service company, headquarters regiment, MLG. 8. Command and Signal a. Command Relationships. The company commander reports to the CLB commander. b. Communications and Information Systems. Communications support is provided by headquarters and service company, CLB, MLG. 9. Supersession. This mission statement supersedes the previous mission statement dated 7 Octob 2015, and is effective upon receipt. ROBERT S. WALSH Deputy Commandant for Combat Development and Integration UNIT IDENTIFICATION CODE: M28338 TRANSPORTATION SERVICES COMPANY CLB-1 CLR-1 M28339 TRANSPORTATION SERVICES COMPANY CLB-5 CLR-1 M28346 TRANSPORTATION SERVICES COMPANY CLB-7 CLR-1 M27337 TRANSPORTATION SERVICES COMPANY CLB-2 CLR-2 M27338 TRANSPORTATION SERVICES COMPANY CLB-6 CLR-2 M29044 TRANSPORTATION SERVICES COMPANY CLB-4 CLR-3
A192: 45567 | C192: - 1 - | D192: 0.99443287
A194: *** UNCLASSIFIED // FOR OFFICIAL USE ONLY ***

Sheet TO
U4: CHARGEABLE | AD4: NON-CHARGEABLE
D5: Has a Desk? | U5: MC Act | W5: MC Res | Y5: Civ | Z5: Other Active | AB5: Other Reserve | AD5: MC Act | AF5: MC Res | AH5: Civ | AJ5: Other Active | AL5: Other Reserve | AN5: MT/MF | AO5: UIC
B6: LINE | C6: NOTE | D6: CCN | E6: CCN Decription | F6: UIC | G6: Rec CD | H6: BIC | I6: Billet Description | J6: Alpha Grade | K6: BMOS | L6: PMOS | M6: B R N | N6: T Y P | O6: S T A | P6: M P R | Q6: Res Typ | R6: S C | S6: W P N | T6: Billet SPN | U6: Off | V6: Enl | W6: Off | X6: Enl | Z6: Off | AA6: Enl | AB6: Off | AC6: Enl | AD6: Off | AE6: Enl | AF6: Off | AG6: Enl | AH6: NC | AI6: T/T | AJ6: Off | AK6: Enl | AL6: Off | AM6: Enl | AP6: A S R | AQ6: IH/CA | AR6: MCC | AS6: F T N
B7: 1 | F7: M29031 | G7: C | H7: M2903100007 | I7: COMMAND ELEMENT
B8: 2 | D8: 61072 | E8: BATTALION SQUADRON HEADQUARTERS - CMC ONLY | F8: M29031 | G8: E | H8: M2903100126 | I8: COMMANDING OFFICER | J8: LTCOL | K8: 0402 | L8: 0402 | M8: M | N8: O | O8: A | P8: A | R8: U | S8: C | U8: 1 | AP8: 1 | AQ8: A-M510 | AR8: 1CJ
B9: 3 | D9: 61072 | E9: BATTALION SQUADRON HEADQUARTERS - CMC ONLY | F9: M29031 | G9: E | H9: M2903100127 | I9: EXECUTIVE OFFICER | J9: MAJ | K9: 0402 | L9: 0402 | M9: M | N9: O | O9: A | P9: A | R9: U | S9: C | U9: 1 | AP9: 1 | AQ9: A-M510 | AR9: 1CJ
B10: 4 | D10: 61072 | E10: BATTALION SQUADRON HEADQUARTERS - CMC ONLY | F10: M29031 | G10: E | H10: M2903100124 | I10: COMMAND SENIOR ENLISTED LEADER | J10: SGTMAJ | K10: 8999 | L10: 8999 | M10: M | N10: E | O10: A | P10: A | R10: T | S10: C | V10: 1 | AP10: 1 | AQ10: A-M510 | AR10: 1CJ
B11: 5 | D11: 21710 | E11: ELECTRONICS / COMMUNICATIONS MAINTENANCE SHOP | F11: M29031 | G11: E | H11: M2903100125 | I11: TRANSMISSIONS SYSTEMS OPERATOR | J11: CPL | K11: 0621 | L11: 0621 | M11: M | N11: E | O11: A | P11: A | R11: S | S11: M | V11: 1 | AP11: 1 | AQ11: A-V441B | AR11: 1CJ
B12: 6 | F12: M29031 | G12: C | H12: M2903100002 | I12: COMPANY HEADQUARTERS SECTION
B13: 7 | D13: 61072 | E13: BATTALION SQUADRON HEADQUARTERS - CMC ONLY | F13: M29031 | G13: E | H13: M2903100211 | I13: COMPANY COMMANDER | J13: CAPT | K13: 0402 | L13: 0402 | M13: M | N13: O | O13: A | P13: A | R13: U | S13: C | U13: 1 | AP13: 1 | AQ13: A-M510 | AR13: 1CJ
B14: 8 | D14: 61072 | E14: BATTALION SQUADRON HEADQUARTERS - CMC ONLY | F14: M29031 | G14: E | H14: M2903100212 | I14: EXECUTIVE OFFICER | J14: 1STLT | K14: 0402 | L14: 0402 | M14: M | N14: O | O14: A | P14: A | R14: U | S14: C | U14: 1 | AP14: 1 | AQ14: A-M510 | AR14: 1CJ
B15: 9 | D15: 61072 | E15: BATTALION SQUADRON HEADQUARTERS - CMC ONLY | F15: M29031 | G15: E | H15: M2903100208 | I15: UNIT SENIOR ENLISTED LEADER | J15: 1STSGT | K15: 8999 | L15: 8999 | M15: M | N15: E | O15: A | P15: A | R15: S | S15: C | V15: 1 | AP15: 1 | AQ15: A-M510 | AR15: 1CJ
B16: 10 | D16: 61072 | E16: BATTALION SQUADRON HEADQUARTERS - CMC ONLY | F16: M29031 | G16: E | H16: M2903100209 | I16: COMPANY GUNNERY SERGEANT | J16: GYSGT | K16: 3047 | L16: 3047 | M16: M | N16: E | O16: A | P16: A | R16: U | S16: C | V16: 1 | AP16: 1 | AQ16: A-M510 | AR16: 1CJ
B17: 11 | D17: 61072 | E17: BATTALION SQUADRON HEADQUARTERS - CMC ONLY | F17: M29031 | G17: E | H17: M2903100224 | I17: TAC CHAPLAIN | J17: LT | K17: 4100 | L17: 4100 | M17: N | N17: O | O17: A | P17: A | R17: U | S17: U | Z17: 1 | AP17: 1 | AQ17: A-M510 | AR17: 1CJ
B18: 12 | D18: 61072 | E18: BATTALION SQUADRON HEADQUARTERS - CMC ONLY | F18: M29031 | G18: E | H18: M2903100225 | I18: RP SPECIALIST | J18: RPSN | K18: A17A | L18: A17A | M18: N | N18: E | O18: A | P18: A | R18: U | S18: C | AA18: 1 | AP18: 1 | AQ18: A-M510 | AR18: 1CJ
B19: 13 | F19: M29031 | G19: C | H19: M2903100003 | I19: S-1
B20: 14 | D20: 61072 | E20: BATTALION SQUADRON HEADQUARTERS - CMC ONLY | F20: M29031 | G20: E | H20: M2903100131 | I20: ADJUTANT | J20: 1STLT | K20: 0102 | L20: 0102 | M20: M | N20: O | O20: A | P20: A | R20: U | S20: C | U20: 1 | AP20: 1 | AQ20: A-M510 | AR20: 1CJ
B21: 15 | D21: 61072 | E21: BATTALION SQUADRON HEADQUARTERS - CMC ONLY | F21: M29031 | G21: E | H21: M2903100129 | I21: ADMIN CHIEF | J21: GYSGT | K21: 0111 | L21: 0111 | M21: M | N21: E | O21: A | P21: A | R21: U | S21: C | V21: 1 | AP21: 1 | AQ21: A-M510 | AR21: 1CJ
B22: 16 | D22: 61072 | E22: BATTALION SQUADRON HEADQUARTERS - CMC ONLY | F22: M29031 | G22: E | H22: M2903100130 | I22: ADMIN CLERK | J22: CPL | K22: 0111 | L22: 0111 | M22: M | N22: E | O22: A | P22: A | R22: U | S22: M | V22: 1 | AP22: 1 | AQ22: A-M510 | AR22: 1CJ
B23: 17 | D23: 61072 | E23: BATTALION SQUADRON HEADQUARTERS - CMC ONLY | F23: M29031 | G23: E | H23: M2903100128 | I23: ADMIN CLERK | J23: LCPL | K23: 0111 | L23: 0111 | M23: M | N23: E | O23: A | P23: A | R23: U | S23: M | V23: 1 | AP23: 1 | AQ23: A-M510 | AR23: 1CJ
B24: 18 | D24: 61072 | E24: BATTALION SQUADRON HEADQUARTERS - CMC ONLY | F24: M29031 | G24: E | H24: M2903100132 | I24: ADMIN CLERK | J24: LCPL | K24: 0111 | L24: 0111 | M24: M | N24: E | O24: A | P24: A | R24: U | S24: M | V24: 1 | AP24: 1 | AQ24: A-M510 | AR24: 1CJ
B25: 19 | F25: M29031 | G25: C | H25: M2903100004 | I25: S-3
B26: 20 | D26: 61072 | E26: BATTALION SQUADRON HEADQUARTERS - CMC ONLY | F26: M29031 | G26: E | H26: M2903100149 | I26: OPERATIONS OFFICER | J26: MAJ | K26: 0477 | L26: 0402 | M26: M | N26: O | O26: A | P26: A | R26: U | S26: C | U26: 1 | AP26: 1 | AQ26: A-M510 | AR26: 1CJ
B27: 21 | D27: 61072 | E27: BATTALION SQUADRON HEADQUARTERS - CMC ONLY | F27: M29031 | G27: E | H27: M2903100133 | I27: OPERATIONS CHIEF | J27: MSGT | K27: 0477 | L27: 0491 | M27: M | N27: E | O27: A | P27: A | R27: U | S27: C | V27: 1 | AP27: 1 | AQ27: A-M510 | AR27: 1CJ
B28: 22 | D28: 61072 | E28: BATTALION SQUADRON HEADQUARTERS - CMC ONLY | F28: M29031 | G28: E | H28: M2903100139 | I28: WATCH CHIEF | J28: SSGT | K28: 3537 | L28: 3537 | M28: M | N28: E | O28: A | P28: A | R28: U | S28: C | V28: 1 | AP28: 1 | AQ28: A-M510 | AR28: 1CJ
B29: 23 | D29: 61072 | E29: BATTALION SQUADRON HEADQUARTERS - CMC ONLY | F29: M29031 | G29: E | H29: M2903100135 | I29: LOGISTICS CHAIN PLANNING CHIEF | J29: SSGT | K29: 3047 | L29: 3047 | M29: M | N29: E | O29: A | P29: A | R29: U | S29: C | V29: 1 | AP29: 1 | AQ29: A-M510 | AR29: 1CJ
B30: 24 | D30: 61072 | E30: BATTALION SQUADRON HEADQUARTERS - CMC ONLY | F30: M29031 | G30: E | H30: M2903100143 | I30: ORDER MANAGEMENT SPECIALIST | J30: SGT | K30: 3047 | L30: 3047 | M30: M | N30: E | O30: A | P30: A | R30: U | S30: M | V30: 1 | AP30: 1 | AQ30: A-M510 | AR30: 1CJ
B31: 25 | D31: 61072 | E31: BATTALION SQUADRON HEADQUARTERS - CMC ONLY | F31: M29031 | G31: E | H31: M2903100146 | I31: TRAINING CLERK | J31: LCPL | K31: 3531 | L31: 3531 | M31: M | N31: E | O31: A | P31: A | R31: U | S31: C | V31: 1 | AP31: 1 | AQ31: A-M510 | AR31: 1CJ
B32: 26 | D32: 61072 | E32: BATTALION SQUADRON HEADQUARTERS - CMC ONLY | F32: M29031 | G32: E | H32: M2903100152 | I32: INTELLIGENCE OFFICER | J32: 1STLT | K32: 0234 | L32: 0202 | M32: M | N32: O | O32: A | P32: A | R32: I | S32: C | U32: 1 | AP32: 1 | AQ32: A-M510 | AR32: 1CJ
B33: 27 | D33: 61072 | E33: BATTALION SQUADRON HEADQUARTERS - CMC ONLY | F33: M29031 | G33: E | H33: M2903100147 | I33: INTELLIGENCE ANALYST | J33: SGT | K33: 0239 | L33: 0231 | M33: M | N33: E | O33: A | P33: A | R33: I | S33: M | V33: 1 | AP33: 1 | AQ33: A-M510 | AR33: 1CJ
B34: 28 | D34: 61072 | E34: BATTALION SQUADRON HEADQUARTERS - CMC ONLY | F34: M29031 | G34: E | H34: M2903100148 | I34: INTELLIGENCE SYSTEMS TECHNICIAN | J34: CPL | K34: 0231 | L34: 0231 | M34: M | N34: E | O34: A | P34: A | R34: I | S34: M | V34: 1 | AP34: 1 | AQ34: A-M510 | AR34: 1CJ
B35: 29 | F35: M29031 | G35: D | H35: M2903100114 | I35: CURRENT OPERATIONS
B36: 30 | D36: 61072 | E36: BATTALION SQUADRON HEADQUARTERS - CMC ONLY | F36: M29031 | G36: E | H36: M2903100151 | I36: CURRENT OPERATIONS OFFICER | J36: 1STLT | K36: 0402 | L36: 0402 | M36: M | N36: O | O36: A | P36: A | R36: U | S36: C | U36: 1 | AP36: 1 | AQ36: A-M510 | AR36: 1CJ
B37: 31 | D37: 61072 | E37: BATTALION SQUADRON HEADQUARTERS - CMC ONLY | F37: M29031 | G37: E | H37: M2903100138 | I37: CURRENT OPERATIONS CHIEF | J37: GYSGT | K37: 3537 | L37: 3537 | M37: M | N37: E | O37: A | P37: A | R37: U | S37: C | V37: 1 | AP37: 1 | AQ37: A-M510 | AR37: 1CJ
B38: 32 | D38: 61072 | E38: BATTALION SQUADRON HEADQUARTERS - CMC ONLY | F38: M29031 | G38: E | H38: M2903100140 | I38: CURRENT OPERATIONS NCO | J38: SGT | K38: 3531 | L38: 3531 | M38: M | N38: E | O38: A | P38: A | R38: U | S38: C | V38: 1 | AP38: 1 | AQ38: A-M510 | AR38: 1CJ
B39: 33 | D39: 61072 | E39: BATTALION SQUADRON HEADQUARTERS - CMC ONLY | F39: M29031 | G39: E | H39: M2903100141 | I39: CURRENT OPERATIONS CLERK | J39: LCPL | K39: 0441 | L39: 0441 | M39: M | N39: E | O39: A | P39: A | R39: U | S39: M | V39: 1 | AP39: 1 | AQ39: A-M510 | AR39: 1CJ
B40: 34 | F40: M29031 | G40: D | H40: M2903100113 | I40: FUTURE OPERATIONS
B41: 35 | D41: 61072 | E41: BATTALION SQUADRON HEADQUARTERS - CMC ONLY | F41: M29031 | G41: E | H41: M2903100134 | I41: FUTURE OPERATIONS CHIEF | J41: GYSGT | K41: 0491 | L41: 0491 | M41: M | N41: E | O41: A | P41: A | R41: U | S41: C | V41: 1 | AP41: 1 | AQ41: A-M510 | AR41: 1CJ
B42: 36 | D42: 61072 | E42: BATTALION SQUADRON HEADQUARTERS - CMC ONLY | F42: M29031 | G42: E | H42: M2903100136 | I42: FUTURE OPERATIONS NCO | J42: SGT | K42: 0441 | L42: 0441 | M42: M | N42: E | O42: A | P42: A | R42: U | S42: M | V42: 1 | AP42: 1 | AQ42: A-M510 | AR42: 1CJ
B43: 37 | D43: 61072 | E43: BATTALION SQUADRON HEADQUARTERS - CMC ONLY | F43: M29031 | G43: E | H43: M2903100137 | I43: FUTURE OPERATIONS CLERK | J43: LCPL | K43: 0441 | L43: 0441 | M43: M | N43: E | O43: A | P43: A | R43: U | S43: M | V43: 1 | AP43: 1 | AQ43: A-M510 | AR43: 1CJ
B44: 38 | F44: M29031 | G44: C | H44: M2903100005 | I44: S-4
B45: 39 | D45: 61072 | E45: BATTALION SQUADRON HEADQUARTERS - CMC ONLY | F45: M29031 | G45: E | H45: M2903100163 | I45: LOGISTICS OFFICER | J45: 1STLT | K45: 0402 | L45: 0402 | M45: M | N45: O | O45: A | P45: A | R45: U | S45: C | U45: 1 | AP45: 1 | AQ45: A-M510 | AR45: 1CJ
B46: 40 | D46: 61072 | E46: BATTALION SQUADRON HEADQUARTERS - CMC ONLY | F46: M29031 | G46: E | H46: M2903100389 | I46: LOGISTICS OFFICER | J46: 1STLT | K46: 0402 | L46: 0402 | M46: M | N46: O | O46: A | P46: A | R46: U | S46: C | U46: 1 | AP46: 1 | AQ46: A-M510 | AR46: 1CJ
B47: 41 | D47: 61072 | E47: BATTALION SQUADRON HEADQUARTERS - CMC ONLY | F47: M29031 | G47: E | H47: M2903100153 | I47: LOGISTICS CHIEF | J47: SSGT | K47: 0441 | L47: 0441 | M47: M | N47: E | O47: A | P47: A | R47: U | S47: C | V47: 1 | AP47: 1 | AQ47: A-M510 | AR47: 1CJ
B48: 42 | D48: 61072 | E48: BATTALION SQUADRON HEADQUARTERS - CMC ONLY | F48: M29031 | G48: E | H48: M2903100154 | I48: EMBARKATION NCO | J48: CPL | K48: 0441 | L48: 0441 | M48: M | N48: E | O48: A | P48: A | R48: U | S48: M | V48: 1 | AP48: 1 | AQ48: A-M510 | AR48: 1CJ
B49: 43 | D49: 61072 | E49: BATTALION SQUADRON HEADQUARTERS - CMC ONLY | F49: M29031 | G49: E | H49: M2903100155 | I49: EMBARKATION CLERK | J49: LCPL | K49: 0441 | L49: 0441 | M49: M | N49: E | O49: A | P49: A | R49: U | S49: M | V49: 1 | AP49: 1 | AQ49: A-M510 | AR49: 1CJ
B50: 44 | D50: 61072 | E50: BATTALION SQUADRON HEADQUARTERS - CMC ONLY | F50: M29031 | G50: E | H50: M2903100156 | I50: MAINTENANCE MANAGEMENT CHIEF | J50: SSGT | K50: 0411 | L50: 0411 | M50: M | N50: E | O50: A | P50: A | R50: U | S50: C | V50: 1 | AP50: 1 | AQ50: A-M510 | AR50: 1CJ
B51: 45 | D51: 61072 | E51: BATTALION SQUADRON HEADQUARTERS - CMC ONLY | F51: M29031 | G51: E | H51: M2903100157 | I51: MAINTENANCE MANAGEMENT CLERK/DRIVER | J51: LCPL | K51: 0411 | L51: 0411 | M51: M | N51: E | O51: A | P51: A | R51: U | S51: M | V51: 1 | AP51: 1 | AQ51: A-M510 | AR51: 1CJ
B52: 46 | D52: 61072 | E52: BATTALION SQUADRON HEADQUARTERS - CMC ONLY | F52: M29031 | G52: E | H52: M2903100158 | I52: AMMUNITION TECHNICIAN | J52: CPL | K52: 2311 | L52: 2311 | M52: M | N52: E | O52: A | P52: A | R52: U | S52: M | V52: 1 | AP52: 1 | AQ52: A-M510 | AR52: 1CJ
B53: 47 | D53: 61072 | E53: BATTALION SQUADRON HEADQUARTERS - CMC ONLY | F53: M29031 | G53: E | H53: M2903100159 | I53: AMMUNITION TECHNICIAN | J53: LCPL | K53: 2311 | L53: 2311 | M53: M | N53: E | O53: A | P53: A | R53: U | S53: M | V53: 1 | AP53: 1 | AQ53: A-M510 | AR53: 1CJ
B54: 48 | F54: M29031 | G54: C | H54: M2903100375 | I54: LANDING SUPPORT SECTION
B55: 49 | D55: 21451 | E55: AUTOMOTIVE ORGANIZATIONAL SHOP | F55: M29031 | G55: E | H55: M2903100376 | I55: LOGISTICS CHIEF | J55: SSGT | K55: 0441 | L55: 0441 | M55: M | N55: E | O55: A | P55: A | R55: U | S55: C | V55: 1 | AP55: 1 | AQ55: A-M510 | AR55: 1CJ
B56: 50 | D56: 21451 | E56: AUTOMOTIVE ORGANIZATIONAL SHOP | F56: M29031 | G56: E | H56: M2903100377 | I56: LANDING SUPPORT SPECIALIST | J56: SGT | K56: 0441 | L56: 0441 | M56: M | N56: E | O56: A | P56: A | R56: U | S56: M | V56: 1 | AP56: 1 | AQ56: A-M510 | AR56: 1CJ
B57: 51 | D57: 21451 | E57: AUTOMOTIVE ORGANIZATIONAL SHOP | F57: M29031 | G57: E | H57: M2903100378 | I57: LANDING SUPPORT SPECIALIST | J57: SGT | K57: 0441 | L57: 0441 | M57: M | N57: E | O57: A | P57: A | R57: U | S57: M | V57: 1 | AP57: 1 | AQ57: A-M510 | AR57: 1CJ
B58: 52 | D58: 21451 | E58: AUTOMOTIVE ORGANIZATIONAL SHOP | F58: M29031 | G58: E | H58: M2903100379 | I58: LANDING SUPPORT SPECIALIST | J58: CPL | K58: 0441 | L58: 0441 | M58: M | N58: E | O58: A | P58: A | R58: U | S58: M | V58: 1 | AP58: 1 | AQ58: A-M510 | AR58: 1CJ
B59: 53 | D59: 21451 | E59: AUTOMOTIVE ORGANIZATIONAL SHOP | F59: M29031 | G59: E | H59: M2903100380 | I59: LANDING SUPPORT SPECIALIST | J59: CPL | K59: 0441 | L59: 0441 | M59: M | N59: E | O59: A | P59: A | R59: U | S59: M | V59: 1 | AP59: 1 | AQ59: A-M510 | AR59: 1CJ
B60: 54 | D60: 21451 | E60: AUTOMOTIVE ORGANIZATIONAL SHOP | F60: M29031 | G60: E | H60: M2903100381 | I60: LANDING SUPPORT SPECIALIST | J60: CPL | K60: 0441 | L60: 0441 | M60: M | N60: E | O60: A | P60: A | R60: U | S60: M | V60: 1 | AP60: 1 | AQ60: A-M510 | AR60: 1CJ
B61: 55 | D61: 21451 | E61: AUTOMOTIVE ORGANIZATIONAL SHOP | F61: M29031 | G61: E | H61: M2903100382 | I61: LANDING SUPPORT SPECIALIST | J61: LCPL | K61: 0441 | L61: 0441 | M61: M | N61: E | O61: A | P61: A | R61: U | S61: M | V61: 1 | AP61: 1 | AQ61: A-M510 | AR61: 1CJ
B62: 56 | D62: 21451 | E62: AUTOMOTIVE ORGANIZATIONAL SHOP | F62: M29031 | G62: E | H62: M2903100383 | I62: LANDING SUPPORT SPECIALIST | J62: LCPL | K62: 0441 | L62: 0441 | M62: M | N62: E | O62: A | P62: A | R62: U | S62: M | V62: 1 | AP62: 1 | AQ62: A-M510 | AR62: 1CJ
B63: 57 | F63: M29031 | G63: C | H63: M2903100006 | I63: S-6
B64: 58 | D64: 21710 | E64: ELECTRONICS / COMMUNICATIONS MAINTENANCE SHOP | F64: M29031 | G64: E | H64: M2903100195 | I64: COMMUNICATIONS OFFICER | J64: 1STLT | K64: 0602 | L64: 0602 | M64: M | N64: O | O64: A | P64: A | R64: I | S64: C | U64: 1 | AP64: 1 | AQ64: A-V641B | AR64: 1CJ
B65: 59 | D65: 21710 | E65: ELECTRONICS / COMMUNICATIONS MAINTENANCE SHOP | F65: M29031 | G65: E | H65: M2903100171 | I65: ASSISTANT TRANSMISSIONS SYSTEMS CHIEF | J65: SSGT | K65: 0629 | L65: 0629 | M65: M | N65: E | O65: A | P65: A | R65: S | S65: C | V65: 1 | AP65: 1 | AQ65: A-V441IM | AR65: 1CJ
B66: 60 | D66: 21710 | E66: ELECTRONICS / COMMUNICATIONS MAINTENANCE SHOP | F66: M29031 | G66: E | H66: M2903100172 | I66: TRANSMISSIONS SYSTEMS OPERATOR | J66: SGT | K66: 0621 | L66: 0621 | M66: M | N66: E | O66: A | P66: A | R66: S | S66: M | V66: 1 | AP66: 1 | AQ66: A-V441IM | AR66: 1CJ
B67: 61 | D67: 21710 | E67: ELECTRONICS / COMMUNICATIONS MAINTENANCE SHOP | F67: M29031 | G67: E | H67: M2903100173 | I67: TRANSMISSIONS SYSTEMS OPERATOR | J67: SGT | K67: 0621 | L67: 0621 | M67: M | N67: E | O67: A | P67: A | R67: S | S67: M | V67: 1 | AP67: 1 | AQ67: A-V441IM | AR67: 1CJ
B68: 62 | D68: 21710 | E68: ELECTRONICS / COMMUNICATIONS MAINTENANCE SHOP | F68: M29031 | G68: E | H68: M2903100174 | I68: TRANSMISSIONS SYSTEMS OPERATOR | J68: SGT | K68: 0621 | L68: 0621 | M68: M | N68: E | O68: A | P68: A | R68: S | S68: M | V68: 1 | AP68: 1 | AQ68: A-V441IM | AR68: 1CJ
B69: 63 | D69: 21710 | E69: ELECTRONICS / COMMUNICATIONS MAINTENANCE SHOP | F69: M29031 | G69: E | H69: M2903100175 | I69: TRANSMISSIONS SYSTEMS OPERATOR | J69: CPL | K69: 0621 | L69: 0621 | M69: M | N69: E | O69: A | P69: A | R69: S | S69: M | V69: 1 | AP69: 1 | AQ69: A-V441B | AR69: 1CJ
B70: 64 | D70: 21710 | E70: ELECTRONICS / COMMUNICATIONS MAINTENANCE SHOP | F70: M29031 | G70: E | H70: M2903100176 | I70: TRANSMISSIONS SYSTEMS OPERATOR | J70: CPL | K70: 0621 | L70: 0621 | M70: M | N70: E | O70: A | P70: A | R70: S | S70: M | V70: 1 | AP70: 1 | AQ70: A-V441B | AR70: 1CJ
B71: 65 | D71: 21710 | E71: ELECTRONICS / COMMUNICATIONS MAINTENANCE SHOP | F71: M29031 | G71: E | H71: M2903100177 | I71: TRANSMISSIONS SYSTEMS OPERATOR | J71: CPL | K71: 0621 | L71: 0621 | M71: M | N71: E | O71: A | P71: A | R71: S | S71: M | V71: 1 | AP71: 1 | AQ71: A-V441B | AR71: 1CJ
B72: 66 | D72: 21710 | E72: ELECTRONICS / COMMUNICATIONS MAINTENANCE SHOP | F72: M29031 | G72: E | H72: M2903100178 | I72: TRANSMISSIONS SYSTEMS OPERATOR | J72: CPL | K72: 0621 | L72: 0621 | M72: M | N72: E | O72: A | P72: A | R72: S | S72: M | V72: 1 | AP72: 1 | AQ72: A-V441B | AR72: 1CJ
B73: 67 | D73: 21710 | E73: ELECTRONICS / COMMUNICATIONS MAINTENANCE SHOP | F73: M29031 | G73: E | H73: M2903100179 | I73: TRANSMISSIONS SYSTEMS OPERATOR | J73: LCPL | K73: 0621 | L73: 0621 | M73: M | N73: E | O73: A | P73: A | R73: S | S73: M | V73: 1 | AP73: 1 | AQ73: A-V441B | AR73: 1CJ
B74: 68 | D74: 21710 | E74: ELECTRONICS / COMMUNICATIONS MAINTENANCE SHOP | F74: M29031 | G74: E | H74: M2903100180 | I74: TRANSMISSIONS SYSTEMS OPERATOR | J74: LCPL | K74: 0621 | L74: 0621 | M74: M | N74: E | O74: A | P74: A | R74: S | S74: M | V74: 1 | AP74: 1 | AQ74: A-V441B | AR74: 1CJ
B75: 69 | D75: 21710 | E75: ELECTRONICS / COMMUNICATIONS MAINTENANCE SHOP | F75: M29031 | G75: E | H75: M2903100164 | I75: NETWORK CHIEF | J75: SSGT | K75: 0639 | L75: 0639 | M75: M | N75: E | O75: A | P75: A | R75: S | S75: C | V75: 1 | AP75: 1 | AQ75: A-V441IM | AR75: 1CJ
B76: 70 | D76: 21710 | E76: ELECTRONICS / COMMUNICATIONS MAINTENANCE SHOP | F76: M29031 | G76: E | H76: M2903100165 | I76: NETWORK ADMINISTRATOR | J76: SGT | K76: 0631 | L76: 0631 | M76: M | N76: E | O76: A | P76: A | R76: S | S76: M | V76: 1 | AP76: 1 | AQ76: A-V441IM | AR76: 1CJ
... B86: 80 | D86: 21710 | E86: ELECTRONICS / COMMUNICATIONS MAINTENANCE SHOP | F86: M29031 | G86: E | H86: M2903100193 | I86: DATA SYSTEMS ADMINISTRATOR | J86: LCPL | K86: 0671 | L86: 0671 | M86: M | N86: E | O86: A | P86: A | R86: S | S86: M | V86: 1 | AP86: 1 | AQ86: A-V451B | AR86: 1CJ
B87: 81 | F87: M29031 | G87: C | H87: M2903100099 | I87: SUPPLY SECTION
B88: 82 | D88: 44112 | E88: STORAGE OF AIR OR GROUND ORGANIC UNITS FOR MARINE CORPS | F88: M29031 | G88: E | H88: M2903100197 | I88: SUPPLY ADMIN CHIEF | J88: SGT | K88: 3047 | L88: 3047 | M88: M | N88: E | O88: A | P88: A | R88: U | S88: M | V88: 1 | AP88: 1 | AQ88: A-M510 | AR88: 1CJ
B89: 83 | D89: 44112 | E89: STORAGE OF AIR OR GROUND ORGANIC UNITS FOR MARINE CORPS | F89: M29031 | G89: E | H89: M2903100198 | I89: SUPPLY ADMIN CLERK | J89: CPL | K89: 3043 | L89: 3043 | M89: M | N89: E | O89: A | P89: A | R89: U | S89: M | V89: 1 | AP89: 1 | AQ89: A-M510 | AR89: 1CJ
B90: 84 | D90: 44112 | E90: STORAGE OF AIR OR GROUND ORGANIC UNITS FOR MARINE CORPS | F90: M29031 | G90: E | H90: M2903100199 | I90: SUPPLY ADMIN CLERK | J90: CPL | K90: 3043 | L90: 3043 | M90: M | N90: E | O90: A | P90: A | R90: U | S90: M | V90: 1 | AP90: 1 | AQ90: A-M510 | AR90: 1CJ
B91: 85 | D91: 44112 | E91: STORAGE OF AIR OR GROUND ORGANIC UNITS FOR MARINE CORPS | F91: M29031 | G91: E | H91: M2903100200 | I91: SUPPLY ADMIN CLERK | J91: LCPL | K91: 3043 | L91: 3043 | M91: M | N91: E | O91: A | P91: A | R91: U | S91: M | V91: 1 | AP91: 1 | AQ91: A-M510 | AR91: 1CJ
B92: 86 | D92: 44112 | E92: STORAGE OF AIR OR GROUND ORGANIC UNITS FOR MARINE CORPS | F92: M29031 | G92: E | H92: M2903100384 | I92: SUPPLY ADMIN CLERK | J92: SGT | K92: 3047 | L92: 3047 | M92: M | N92: E | O92: A | P92: A | R92: U | S92: M | V92: 1 | AP92: 1 | AQ92: A-M510 | AR92: 1CJ
B93: 87 | D93: 44112 | E93: STORAGE OF AIR OR GROUND ORGANIC UNITS FOR MARINE CORPS | F93: M29031 | G93: E | H93: M2903100385 | I93: SUPPLY ADMIN CLERK | J93: CPL | K93: 3043 | L93: 3043 | M93: M | N93: E | O93: A | P93: A | R93: U | S93: M | V93: 1 | AP93: 1 | AQ93: A-M510 | AR93: 1CJ
B94: 88 | D94: 44112 | E94: STORAGE OF AIR OR GROUND ORGANIC UNITS FOR MARINE CORPS | F94: M29031 | G94: E | H94: M2903100386 | I94: SUPPLY ADMIN CLERK | J94: LCPL | K94: 3043 | L94: 3043 | M94: M | N94: E | O94: A | P94: A | R94: U | S94: M | V94: 1 | AP94: 1 | AQ94: A-M510 | AR94: 1CJ
B95: 89 | D95: 44112 | E95: STORAGE OF AIR OR GROUND ORGANIC UNITS FOR MARINE CORPS | F95: M29031 | G95: E | H95: M2903100203 | I95: WAREHOUSE CHIEF | J95: SSGT | K95: 3047 | L95: 3047 | M95: M | N95: E | O95: A | P95: A | R95: U | S95: C | V95: 1 | AP95: 1 | AQ95: A-M510 | AR95: 1CJ
B96: 90 | D96: 44112 | E96: STORAGE OF AIR OR GROUND ORGANIC UNITS FOR MARINE CORPS | F96: M29031 | G96: E | H96: M2903100204 | I96: WAREHOUSE CLERK | J96: CPL | K96: 3051 | L96: 3051 | M96: M | N96: E | O96: A | P96: A | R96: U | S96: M | V96: 1 | AP96: 1 | AQ96: A-M510 | AR96: 1CJ
B97: 91 | D97: 44112 | E97: STORAGE OF AIR OR GROUND ORGANIC UNITS FOR MARINE CORPS | F97: M29031 | G97: E | H97: M2903100387 | I97: WAREHOUSE CLERK | J97: LCPL | K97: 3051 | L97: 3051 | M97: M | N97: E | O97: A | P97: A | R97: U | S97: M | V97: 1 | AP97: 1 | AQ97: A-M510 | AR97: 1CJ
B98: 92 | D98: 44112 | E98: STORAGE OF AIR OR GROUND ORGANIC UNITS FOR MARINE CORPS | F98: M29031 | G98: E | H98: M2903100388 | I98: WAREHOUSE CLERK | J98: PFC | K98: 3051 | L98: 3051 | M98: M | N98: E | O98: A | P98: A | R98: U | S98: M | V98: 1 | AP98: 1 | AQ98: A-M510 | AR98: 1CJ
B99: 93 | F99: M29031 | G99: C | H99: M2903100116 | I99: MEDICAL SECTION BATTALION AID STATION
B100: 94 | D100: 61072 | E100: BATTALION SQUADRON HEADQUARTERS - CMC ONLY | F100: M29031 | G100: E | H100: M2903100213 | I100: PHYSICIAN ASST | J100: LTJG | K100: 2300 | L100: 2300 | M100: N | N100: O | O100: A | P100: A | R100: S | S100: P | Z100: 1 | AP100: 1 | AQ100: A-M510 | AR100: 1CJ
B101: 95 | D101: 61072 | E101: BATTALION SQUADRON HEADQUARTERS - CMC ONLY | F101: M29031 | G101: E | H101: M2903100214 | I101: FLD MED TECH | J101: HM1 | K101: L03A | L101: L03A | M101: N | N101: E | O101: A | P101: A | R101: U | S101: P | AA101: 1 | AP101: 1 | AQ101: A-M510 | AR101: 1CJ
B102: 96 | D102: 61072 | E102: BATTALION SQUADRON HEADQUARTERS - CMC ONLY | F102: M29031 | G102: E | H102: M2903100215 | I102: FLD MED TECH | J102: HM2 | K102: L03A | L102: L03A | M102: N | N102: E | O102: A | P102: A | R102: U | S102: C | AA102: 1 | AP102: 1 | AQ102: A-M510 | AR102: 1CJ
B103: 97 | D103: 61072 | E103: BATTALION SQUADRON HEADQUARTERS - CMC ONLY | F103: M29031 | G103: E | H103: M2903100216 | I103: SURFACE IDC | J103: HM2 | K103: L10A | L103: L03A | M103: N | N103: E | O103: A | P103: A | R103: U | S103: C | AA103: 1 | AP103: 1 | AQ103: A-M510 | AR103: 1CJ
B104: 98 | D104: 61072 | E104: BATTALION SQUADRON HEADQUARTERS - CMC ONLY | F104: M29031 | G104: E | H104: M2903100217 | I104: FLD MED TECH | J104: HM3 | K104: L03A | L104: L03A | M104: N | N104: E | O104: A | P104: A | R104: U | S104: C | AA104: 1 | AP104: 1 | AQ104: A-M510 | AR104: 1CJ
B105: 99 | D105: 61072 | E105: BATTALION SQUADRON HEADQUARTERS - CMC ONLY | F105: M29031 | G105: E | H105: M2903100218 | I105: FLD MED TECH | J105: HM3 | K105: L03A | L105: L03A | M105: N | N105: E | O105: A | P105: A | R105: U | S105: C | AA105: 1 | AP105: 1 | AQ105: A-M510 | AR105: 1CJ
B106: 100 | D106: 61072 | E106: BATTALION SQUADRON HEADQUARTERS - CMC ONLY | F106: M29031 | G106: E | H106: M2903100219 | I106: FLD MED TECH | J106: HM3 | K106: L03A | L106: L03A | M106: N | N106: E | O106: A | P106: A | R106: U | S106: C | AA106: 1 | AP106: 1 | AQ106: A-M510 | AR106: 1CJ
B107: 101 | D107: 61072 | E107: BATTALION SQUADRON HEADQUARTERS - CMC ONLY | F107: M29031 | G107: E | H107: M2903100220 | I107: FLD MED TECH | J107: HM3 | K107: L03A | L107: L03A | M107: N | N107: E | O107: A | P107: A | R107: U | S107: C | AA107: 1 | AP107: 1 | AQ107: A-M510 | AR107: 1CJ
B108: 102 | D108: 61072 | E108: BATTALION SQUADRON HEADQUARTERS - CMC ONLY | F108: M29031 | G108: E | H108: M2903100221 | I108: FLD MED TECH | J108: HN | K108: L03A | L108: L03A | M108: N | N108: E | O108: A | P108: A | R108: U | S108: C | AA108: 1 | AP108: 1 | AQ108: A-M510 | AR108: 1CJ
B109: 103 | D109: 61072 | E109: BATTALION SQUADRON HEADQUARTERS - CMC ONLY | F109: M29031 | G109: E | H109: M2903100222 | I109: FLD MED TECH | J109: HN | K109: L03A | L109: L03A | M109: N | N109: E | O109: A | P109: A | R109: U | S109: C | AA109: 1 | AP109: 1 | AQ109: A-M510 | AR109: 1CJ
B110: 104 | D110: 61072 | E110: BATTALION SQUADRON HEADQUARTERS - CMC ONLY | F110: M29031 | G110: E | H110: M2903100223 | I110: FLD MED TECH | J110: HN | K110: L03A | L110: L03A | M110: N | N110: E | O110: A | P110: A | R110: U | S110: C | AA110: 1 | AP110: 1 | AQ110: A-M510 | AR110: 1CJ
B111: 105 | F111: M29031 | G111: C | H111: M2903100252 | I111: MAINTENANCE SERVICES PLATOON
B112: 106 | F112: M29031 | G112: D | H112: M2903100253 | I112: PLATOON HEADQUARTERS
...

Sheet TE
B4: ROW | C4: NOTE | D4: CCN | E4: CCN Description | F4: CCN 21451 Equipment Type (if applicable) | G4: UIC | H4: TAMCN Short | I4: TAMCN | J4: Nomenclature (Name - Model) | K4: TAM Stat | L4: U/I | M4: Rdy | N4: Ind Qty | O4: Org Qty | P4: Unit T/E | Q4: L, Ft | R4: W, Ft | S4: H, Ft | T4: Volume Ea, ft3 | U4: Volume Total, ft3
B5: 1 | D5: 21710 | E5: ELECTRONICS / COMMUNICATIONS MAINTENANCE SHOP | G5: M29031 | H5: A0022 | I5: A00227G | J5: COMPUTER SYSTEM,DIG - 16007A0000 | K5: IS | L5: EA | M5: N | N5: 0 | O5: 4 | P5: 4 | Q5: 1.75 | R5: 1.42 | S5: 1.42 | T5: 3.5287 | U5: 14.1148
B6: =1+B5 -> 2 | D6: 44112 | E6: STORAGE OF AIR OR GROUND ORGANIC UNITS FOR MARINE CORPS | G6: M29031 | H6: A0047 | I6: A00477B | J6: SHELTER,EXPANDABLE - 09021A0000 | K6: IS | L6: EA | M6: N | N6: 0 | O6: 1 | P6: 1 | Q6: 20 | R6: 8 | S6: 8 | T6: 1280 | U6: 1280
B7: =1+B6 -> 3 | D7: 21710 | E7: ELECTRONICS / COMMUNICATIONS MAINTENANCE SHOP | G7: M29031 | H7: A0061 | I7: A00617G | J7: MAST SECTION - TEAMS TRAILER | K7: IS | L7: EA | M7: N | N7: 0 | O7: 0 | P7: 0 | Q7: 8.83 | R7: 8.5 | S7: 8.83 | T7: 662.73565 | U7: 0
B8: =1+B7 -> 4 | D8: 21710 | E8: ELECTRONICS / COMMUNICATIONS MAINTENANCE SHOP | G8: M29031 | H8: A0067 | I8: A00677G | J8: RADIO SET - AN/MRC-148A | K8: IS | L8: EA | M8: M | N8: 0 | O8: 3 | P8: 3 | Q8: 7.16 | R8: 6.25 | S8: 4.66 | T8: 208.535 | U8: 625.605
B9: =1+B8 -> 5 | D9: 21710 | E9: ELECTRONICS / COMMUNICATIONS MAINTENANCE SHOP | G9: M29031 | H9: A0073 | I9: A00732B | J9: CHARGER,BATTERY - BTC-70100 | K9: IS | L9: EA | M9: N | N9: 0 | O9: 2 | P9: 2 | Q9: 1.67 | R9: 1.08 | S9: 0.52 | T9: 0.937872 | U9: 1.875744
B10: =1+B9 -> 6 | D10: 21710 | E10: ELECTRONICS / COMMUNICATIONS MAINTENANCE SHOP | G10: M29031 | H10: A0097 | I10: A00977G | J10: RADIO SET - AN/VRC-110 | K10: DP | L10: EA | M10: N | N10: 0 | O10: 2 | P10: 2 | Q10: 1.17 | R10: 0.67 | S10: 0.92 | T10: 0.721188 | U10: 1.442376
B11: =1+B10 -> 7 | D11: 21710 | E11: ELECTRONICS / COMMUNICATIONS MAINTENANCE SHOP | G11: M29031 | H11: A0117 | I11: A01177G | J11: MARINE ELECTROMAGNETIC WARFARE GROUND FAMILY OF SYSTEMS (MEGFOS) -MOUNTED, HEAVY - | K11: PL | L11: 0 | M11: N | N11: 0 | O11: 1 | P11: 1 | Q11: 0 | R11: 0 | S11: 0 | T11: 0 | U11: 0
B12: =1+B11 -> 8 | D12: 21710 | E12: ELECTRONICS / COMMUNICATIONS MAINTENANCE SHOP | G12: M29031 | H12: A0118 | I12: A01187G | J12: RADIO SET - AN/PRC-153(V)1 | K12: DP | L12: EA | M12: N | N12: 0 | O12: 64 | P12: 64 | Q12: 0.57 | R12: 0.22 | S12: 0.57 | T12: 0.071478 | U12: 4.574592
B13: =1+B12 -> 9 | D13: 21710 | E13: ELECTRONICS / COMMUNICATIONS MAINTENANCE SHOP | G13: M29031 | H13: A0126 | I13: A01267G | J13: MULTI-BAND FREQUENC - AN/VRC-103(V)2 | K13: DP | L13: EA | M13: N | N13: 0 | O13: 3 | P13: 3 | Q13: 1.24 | R13: 1.25 | S13: 0.82 | T13: 1.271 | U13: 3.813
B14: =1+B13 -> 10 | D14: 21710 | E14: ELECTRONICS / COMMUNICATIONS MAINTENANCE SHOP | G14: M29031 | H14: A0139 | I14: A01397G | J14: RADIO SET - AN/TRC-209A(C)V1 | K14: IS | L14: EA | M14: R | N14: 0 | O14: 3 | P14: 3 | Q14: 6.75 | R14: 2.17 | S14: 3 | T14: 43.9425 | U14: 131.8275
B15: =1+B14 -> 11 | D15: 21710 | E15: ELECTRONICS / COMMUNICATIONS MAINTENANCE SHOP | G15: M29031 | H15: A0162 | I15: A01627G | J15: MEGFOS-BACKPACK, USER - | K15: PL | L15: 0 | M15: N | N15: 0 | O15: 3 | P15: 3 | Q15: 0 | R15: 0 | S15: 0 | T15: 0 | U15: 0
B16: =1+B15 -> 12 | D16: 21710 | E16: ELECTRONICS / COMMUNICATIONS MAINTENANCE SHOP | G16: M29031 | H16: A0173 | I16: A01737G | J16: SECURITY DATA SYSTE - AN/GSQ-274A | K16: IS | L16: EA | M16: M | N16: 0 | O16: 2 | P16: 2 | Q16: 3.04 | R16: 1.87 | S16: 1.36 | T16: 7.731328 | U16: 15.462656
B17: =1+B16 -> 13 | D17: 21710 | E17: ELECTRONICS / COMMUNICATIONS MAINTENANCE SHOP | G17: M29031 | H17: A0174 | I17: A01747G | J17: SWITCHING SET,COMMU - AN/TYQ-148B | K17: IS | L17: EA | M17: M | N17: 0 | O17: 1 | P17: 1 | Q17: 3.04 | R17: 1.87 | S17: 1.65 | T17: 9.37992 | U17: 9.37992
B18: =1+B17 -> 14 | D18: 21710 | E18: ELECTRONICS / COMMUNICATIONS MAINTENANCE SHOP | G18: M29031 | H18: A0175 | I18: A01757G | J18: COMPUTER,DIGITAL DA - 15021A0000-0 | K18: IS | L18: EA | M18: R | N18: 0 | O18: 2 | P18: 2 | Q18: 1.25 | R18: 1.65 | S18: 0.44 | T18: 0.9075 | U18: 1.815
B19: =1+B18 -> 15 | D19: 21710 | E19: ELECTRONICS / COMMUNICATIONS MAINTENANCE SHOP | G19: M29031 | H19: A0176 | I19: A01767G | J19: SWITCHING GROUP,DIG - ON-704B/TYC | K19: IS | L19: EA | M19: R | N19: 0 | O19: 8 | P19: 8 | Q19: 2.63 | R19: 1.71 | S19: 1.04 | T19: 4.677192 | U19: 37.417536
B20: =1+B19 -> 16 | D20: 21710 | E20: ELECTRONICS / COMMUNICATIONS MAINTENANCE SHOP | G20: M29031 | H20: A0177 | I20: A01777G | J20: COMPUTER SYSTEM,DIG - 15017A0000-00 | K20: IS | L20: EA | M20: M | N20: 0 | O20: 2 | P20: 2 | Q20: 3.04 | R20: 1.87 | S20: 1.07 | T20: 6.082736 | U20: 12.165472
B21: =1+B20 -> 17 | D21: #N/A | E21: #N/A | G21: M29031 | H21: A0198 | I21: A01987G | J21: RADIO SET - 12200-1823-01 | K21: IS | L21: EA | M21: N | N21: 0 | O21: 5 | P21: 5 | Q21: 0 | R21: 0 | S21: 0 | T21: 0 | U21: 0
B22: =1+B21 -> 18 | D22: 21710 | E22: ELECTRONICS / COMMUNICATIONS MAINTENANCE SHOP | G22: M29031 | H22: A0205 | I22: A02057G | J22: RADIO SET - 12167-0100-02 | K22: PL | L22: EA | M22: N | N22: 0 | O22: 6 | P22: 6 | Q22: 0 | R22: 0 | S22: 0 | T22: 0 | U22: 0
B23: =1+B22 -> 19 | D23: 21710 | E23: ELECTRONICS / COMMUNICATIONS MAINTENANCE SHOP | G23: M29031 | H23: A0206 | I23: A02067G | J23: RADIO SET - VRC | K23: IS | L23: EA | M23: N | N23: 0 | O23: 4 | P23: 4 | Q23: 0 | R23: 0 | S23: 0 | T23: 0 | U23: 0
B24: =1+B23 -> 20 | D24: 21710 | E24: ELECTRONICS / COMMUNICATIONS MAINTENANCE SHOP | G24: M29031 | H24: A0207 | I24: A02077G | J24: RADIO SET - | K24: IS | L24: EA | M24: N | N24: 0 | O24: 36 | P24: 36 | Q24: 0 | R24: 0 | S24: 0 | T24: 0 | U24: 0
B25: =1+B24 -> 21 | D25: 21710 | E25: ELECTRONICS / COMMUNICATIONS MAINTENANCE SHOP | G25: M29031 | H25: A0208 | I25: A02087G | J25: AMPLIFIER-POWER SUP - VRC | K25: PL | L25: EA | M25: N | N25: 0 | O25: 10 | P25: 10 | Q25: 0 | R25: 0 | S25: 0 | T25: 0 | U25: 0
B26: =1+B25 -> 22 | D26: 21710 | E26: ELECTRONICS / COMMUNICATIONS MAINTENANCE SHOP | G26: M29031 | H26: A0210 | I26: A02107G | J26: ANTENNA GROUP - OE-4703/G | K26: IS | L26: EA | M26: N | N26: 0 | O26: 6 | P26: 6 | Q26: 1.54 | R26: 0.5 | S26: 0.5 | T26: 0.385 | U26: 2.31
B27: =1+B26 -> 23 | D27: 21710 | E27: ELECTRONICS / COMMUNICATIONS MAINTENANCE SHOP | G27: M29031 | H27: A0211 | I27: A02117G | J27: ANTENNA GROUP - OE-4702/G | K27: IS | L27: EA | M27: N | N27: 0 | O27: 6 | P27: 6 | Q27: 2.08 | R27: 0.42 | S27: 0.42 | T27: 0.366912 | U27: 2.201472
B28: =1+B27 -> 24 | D28: 21710 | E28: ELECTRONICS / COMMUNICATIONS MAINTENANCE SHOP | G28: M29031 | H28: A0266 | I28: A02667G | J28: RADIO SET - AN/VRC-104C | K28: IS | L28: EA | M28: R | N28: 0 | O28: 10 | P28: 10 | Q28: 1.29 | R28: 1.07 | S28: 1.5 | T28: 2.07045 | U28: 20.7045
B29: =1+B28 -> 25 | D29: 21710 | E29: ELECTRONICS / COMMUNICATIONS MAINTENANCE SHOP | G29: M29031 | H29: A0272 | I29: A02727G | J29: RADIO SET CONTROL G - OK-686/PRC | K29: IS | L29: EA | M29: N | N29: 0 | O29: 12 | P29: 12 | Q29: 0.74 | R29: 0.65 | S29: 0.27 | T29: 0.12987 | U29: 1.55844
B30: =1+B29 -> 26 | D30: 21710 | E30: ELECTRONICS / COMMUNICATIONS MAINTENANCE SHOP | G30: M29031 | H30: A0298 | I30: A02987G | J30: OPTICAL READER,DATA - CN80G | K30: IS | L30: EA | M30: N | N30: 0 | O30: 9 | P30: 9 | Q30: 1 | R30: 1 | S30: 1 | T30: 1 | U30: 9
B31: =1+B30 -> 27 | D31: 21710 | E31: ELECTRONICS / COMMUNICATIONS MAINTENANCE SHOP | G31: M29031 | H31: A0300 | I31: A03007G | J31: PRINTER,AUTOMATIC D - PD42 PRINTER | K31: IS | L31: EA | M31: N | N31: 0 | O31: 1 | P31: 1 | Q31: 2 | R31: 1 | S31: 1 | T31: 2 | U31: 2
B32: =1+B31 -> 28 | D32: 21710 | E32: ELECTRONICS / COMMUNICATIONS MAINTENANCE SHOP | G32: M29031 | H32: A0312 | I32: A03127G | J32: INTERFACE UNIT,COMM - J-6884A/TYQ | K32: IS | L32: EA | M32: R | N32: 0 | O32: 1 | P32: 1 | Q32: 3.04 | R32: 1.87 | S32: 1.22 | T32: 6.935456 | U32: 6.935456
B33: =1+B32 -> 29 | D33: 21710 | E33: ELECTRONICS / COMMUNICATIONS MAINTENANCE SHOP | G33: M29031 | H33: A0331 | I33: A03317G | J33: RADIO SET - AN/VRC-113(C) | K33: IS | L33: EA | M33: N | N33: 0 | O33: 6 | P33: 6 | Q33: 1.2 | R33: 1.04 | S33: 0.92 | T33: 1.14816 | U33: 6.88896
... B38: =1+B37 -> 34 | D38: 21710 | E38: ELECTRONICS / COMMUNICATIONS MAINTENANCE SHOP | G38: M29031 | H38: A0874 | I38: A08747G | J38: WORKSTATION,PORTABL - AN/PYQ-25 | K38: IS | L38: EA | M38: R | N38: 0 | O38: 3 | P38: 3 | Q38: 2.83 | R38: 2.08 | S38: 4 | T38: 23.5456 | U38: 70.6368
B39: =1+B38 -> 35 | D39: 21710 | E39: ELECTRONICS / COMMUNICATIONS MAINTENANCE SHOP | G39: M29031 | H39: A1260 | I39: A12607GK | J39: NAVIGATION SET,SATE - AN/PSN-13(A) | K39: IS | L39: EA | M39: 0 | N39: 0 | O39: 6 | P39: 6 | Q39: 0.58 | R39: 0.33 | S39: 0.17 | T39: 0.032538 | U39: 0.195228
B40: =1+B39 -> 36 | D40: 21710 | E40: ELECTRONICS / COMMUNICATIONS MAINTENANCE SHOP | G40: M29031 | H40: A1260 | I40: A12607G | J40: NAVIGATION SET,SATE - AN/PSN-13(A) | K40: IS | L40: EA | M40: N | N40: 0 | O40: 5 | P40: 5 | Q40: 0.58 | R40: 0.33 | S40: 0.17 | T40: 0.032538 | U40: 0.16269
B41: =1+B40 -> 37 | D41: 21710 | E41: ELECTRONICS / COMMUNICATIONS MAINTENANCE SHOP | G41: M29031 | H41: A1260 | I41: A12607GL | J41: RECEIVER,RADIO NAVI - AN/PSN-13(B) | K41: IS | L41: EA | M41: 0 | N41: 0 | O41: 0 | P41: 0 | Q41: 0.58 | R41: 0.33 | S41: 0.17 | T41: 0.032538 | U41: 0
B42: =1+B41 -> 38 | D42: 21710 | E42: ELECTRONICS / COMMUNICATIONS MAINTENANCE SHOP | G42: M29031 | H42: A2042 | I42: A20427G | J42: RADIO SET - AN/PRC-150 (C) | K42: DP | L42: EA | M42: N | N42: 0 | O42: 5 | P42: 5 | Q42: 1.12 | R42: 0.87 | S42: 0.25 | T42: 0.2436 | U42: 1.218
B43: =1+B42 -> 39 | D43: 21710 | E43: ELECTRONICS / COMMUNICATIONS MAINTENANCE SHOP | G43: M29031 | H43: A2043 | I43: A20437G | J43: MBITR URBAN VERSION - AN/PRC-148(V)2 | K43: DP | L43: 0 | M43: N | N43: 0 | O43: 36 | P43: 36 | Q43: 0.7 | R43: 0.22 | S43: 0.13 | T43: 0.02002 | U43: 0.72072
B44: =1+B43 -> 40 | D44: 21710 | E44: ELECTRONICS / COMMUNICATIONS MAINTENANCE SHOP | G44: M29031 | H44: A2068 | I44: A20687G | J44: RADIO SET - AN/PRC-117F(V)1C | K44: DP | L44: EA | M44: N | N44: 0 | O44: 11 | P44: 11 | Q44: 1.17 | R44: 0.92 | S44: 0.33 | T44: 0.355212 | U44: 3.907332
B45: =1+B44 -> 41 | D45: 44112 | E45: STORAGE OF AIR OR GROUND ORGANIC UNITS FOR MARINE CORPS | G45: M29031 | H45: A2337 | I45: A23372B | J45: SHELTER,NONEXPANDAB - 82A5050B0000 | K45: IS | L45: EA | M45: N | N45: 0 | O45: 1 | P45: 1 | Q45: 20 | R45: 8 | S45: 8 | T45: 1280 | U45: 1280
B46: =1+B45 -> 42 | D46: 44112 | E46: STORAGE OF AIR OR GROUND ORGANIC UNITS FOR MARINE CORPS | G46: M29031 | H46: A2338 | I46: A23382B | J46: SHELTER,NONEXPANDAB - 87036B0000 | K46: IS | L46: EA | M46: N | N46: 0 | O46: 2 | P46: 2 | Q46: 10 | R46: 8 | S46: 8 | T46: 640 | U46: 1280
B47: =1+B46 -> 43 | D47: 21710 | E47: ELECTRONICS / COMMUNICATIONS MAINTENANCE SHOP | G47: M29031 | H47: A7001 | I47: A70017G | J47: TEST SET,OPTICAL PO - PX-D110M | K47: IS | L47: EA | M47: N | N47: 0 | O47: 1 | P47: 1 | Q47: 1.67 | R47: 2 | S47: 0.83 | T47: 2.7722 | U47: 2.7722
B48: =1+B47 -> 44 | D48: 21710 | E48: ELECTRONICS / COMMUNICATIONS MAINTENANCE SHOP | G48: M29031 | H48: A7005 | I48: A70057G | J48: ANALYZER,SPECTRUM - FSV40-N | K48: IS | L48: EA | M48: N | N48: 0 | O48: 1 | P48: 1 | Q48: 1.33 | R48: 1.33 | S48: 0.67 | T48: 1.185163 | U48: 1.185163
B49: =1+B48 -> 45 | D49: 21710 | E49: ELECTRONICS / COMMUNICATIONS MAINTENANCE SHOP | G49: M29031 | H49: A7059 | I49: A70597G | J49: OHMMETER - R1L-C | K49: IS | L49: EA | M49: N | N49: 0 | O49: 1 | P49: 1 | Q49: 0.92 | R49: 1.17 | S49: 0.58 | T49: 0.624312 | U49: 0.624312
B50: =1+B49 -> 46 | D50: 21710 | E50: ELECTRONICS / COMMUNICATIONS MAINTENANCE SHOP | G50: M29031 | H50: A7061 | I50: A70617G | J50: OSCILLOSCOPE - FLK199C | K50: IS | L50: EA | M50: N | N50: 0 | O50: 2 | P50: 2 | Q50: 1.5 | R50: 1.17 | S50: 0.5 | T50: 0.8775 | U50: 1.755
B51: =1+B50 -> 47 | D51: 21710 | E51: ELECTRONICS / COMMUNICATIONS MAINTENANCE SHOP | G51: M29031 | H51: A7080 | I51: A70807G | J51: TEST SET,RADIO - 3515N | K51: IS | L51: EA | M51: N | N51: 0 | O51: 5 | P51: 5 | Q51: 1 | R51: 0.83 | S51: 0.25 | T51: 0.2075 | U51: 1.0375
B52: =1+B51 -> 48 | D52: 21710 | E52: ELECTRONICS / COMMUNICATIONS MAINTENANCE SHOP | G52: M29031 | H52: A7086 | I52: A70867G | J52: REFLECTOMETER,OPTIC - TB4000-NV-C | K52: IS | L52: EA | M52: N | N52: 0 | O52: 1 | P52: 1 | Q52: 0.83 | R52: 0.85 | S52: 0.44 | T52: 0.31042 | U52: 0.31042
B53: =1+B52 -> 49 | D53: #N/A | E53: #N/A | G53: M29031 | H53: A7502 | I53: A75022H | J53: ADAPTER SET,TEST - | K53: IS | L53: EA | M53: N | N53: 0 | O53: 3 | P53: 3 | Q53: 0 | R53: 0 | S53: 0 | T53: 0 | U53: 0
B54: =1+B53 -> 50 | D54: 21710 | E54: ELECTRONICS / COMMUNICATIONS MAINTENANCE SHOP | G54: M29031 | H54: A7504 | I54: A75047G | J54: MAINTENANCE KIT,ELE - GETAC B360-GEN2 | K54: IS | L54: EA | M54: N | N54: 0 | O54: 10 | P54: 10 | Q54: 1.83 | R54: 1.33 | S54: 1 | T54: 2.4339 | U54: 24.339
B55: =1+B54 -> 51 | D55: #N/A | E55: #N/A | G55: M29031 | H55: A7505 | I55: A75057H | J55: TEST SET,RADIO - | K55: PL | L55: KT | M55: N | N55: 0 | O55: 5 | P55: 5 | Q55: 0 | R55: 0 | S55: 0 | T55: 0 | U55: 0
B56: =1+B55 -> 52 | D56: 21710 | E56: ELECTRONICS / COMMUNICATIONS MAINTENANCE SHOP | G56: M29031 | H56: A7705 | I56: A77057G | J56: POWER SUPPLY 18-30V - PP8474/G | K56: IS | L56: EA | M56: N | N56: 0 | O56: 3 | P56: 3 | Q56: 1.42 | R56: 0.66 | S56: 0.94 | T56: 0.880968 | U56: 2.642904
B57: =1+B56 -> 53 | D57: 21710 | E57: ELECTRONICS / COMMUNICATIONS MAINTENANCE SHOP | G57: M29031 | H57: A7706 | I57: A77067G | J57: POWER SUPPLY - XHR40-25M106 | K57: IS | L57: EA | M57: N | N57: 0 | O57: 5 | P57: 5 | Q57: 2.04 | R57: 1.27 | S57: 0.67 | T57: 1.735836 | U57: 8.67918
B58: =1+B57 -> 54 | D58: 21710 | E58: ELECTRONICS / COMMUNICATIONS MAINTENANCE SHOP | G58: M29031 | H58: A7902 | I58: A79022E | J58: TOOL KIT,ELECTRONIC - TK-2800 | K58: IS | L58: EA | M58: N | N58: 0 | O58: 3 | P58: 3 | Q58: 1.67 | R58: 1.42 | S58: 1.33 | T58: 3.153962 | U58: 9.461886
B59: =1+B58 -> 55 | D59: 21710 | E59: ELECTRONICS / COMMUNICATIONS MAINTENANCE SHOP | G59: M29031 | H59: A8001 | I59: A80017GA | J59: ENCRYPTION-DECRYPTI - KGV-72 | K59: IS | L59: EA | M59: 0 | N59: 0 | O59: 6 | P59: 6 | Q59: 0.67 | R59: 0.25 | S59: 0.42 | T59: 0.07035 | U59: 0.4221
B60: =1+B59 -> 56 | D60: 21710 | E60: ELECTRONICS / COMMUNICATIONS MAINTENANCE SHOP | G60: M29031 | H60: A8006 | I60: A80067GC | J60: ENCRYPTION-DECRYPTI - KG-250XS | K60: IS | L60: EA | M60: 0 | N60: 0 | O60: 2 | P60: 2 | Q60: 0.33 | R60: 0.33 | S60: 0.17 | T60: 0.018513 | U60: 0.037026
B61: =1+B60 -> 57 | D61: 21710 | E61: ELECTRONICS / COMMUNICATIONS MAINTENANCE SHOP | G61: M29031 | H61: A8023 | I61: A80237G | J61: TRANSFER UNIT,CRYPT - AN/PYQ-10 | K61: IS | L61: EA | M61: N | N61: 0 | O61: 8 | P61: 8 | Q61: 0.67 | R61: 0.42 | S61: 0.25 | T61: 0.07035 | U61: 0.5628
B62: =1+B61 -> 58 | D62: 21710 | E62: ELECTRONICS / COMMUNICATIONS MAINTENANCE SHOP | G62: M29031 | H62: A8084 | I62: A80847G | J62: ENCRYPTION-DECRYPTI - KIV-7M | K62: IS | L62: EA | M62: N | N62: 0 | O62: 6 | P62: 6 | Q62: 0.67 | R62: 0.5 | S62: 0.08 | T62: 0.0268 | U62: 0.1608
B63: =1+B62 -> 59 | D63: 21710 | E63: ELECTRONICS / COMMUNICATIONS MAINTENANCE SHOP | G63: M29031 | H63: A8084 | I63: A80847GB | J63: ENCRYPTION-DECRYPTI - KIV-7M | K63: IS | L63: EA | M63: 0 | N63: 0 | O63: 4 | P63: 4 | Q63: 0.67 | R63: 0.5 | S63: 0.08 | T63: 0.0268 | U63: 0.1072
B64: =1+B63 -> 60 | D64: 21710 | E64: ELECTRONICS / COMMUNICATIONS MAINTENANCE SHOP | G64: M29031 | H64: A8088 | I64: A80887G | J64: ENCRYPTION-DECRYPTI - KG-175D | K64: IS | L64: EA | M64: N | N64: 0 | O64: 2 | P64: 2 | Q64: 0.92 | R64: 0.5 | S64: 0.17 | T64: 0.0782 | U64: 0.1564
B65: =1+B64 -> 61 | D65: 21710 | E65: ELECTRONICS / COMMUNICATIONS MAINTENANCE SHOP | G65: M29031 | H65: A8088 | I65: A80887GB | J65: ENCRYPTION-DECRYPTI - KG-175D | K65: IS | L65: EA | M65: 0 | N65: 0 | O65: 4 | P65: 4 | Q65: 0.92 | R65: 0.5 | S65: 0.17 | T65: 0.0782 | U65: 0.3128
B66: =1+B65 -> 62 | D66: 21710 | E66: ELECTRONICS / COMMUNICATIONS MAINTENANCE SHOP | G66: M29031 | H66: A9012 | I66: A90122G | J66: MAINTENANCE KIT,ELE - | K66: PL | L66: EA | M66: N | N66: 0 | O66: 1 | P66: 1 | Q66: 0 | R66: 0 | S66: 0 | T66: 0 | U66: 0
B67: =1+B66 -> 63 | D67: 21710 | E67: ELECTRONICS / COMMUNICATIONS MAINTENANCE SHOP | G67: M29031 | H67: A9015 | I67: A90157G | J67: THEATER MEDICAL INF - EVO73AV | K67: IS | L67: EA | M67: N | N67: 0 | O67: 2 | P67: 2 | Q67: 1.11 | R67: 1.11 | S67: 0.08 | T67: 0.098568 | U67: 0.197136
B68: =1+B67 -> 64 | D68: 21710 | E68: ELECTRONICS / COMMUNICATIONS MAINTENANCE SHOP | G68: M29031 | H68: A9023 | I68: A90237GD | J68: COMPUTER SYSTEM,DIG - 210-BDTH | K68: IS | L68: EA | M68: 0 | N68: 0 | O68: 2 | P68: 2 | Q68: 1 | R68: 1.25 | S68: 0.17 | T68: 0.2125 | U68: 0.425
B69: =1+B68 -> 65 | D69: 21710 | E69: ELECTRONICS / COMMUNICATIONS MAINTENANCE SHOP | G69: M29031 | H69: A9025 | I69: A90257GB | J69: COMPUTER,SERVER - SEVERAL | K69: DP | L69: EA | M69: 0 | N69: 0 | O69: 4 | P69: 4 | Q69: 2 | R69: 1.42 | S69: 0.25 | T69: 0.71 | U69: 2.84
B70: =1+B69 -> 66 | D70: 21710 | E70: ELECTRONICS / COMMUNICATIONS MAINTENANCE SHOP | G70: M29031 | H70: A9089 | I70: A90897G | J70: COMPUTER SET,DIGITA - AN/GYK-62H | K70: IS | L70: EA | M70: N | N70: 0 | O70: 2 | P70: 2 | Q70: 4 | R70: 2.5 | S70: 1.75 | T70: 17.5 | U70: 35
B71: =1+B70 -> 67 | D71: 21710 | E71: ELECTRONICS / COMMUNICATIONS MAINTENANCE SHOP | G71: M29031 | H71: A9100 | I71: A91007GL | J71: COMPUTER SYSTEM,DIG - SEVERAL | K71: DP | L71: EA | M71: 0 | N71: 0 | O71: 0 | P71: 0 | Q71: 0.83 | R71: 1.17 | S71: 0.17 | T71: 0.165087 | U71: 0
B72: =1+B71 -> 68 | D72: 21710 | E72: ELECTRONICS / COMMUNICATIONS MAINTENANCE SHOP | G72: M29031 | H72: A9100 | I72: A91007G | J72: COMPUTER SYSTEM,DIG - HP ELITEBOOK 645 | K72: IS | L72: EA | M72: N | N72: 0 | O72: 180 | P72: 180 | Q72: 0.83 | R72: 1.17 | S72: 0.17 | T72: 0.165087 | U72: 29.71566
B73: =1+B72 -> 69 | D73: 21710 | E73: ELECTRONICS / COMMUNICATIONS MAINTENANCE SHOP | G73: M29031 | H73: A9100 | I73: A91007GM | J73: COMPUTER SYSTEM,DIG - 210-AFUC | K73: DP | L73: EA | M73: 0 | N73: 0 | O73: 2 | P73: 2 | Q73: 0.83 | R73: 1.17 | S73: 0.17 | T73: 0.165087 | U73: 0.330174
B74: =1+B73 -> 70 | D74: 21820 | E74: CONSTRUCTION / WEIGHT HANDLING EQUIPMENT SHOP | G74: M29031 | H74: B0008 | I74: B00087BB | J74: AIR CONDITIONER - GL0583ZAADWYX11 | K74: IS | L74: EA | M74: 0 | N74: 0 | O74: 1 | P74: 1 | Q74: 3.97 | R74: 3.08 | S74: 3.95 | T74: 48.29902 | U74: 48.29902
B75: =1+B74 -> 71 | D75: #N/A | E75: #N/A | G75: M29031 | H75: C0010 | I75: C00102F | J75: CARRIER,SMALL ARMS - | K75: IS | L75: EA | M75: N | N75: 122 | O75: 0 | P75: 122 | Q75: 1.17 | R75: 0.29 | S75: 1.75 | T75: 0.593775 | U75: 72.44055
B76: =1+B75 -> 72 | D76: CSP | E76: #N/A | G76: M29031 | H76: C0015 | I76: C00152E | J76: INSERT,SMALL ARMS P - 95662 | K76: IS | L76: EA | M76: N | N76: 244 | O76: 0 | P76: 244 | Q76: 0.67 | R76: 0.5 | S76: 0.08 | T76: 0.0268 | U76: 6.5392
B77: =1+B76 -> 73 | D77: CSP | E77: #N/A | G77: M29031 | H77: C0029 | I77: C00292F | J77: DRAWERS,COLD WEATHE - FRGFDR | K77: IS | L77: PR | M77: N | N77: 122 | O77: 0 | P77: 122 | Q77: 0.83 | R77: 0.5 | S77: 0.17 | T77: 0.07055 | U77: 8.6071
B78: =1+B77 -> 74 | D78: CSP | E78: #N/A | G78: M29031 | H78: C0040 | I78: C00402E | J78: PAD,KNEE - MEDIUM | K78: IS | L78: 0 | M78: N | N78: 31 | O78: 0 | P78: 31 | Q78: 0.96 | R78: 0.67 | S78: 0.42 | T78: 0.270144 | U78: 8.374464
B79: =1+B78 -> 75 | D79: CSP | E79: #N/A | G79: M29031 | H79: C0041 | I79: C00412E | J79: ELBOW PADS,EXTERNAL - SMALL | K79: IS | L79: 0 | M79: N | N79: 31 | O79: 0 | P79: 31 | Q79: 0.87 | R79: 0.46 | S79: 0.46 | T79: 0.184092 | U79: 5.706852
B80: =1+B79 -> 76 | D80: CSP | E80: #N/A | G80: M29031 | H80: C0061 | I80: C00612F | J80: CARRIER,SMALL ARMS - PC GEN II | K80: IS | L80: EA | M80: N | N80: 122 | O80: 0 | P80: 122 | Q80: 2 | R80: 1.5 | S80: 0.67 | T80: 2.01 | U80: 245.22
B81: =1+B80 -> 77 | D81: 44112 | E81: STORAGE OF AIR OR GROUND ORGANIC UNITS FOR MARINE CORPS | G81: M29031 | H81: C0062 | I81: C00622F | J81: COAT,CHEMICAL PROTE - UNIVERSAL COAT | K81: IS | L81: EA | M81: N | N81: 244 | O81: 0 | P81: 244 | Q81: 1.08 | R81: 0.58 | S81: 0.25 | T81: 0.1566 | U81: 38.2104
B82: =1+B81 -> 78 | D82: 44112 | E82: STORAGE OF AIR OR GROUND ORGANIC UNITS FOR MARINE CORPS | G82: M29031 | H82: C0063 | I82: C00632F | J82: TROUSERS,CHEMICAL P - UNIVERSAL TROU | K82: IS | L82: PR | M82: N | N82: 244 | O82: 0 | P82: 244 | Q82: 1.08 | R82: 0.75 | S82: 0.17 | T82: 0.1377 | U82: 33.5988
B83: =1+B82 -> 79 | D83: CSP | E83: #N/A | G83: M29031 | H83: C0074 | I83: C00742E | J83: FLASHLIGHT - 14032 | K83: IS | L83: EA | M83: N | N83: 122 | O83: 0 | P83: 122 | Q83: 0.25 | R83: 0.08 | S83: 0.08 | T83: 0.0016 | U83: 0.1952
B84: =1+B83 -> 80 | D84: CSP | E84: #N/A | G84: M29031 | H84: C0083 | I84: C00832E | J84: STRAP CUTTER,RESCUE - 1431 | K84: IS | L84: EA | M84: N | N84: 122 | O84: 0 | P84: 122 | Q84: 0.58 | R84: 0.17 | S84: 0.08 | T84: 0.007888 | U84: 0.962336
B85: =1+B84 -> 81 | D85: CSP | E85: #N/A | G85: M29031 | H85: C0115 | I85: C01152F | J85: DRAWERS,COLD WEATHE - FRDRCW | K85: IS | L85: PR | M85: N | N85: 244 | O85: 0 | P85: 244 | Q85: 0.83 | R85: 0.5 | S85: 0.17 | T85: 0.07055 | U85: 17.2142
B86: =1+B85 -> 82 | D86: CSP | E86: #N/A | G86: M29031 | H86: C0116 | I86: C01162F | J86: UNDERSHIRT,COLD WEA - FRUSHCW | K86: IS | L86: EA | M86: N | N86: 244 | O86: 0 | P86: 244 | Q86: 0.83 | R86: 0.5 | S86: 0.17 | T86: 0.07055 | U86: 17.2142
B87: =1+B86 -> 83 | D87: CSP | E87: #N/A | G87: M29031 | H87: C0117 | I87: C01172F | J87: SHIRT,COLD WEATHER - FRGFP07 | K87: IS | L87: EA | M87: N | N87: 122 | O87: 0 | P87: 122 | Q87: 0.83 | R87: 0.5 | S87: 0.17 | T87: 0.07055 | U87: 8.6071
B88: =1+B87 -> 84 | D88: 44112 | E88: STORAGE OF AIR OR GROUND ORGANIC UNITS FOR MARINE CORPS | G88: M29031 | H88: C0120 | I88: C01202E | J88: HELMET,GROUND TROOP - ECH | K88: IS | L88: EA | M88: N | N88: 122 | O88: 0 | P88: 122 | Q88: 1 | R88: 1 | S88: 1 | T88: 1 | U88: 122
B89: =1+B88 -> 85 | D89: CSP | E89: #N/A | G89: M29031 | H89: C0132 | I89: C01322B | J89: PAPER,CHEMICAL AGEN - M8 | K89: IS | L89: BK | M89: N | N89: 122 | O89: 0 | P89: 122 | Q89: 0 | R89: 0 | S89: 0 | T89: 0 | U89: 0
B90: =1+B89 -> 86 | D90: CSP | E90: #N/A | G90: M29031 | H90: C0135 | I90: C01352F | J90: BOOTS,COLD WEATHER - C/W RAT | K90: IS | L90: EA | M90: N | N90: 122 | O90: 0 | P90: 122 | Q90: 1 | R90: 1 | S90: 0.5 | T90: 0.5 | U90: 61
B91: =1+B90 -> 87 | D91: CSP | E91: #N/A | G91: M29031 | H91: C0136 | I91: C01362F | J91: BOOTS,HOT WEATHER - H/W RAT | K91: IS | L91: EA | M91: N | N91: 122 | O91: 0 | P91: 122 | Q91: 1 | R91: 1 | S91: 0.5 | T91: 0.5 | U91: 61
B92: =1+B91 -> 88 | D92: CSP | E92: #N/A | G92: M29031 | H92: C0137 | I92: C01372F | J92: JACKET,COMBAT - N/A | K92: IS | L92: EA | M92: N | N92: 122 | O92: 0 | P92: 122 | Q92: 1.12 | R92: 1 | S92: 0.25 | T92: 0.28 | U92: 34.16
B93: =1+B92 -> 89 | D93: 44112 | E93: STORAGE OF AIR OR GROUND ORGANIC UNITS FOR MARINE CORPS | G93: M29031 | H93: C0169 | I93: C01692F | J93: MAT,SLEEPING - ISM | K93: IS | L93: EA | M93: N | N93: 122 | O93: 0 | P93: 122 | Q93: 0 | R93: 0 | S93: 0 | T93: 0 | U93: 0
B94: =1+B93 -> 90 | D94: 44112 | E94: STORAGE OF AIR OR GROUND ORGANIC UNITS FOR MARINE CORPS | G94: M29031 | H94: C0170 | I94: C01702F | J94: LINER,WET WEATHER P - N/A | K94: IS | L94: EA | M94: N | N94: 122 | O94: 0 | P94: 122 | Q94: 0 | R94: 0 | S94: 0 | T94: 0 | U94: 0
B95: =1+B94 -> 91 | D95: CSP | E95: #N/A | G95: M29031 | H95: C0180 | I95: C01802F | J95: BELT,INDIVIDUAL EQU - N/A | K95: IS | L95: EA | M95: N | N95: 122 | O95: 0 | P95: 122 | Q95: 1 | R95: 0.33 | S95: 0.33 | T95: 0.1089 | U95: 13.2858
B96: =1+B95 -> 92 | D96: 44112 | E96: STORAGE OF AIR OR GROUND ORGANIC UNITS FOR MARINE CORPS | G96: M29031 | H96: C0188 | I96: C01882F | J96: No Item Name Availa - N/A | K96: IS | L96: EA | M96: N | N96: 64 | O96: 0 | P96: 64 | Q96: 0.33 | R96: 0.17 | S96: 0.25 | T96: 0.014025 | U96: 0.8976
B97: =1+B96 -> 93 | D97: 44112 | E97: STORAGE OF AIR OR GROUND ORGANIC UNITS FOR MARINE CORPS | G97: M29031 | H97: C0189 | I97: C01892F | J97: POUCH,MONOCULAR NIG - N/A | K97: IS | L97: EA | M97: N | N97: 16 | O97: 0 | P97: 16 | Q97: 0.58 | R97: 0.58 | S97: 0.42 | T97: 0.141288 | U97: 2.260608
B98: =1+B97 -> 94 | D98: 44112 | E98: STORAGE OF AIR OR GROUND ORGANIC UNITS FOR MARINE CORPS | G98: M29031 | H98: C0190 | I98: C01902F | J98: POUCH,TACTICAL HAND - N/A | K98: IS | L98: EA | M98: N | N98: 0 | O98: 0 | P98: 0 | Q98: 0.5 | R98: 0.25 | S98: 0.17 | T98: 0.02125 | U98: 0
B99: =1+B98 -> 95 | D99: 44112 | E99: STORAGE OF AIR OR GROUND ORGANIC UNITS FOR MARINE CORPS | G99: M29031 | H99: C0191 | I99: C01912F | J99: CANTEEN,GENERAL PUR - 4015CB | K99: IS | L99: EA | M99: N | N99: 244 | O99: 0 | P99: 244 | Q99: 0.17 | R99: 0.33 | S99: 0.5 | T99: 0.02805 | U99: 6.8442
B100: =1+B99 -> 96 | D100: #N/A | E100: #N/A | G100: M29031 | H100: C0218 | I100: C02182B | J100: DECONTAMINATION KIT - 10038819 | K100: IS | L100: BX | M100: N | N100: 2 | O100: 0 | P100: 2 | Q100: 0 | R100: 0 | S100: 0 | T100: 0 | U100: 0
B101: =1+B100 -> 97 | D101: #N/A | E101: #N/A | G101: M29031 | H101: C0222 | I101: C02222F | J101: HELMET,GROUND TROOP - HC ECH | K101: IS | L101: EA | M101: N | N101: 0 | O101: 0 | P101: 0 | Q101: 1 | R101: 1 | S101: 1 | T101: 1 | U101: 0
B102: =1+B101 -> 98 | D102: CSP | E102: #N/A | G102: M29031 | H102: C0260 | I102: C02602F | J102: GAITER,NECK - A-A-55247 | K102: IS | L102: EA | M102: N | N102: 122 | O102: 0 | P102: 122 | Q102: 1.25 | R102: 0.83 | S102: 0.08 | T102: 0.083 | U102: 10.126
B103: =1+B102 -> 99 | D103: 44112 | E103: STORAGE OF AIR OR GROUND ORGANIC UNITS FOR MARINE CORPS | G103: M29031 | H103: C1000 | I103: C10002E | J103: No Item Name Availa - 11-04 | K103: IS | L103: KT | M103: N | N103: 0 | O103: 1 | P103: 1 | Q103: 5 | R103: 2 | S103: 1 | T103: 10 | U103: 10
B104: =1+B103 -> 100 | D104: 44112 | E104: STORAGE OF AIR OR GROUND ORGANIC UNITS FOR MARINE CORPS | G104: M29031 | H104: C1023 | I104: C10232F | J104: HOOD,COMBAT VEHICLE - MIL-H-44265 | K104: IS | L104: 0 | M104: N | N104: 0 | O104: 0 | P104: 0 | Q104: 0.5 | R104: 0.5 | S104: 0.17 | T104: 0.0425 | U104: 0
B105: =1+B104 -> 101 | D105: CSP | E105: #N/A | G105: M29031 | H105: C1055 | I105: C10552F | J105: CAP,COLD WEATHER - CR/PD01-09 | K105: IS | L105: EA | M105: N | N105: 122 | O105: 0 | P105: 122 | Q105: 0.75 | R105: 0.83 | S105: 0.08 | T105: 0.0498 | U105: 6.0756
B106: =1+B105 -> 102 | D106: CSP | E106: #N/A | G106: M29031 | H106: C1107 | I106: C11072F | J106: GLOVES,MEN'S AND WO - SIZE 3 | K106: IS | L106: PR | M106: N | N106: 122 | O106: 0 | P106: 122 | Q106: 1 | R106: 0.5 | S106: 0.08 | T106: 0.04 | U106: 4.88
B107: =1+B106 -> 103 | D107: CSP | E107: #N/A | G107: M29031 | H107: C1120 | I107: C11202F | J107: GLOVE INSERTS,COLD - 70113 | K107: IS | L107: PR | M107: N | N107: 244 | O107: 0 | P107: 244 | Q107: 1 | R107: 0.5 | S107: 0.08 | T107: 0.04 | U107: 9.76
...

Sheet 14312
A1: BASIC FACILITY REQUIREMENTS WORKSHEET
A3: Installation: | F3: =UNIT_ROLLUP!F3 -> H&S BN MCIPAC MCB CP BUTLER JA | M3: Tenant: | R3: =UNIT_ROLLUP!R3 -> CLB 4
A4: Installation UIC: | F4: =UNIT_ROLLUP!F4 -> M67400 | M4: Tenant UIC: | R4: =UNIT_ROLLUP!R4 -> M29030 | Y4: Planning Area: | AE4: =UNIT_ROLLUP!AE4 -> SW
A5: CCN: | C5: 14312 | M5: Nomenclature: | R5: Operational Vehicle Laydown Area
A6: LOADING ANALYSIS / JUSTIFICATION OF REQUIREMENT
A7: Description:
B8: Mission: This Mission Statement prescribes the organizational structure, billet authorization, personnel strength, and individual weapons for the Marine Expeditionary Unit (MEU) Combat Logistics Battalion (CLB), Marine Logistics Group (MLG). Provide tactical logistics support above the organic capabilities of supported elements of the MEU. CCN: An operational vehicle parking and/or laydown area consists of an asphalt or concrete paved area large enough to store and provide circulation for the vehicles and equipment for which the command is responsible. Justification: CLB 22 requires a laydown area for storage of their assigned vehicles and equipment.
A16: Planning Criteria:
B17: UFC 2-000-05N (P-80) CCN 14312
A18: Loading:
B19: FY2025 Table of Equipment (attached)
A20: Analysis:
B21: Subordinate Unit | M21: Area
B22: ='Header '!A$6 -> M29030 | E22: ='Header '!B$6 -> CLB 4 | M22: =AC90+AC135-M24 -> 0
B23: ='Header '!A$6 -> M29030 | E23: EOD Requirement | M23: =AC180 -> 0
B24: ='Header '!A$6 -> M29030 | E24: COMM Laydown | M24: =SUM(AC53:AE57,AC121,) -> 0
E25: Totals = | M25: =SUM(M22:P23) -> 0
A46: TOTAL REQUIREMENT: | H46: =M25 -> 0 | L46: GSY | AC46: Page | AD46: 1 | AE46: of | AF46: 5
A47: CCN: | C47: =C5 -> 14312 | M47: Nomenclature: | R47: =R5 -> Operational Vehicle Laydown Area
C49: Operational Vehicle Laydown Area per P-80 Table 14312-1
C50: =B22 -> M29030 | F50: =E22 -> CLB 4
C51: TAMCN | G51: Description | U51: L, ft | W51: No. | Y51: Area (NSY) | AA51: NTG | AC51: GSY
C53: A0255 | G53: =IFERROR(INDEX(#REF!,MATCH(C53,#REF!,0)),"") | U53: =IFERROR(MAX(INDEX(#REF!,MATCH('14312'!C53,#REF!,0)),INDEX(#REF!,MATCH('14312'!C53,#REF!,0))),"") | W53: =IF(U53<>"",IF(C53="C4431",SUMIFS(#REF!,#REF!,C53,#REF!,$C$50)/2,SUMIFS(#REF!,#REF!,C53,#REF!,$C$50)),"") | Y53: =IF(U53<>"",IF(C53="C4431",4*4*2/9,IF($U53<10,15,IF($U53<20,25,IF($U53<30,45,IF($U53<50,70,101))))),"") | AA53: =IF(U53<>"",IF($U53<10,1.5,IF($U53<30,1.75,2)),"") | AC53: =IFERROR(W53*Y53*AA53,"")
C54: A0457 | G54: =IFERROR(INDEX(#REF!,MATCH(C54,#REF!,0)),"") | U54: =IFERROR(MAX(INDEX(#REF!,MATCH('14312'!C54,#REF!,0)),INDEX(#REF!,MATCH('14312'!C54,#REF!,0))),"") | W54: =IF(U54<>"",IF(C54="C4431",SUMIFS(#REF!,#REF!,C54,#REF!,$C$50)/2,SUMIFS(#REF!,#REF!,C54,#REF!,$C$50)),"") | Y54: =IF(U54<>"",IF(C54="C4431",4*4*2/9,IF($U54<10,15,IF($U54<20,25,IF($U54<30,45,IF($U54<50,70,101))))),"") | AA54: =IF(U54<>"",IF($U54<10,1.5,IF($U54<30,1.75,2)),"") | AC54: =IFERROR(W54*Y54*AA54,"")
C55: A0458 | G55: =IFERROR(INDEX(#REF!,MATCH(C55,#REF!,0)),"") | U55: =IFERROR(MAX(INDEX(#REF!,MATCH('14312'!C55,#REF!,0)),INDEX(#REF!,MATCH('14312'!C55,#REF!,0))),"") | W55: =IF(U55<>"",IF(C55="C4431",SUMIFS(#REF!,#REF!,C55,#REF!,$C$50)/2,SUMIFS(#REF!,#REF!,C55,#REF!,$C$50)),"") | Y55: =IF(U55<>"",IF(C55="C4431",4*4*2/9,IF($U55<10,15,IF($U55<20,25,IF($U55<30,45,IF($U55<50,70,101))))),"") | AA55: =IF(U55<>"",IF($U55<10,1.5,IF($U55<30,1.75,2)),"") | AC55: =IFERROR(W55*Y55*AA55,"")
C56: A2335 | G56: =IFERROR(INDEX(#REF!,MATCH(C56,#REF!,0)),"") | U56: =IFERROR(MAX(INDEX(#REF!,MATCH('14312'!C56,#REF!,0)),INDEX(#REF!,MATCH('14312'!C56,#REF!,0))),"") | W56: =IF(U56<>"",IF(C56="C4431",SUMIFS(#REF!,#REF!,C56,#REF!,$C$50)/2,SUMIFS(#REF!,#REF!,C56,#REF!,$C$50)),"") | Y56: =IF(U56<>"",IF(C56="C4431",4*4*2/9,IF($U56<10,15,IF($U56<20,25,IF($U56<30,45,IF($U56<50,70,101))))),"") | AA56: =IF(U56<>"",IF($U56<10,1.5,IF($U56<30,1.75,2)),"") | AC56: =IFERROR(W56*Y56*AA56,"")
C57: A2336 | G57: =IFERROR(INDEX(#REF!,MATCH(C57,#REF!,0)),"") | U57: =IFERROR(MAX(INDEX(#REF!,MATCH('14312'!C57,#REF!,0)),INDEX(#REF!,MATCH('14312'!C57,#REF!,0))),"") | W57: =IF(U57<>"",IF(C57="C4431",SUMIFS(#REF!,#REF!,C57,#REF!,$C$50)/2,SUMIFS(#REF!,#REF!,C57,#REF!,$C$50)),"") | Y57: =IF(U57<>"",IF(C57="C4431",4*4*2/9,IF($U57<10,15,IF($U57<20,25,IF($U57<30,45,IF($U57<50,70,101))))),"") | AA57: =IF(U57<>"",IF($U57<10,1.5,IF($U57<30,1.75,2)),"") | AC57: =IFERROR(W57*Y57*AA57,"")
C58: B0036 | G58: =IFERROR(INDEX(#REF!,MATCH(C58,#REF!,0)),"") | U58: =IFERROR(MAX(INDEX(#REF!,MATCH('14312'!C58,#REF!,0)),INDEX(#REF!,MATCH('14312'!C58,#REF!,0))),"") | W58: =IF(U58<>"",IF(C58="C4431",SUMIFS(#REF!,#REF!,C58,#REF!,$C$50)/2,SUMIFS(#REF!,#REF!,C58,#REF!,$C$50)),"") | Y58: =IF(U58<>"",IF(C58="C4431",4*4*2/9,IF($U58<10,15,IF($U58<20,25,IF($U58<30,45,IF($U58<50,70,101))))),"") | AA58: =IF(U58<>"",IF($U58<10,1.5,IF($U58<30,1.75,2)),"") | AC58: =IFERROR(W58*Y58*AA58,"")
C59: B0037 | G59: =IFERROR(INDEX(#REF!,MATCH(C59,#REF!,0)),"") | U59: =IFERROR(MAX(INDEX(#REF!,MATCH('14312'!C59,#REF!,0)),INDEX(#REF!,MATCH('14312'!C59,#REF!,0))),"") | W59: =IF(U59<>"",IF(C59="C4431",SUMIFS(#REF!,#REF!,C59,#REF!,$C$50)/2,SUMIFS(#REF!,#REF!,C59,#REF!,$C$50)),"") | Y59: =IF(U59<>"",IF(C59="C4431",4*4*2/9,IF($U59<10,15,IF($U59<20,25,IF($U59<30,45,IF($U59<50,70,101))))),"") | AA59: =IF(U59<>"",IF($U59<10,1.5,IF($U59<30,1.75,2)),"") | AC59: =IFERROR(W59*Y59*AA59,"")
C60: B0040 | G60: =IFERROR(INDEX(#REF!,MATCH(C60,#REF!,0)),"") | U60: =IFERROR(MAX(INDEX(#REF!,MATCH('14312'!C60,#REF!,0)),INDEX(#REF!,MATCH('14312'!C60,#REF!,0))),"") | W60: =IF(U60<>"",IF(C60="C4431",SUMIFS(#REF!,#REF!,C60,#REF!,$C$50)/2,SUMIFS(#REF!,#REF!,C60,#REF!,$C$50)),"") | Y60: =IF(U60<>"",IF(C60="C4431",4*4*2/9,IF($U60<10,15,IF($U60<20,25,IF($U60<30,45,IF($U60<50,70,101))))),"") | AA60: =IF(U60<>"",IF($U60<10,1.5,IF($U60<30,1.75,2)),"") | AC60: =IFERROR(W60*Y60*AA60,"")
C61: B0043 | G61: =IFERROR(INDEX(#REF!,MATCH(C61,#REF!,0)),"") | U61: =IFERROR(MAX(INDEX(#REF!,MATCH('14312'!C61,#REF!,0)),INDEX(#REF!,MATCH('14312'!C61,#REF!,0))),"") | W61: =IF(U61<>"",IF(C61="C4431",SUMIFS(#REF!,#REF!,C61,#REF!,$C$50)/2,SUMIFS(#REF!,#REF!,C61,#REF!,$C$50)),"") | Y61: =IF(U61<>"",IF(C61="C4431",4*4*2/9,IF($U61<10,15,IF($U61<20,25,IF($U61<30,45,IF($U61<50,70,101))))),"") | AA61: =IF(U61<>"",IF($U61<10,1.5,IF($U61<30,1.75,2)),"") | AC61: =IFERROR(W61*Y61*AA61,"")
C62: B0063 | G62: =IFERROR(INDEX(#REF!,MATCH(C62,#REF!,0)),"") | U62: =IFERROR(MAX(INDEX(#REF!,MATCH('14312'!C62,#REF!,0)),INDEX(#REF!,MATCH('14312'!C62,#REF!,0))),"") | W62: =IF(U62<>"",IF(C62="C4431",SUMIFS(#REF!,#REF!,C62,#REF!,$C$50)/2,SUMIFS(#REF!,#REF!,C62,#REF!,$C$50)),"") | Y62: =IF(U62<>"",IF(C62="C4431",4*4*2/9,IF($U62<10,15,IF($U62<20,25,IF($U62<30,45,IF($U62<50,70,101))))),"") | AA62: =IF(U62<>"",IF($U62<10,1.5,IF($U62<30,1.75,2)),"") | AC62: =IFERROR(W62*Y62*AA62,"")
C63: B0071 | G63: =IFERROR(INDEX(#REF!,MATCH(C63,#REF!,0)),"") | U63: =IFERROR(MAX(INDEX(#REF!,MATCH('14312'!C63,#REF!,0)),INDEX(#REF!,MATCH('14312'!C63,#REF!,0))),"") | W63: =IF(U63<>"",IF(C63="C4431",SUMIFS(#REF!,#REF!,C63,#REF!,$C$50)/2,SUMIFS(#REF!,#REF!,C63,#REF!,$C$50)),"") | Y63: =IF(U63<>"",IF(C63="C4431",4*4*2/9,IF($U63<10,15,IF($U63<20,25,IF($U63<30,45,IF($U63<50,70,101))))),"") | AA63: =IF(U63<>"",IF($U63<10,1.5,IF($U63<30,1.75,2)),"") | AC63: =IFERROR(W63*Y63*AA63,"")
C64: B0076 | G64: =IFERROR(INDEX(#REF!,MATCH(C64,#REF!,0)),"") | U64: =IFERROR(MAX(INDEX(#REF!,MATCH('14312'!C64,#REF!,0)),INDEX(#REF!,MATCH('14312'!C64,#REF!,0))),"") | W64: =IF(U64<>"",IF(C64="C4431",SUMIFS(#REF!,#REF!,C64,#REF!,$C$50)/2,SUMIFS(#REF!,#REF!,C64,#REF!,$C$50)),"") | Y64: =IF(U64<>"",IF(C64="C4431",4*4*2/9,IF($U64<10,15,IF($U64<20,25,IF($U64<30,45,IF($U64<50,70,101))))),"") | AA64: =IF(U64<>"",IF($U64<10,1.5,IF($U64<30,1.75,2)),"") | AC64: =IFERROR(W64*Y64*AA64,"")
... C89: C0187 | G89: =IFERROR(INDEX(#REF!,MATCH(C89,#REF!,0)),"") | U89: =IFERROR(MAX(INDEX(#REF!,MATCH('14312'!C89,#REF!,0)),INDEX(#REF!,MATCH('14312'!C89,#REF!,0))),"") | W89: =IF(U89<>"",IF(C89="C4431",SUMIFS(#REF!,#REF!,C89,#REF!,$C$50)/2,SUMIFS(#REF!,#REF!,C89,#REF!,$C$50)),"") | Y89: =IF(U89<>"",IF(C89="C4431",4*4*2/9,IF($U89<10,15,IF($U89<20,25,IF($U89<30,45,IF($U89<50,70,101))))),"") | AA89: =IF(U89<>"",IF($U89<10,1.5,IF($U89<30,1.75,2)),"") | AC89: =IFERROR(W89*Y89*AA89,"")
AB90: Total = | AC90: =SUM(AC53:AE89) -> 0
AC91: Page | AD91: =AD46+1 -> 2 | AE91: of | AF91: 4
A92: CCN: | C92: =C47 -> 14312 | M92: Nomenclature: | R92: =R47 -> Operational Vehicle Laydown Area
C94: Operational Vehicle Laydown Area per P-80 Table 14312-1
C95: =C50 -> M29030 | F95: =F50 -> CLB 4
C96: TAMCN | G96: Description | U96: L, ft | W96: No. | Y96: Area (NSY) | AA96: NTG | AC96: GSY
C98: C7905 | G98: =IFERROR(INDEX(#REF!,MATCH(C98,#REF!,0)),"") | U98: =IFERROR(MAX(INDEX(#REF!,MATCH('14312'!C98,#REF!,0)),INDEX(#REF!,MATCH('14312'!C98,#REF!,0))),"") | W98: =IF(U98<>"",IF(C98="C4431",SUMIFS(#REF!,#REF!,C98,#REF!,$C$95)/2,SUMIFS(#REF!,#REF!,C98,#REF!,$C$95)),"") | Y98: =IF(U98<>"",IF(C98="C4431",4*4*2/9,IF($U98<10,15,IF($U98<20,25,IF($U98<30,45,IF($U98<50,70,101))))),"") | AA98: =IF(U98<>"",IF($U98<10,1.5,IF($U98<30,1.75,2)),"") | AC98: =IFERROR(W98*Y98*AA98,"")
C99: C7908 | G99: =IFERROR(INDEX(#REF!,MATCH(C99,#REF!,0)),"") | U99: =IFERROR(MAX(INDEX(#REF!,MATCH('14312'!C99,#REF!,0)),INDEX(#REF!,MATCH('14312'!C99,#REF!,0))),"") | W99: =IF(U99<>"",IF(C99="C4431",SUMIFS(#REF!,#REF!,C99,#REF!,$C$95)/2,SUMIFS(#REF!,#REF!,C99,#REF!,$C$95)),"") | Y99: =IF(U99<>"",IF(C99="C4431",4*4*2/9,IF($U99<10,15,IF($U99<20,25,IF($U99<30,45,IF($U99<50,70,101))))),"") | AA99: =IF(U99<>"",IF($U99<10,1.5,IF($U99<30,1.75,2)),"") | AC99: =IFERROR(W99*Y99*AA99,"")
C100: C7911 | G100: =IFERROR(INDEX(#REF!,MATCH(C100,#REF!,0)),"") | U100: =IFERROR(MAX(INDEX(#REF!,MATCH('14312'!C100,#REF!,0)),INDEX(#REF!,MATCH('14312'!C100,#REF!,0))),"") | W100: =IF(U100<>"",IF(C100="C4431",SUMIFS(#REF!,#REF!,C100,#REF!,$C$95)/2,SUMIFS(#REF!,#REF!,C100,#REF!,$C$95)),"") | Y100: =IF(U100<>"",IF(C100="C4431",4*4*2/9,IF($U100<10,15,IF($U100<20,25,IF($U100<30,45,IF($U100<50,70,101))))),"") | AA100: =IF(U100<>"",IF($U100<10,1.5,IF($U100<30,1.75,2)),"") | AC100: =IFERROR(W100*Y100*AA100,"")
C101: C7913 | G101: =IFERROR(INDEX(#REF!,MATCH(C101,#REF!,0)),"") | U101: =IFERROR(MAX(INDEX(#REF!,MATCH('14312'!C101,#REF!,0)),INDEX(#REF!,MATCH('14312'!C101,#REF!,0))),"") | W101: =IF(U101<>"",IF(C101="C4431",SUMIFS(#REF!,#REF!,C101,#REF!,$C$95)/2,SUMIFS(#REF!,#REF!,C101,#REF!,$C$95)),"") | Y101: =IF(U101<>"",IF(C101="C4431",4*4*2/9,IF($U101<10,15,IF($U101<20,25,IF($U101<30,45,IF($U101<50,70,101))))),"") | AA101: =IF(U101<>"",IF($U101<10,1.5,IF($U101<30,1.75,2)),"") | AC101: =IFERROR(W101*Y101*AA101,"")
C102: D0003 | G102: =IFERROR(INDEX(#REF!,MATCH(C102,#REF!,0)),"") | U102: =IFERROR(MAX(INDEX(#REF!,MATCH('14312'!C102,#REF!,0)),INDEX(#REF!,MATCH('14312'!C102,#REF!,0))),"") | W102: =IF(U102<>"",IF(C102="C4431",SUMIFS(#REF!,#REF!,C102,#REF!,$C$95)/2,SUMIFS(#REF!,#REF!,C102,#REF!,$C$95)),"") | Y102: =IF(U102<>"",IF(C102="C4431",4*4*2/9,IF($U102<10,15,IF($U102<20,25,IF($U102<30,45,IF($U102<50,70,101))))),"") | AA102: =IF(U102<>"",IF($U102<10,1.5,IF($U102<30,1.75,2)),"") | AC102: =IFERROR(W102*Y102*AA102,"")
C103: D0005 | G103: =IFERROR(INDEX(#REF!,MATCH(C103,#REF!,0)),"") | U103: =IFERROR(MAX(INDEX(#REF!,MATCH('14312'!C103,#REF!,0)),INDEX(#REF!,MATCH('14312'!C103,#REF!,0))),"") | W103: =IF(U103<>"",IF(C103="C4431",SUMIFS(#REF!,#REF!,C103,#REF!,$C$95)/2,SUMIFS(#REF!,#REF!,C103,#REF!,$C$95)),"") | Y103: =IF(U103<>"",IF(C103="C4431",4*4*2/9,IF($U103<10,15,IF($U103<20,25,IF($U103<30,45,IF($U103<50,70,101))))),"") | AA103: =IF(U103<>"",IF($U103<10,1.5,IF($U103<30,1.75,2)),"") | AC103: =IFERROR(W103*Y103*AA103,"")
C104: D0015 | G104: =IFERROR(INDEX(#REF!,MATCH(C104,#REF!,0)),"") | U104: =IFERROR(MAX(INDEX(#REF!,MATCH('14312'!C104,#REF!,0)),INDEX(#REF!,MATCH('14312'!C104,#REF!,0))),"") | W104: =IF(U104<>"",IF(C104="C4431",SUMIFS(#REF!,#REF!,C104,#REF!,$C$95)/2,SUMIFS(#REF!,#REF!,C104,#REF!,$C$95)),"") | Y104: =IF(U104<>"",IF(C104="C4431",4*4*2/9,IF($U104<10,15,IF($U104<20,25,IF($U104<30,45,IF($U104<50,70,101))))),"") | AA104: =IF(U104<>"",IF($U104<10,1.5,IF($U104<30,1.75,2)),"") | AC104: =IFERROR(W104*Y104*AA104,"")
C105: D0016 | G105: =IFERROR(INDEX(#REF!,MATCH(C105,#REF!,0)),"") | U105: =IFERROR(MAX(INDEX(#REF!,MATCH('14312'!C105,#REF!,0)),INDEX(#REF!,MATCH('14312'!C105,#REF!,0))),"") | W105: =IF(U105<>"",IF(C105="C4431",SUMIFS(#REF!,#REF!,C105,#REF!,$C$95)/2,SUMIFS(#REF!,#REF!,C105,#REF!,$C$95)),"") | Y105: =IF(U105<>"",IF(C105="C4431",4*4*2/9,IF($U105<10,15,IF($U105<20,25,IF($U105<30,45,IF($U105<50,70,101))))),"") | AA105: =IF(U105<>"",IF($U105<10,1.5,IF($U105<30,1.75,2)),"") | AC105: =IFERROR(W105*Y105*AA105,"")
C106: D0022 | G106: =IFERROR(INDEX(#REF!,MATCH(C106,#REF!,0)),"") | U106: =IFERROR(MAX(INDEX(#REF!,MATCH('14312'!C106,#REF!,0)),INDEX(#REF!,MATCH('14312'!C106,#REF!,0))),"") | W106: 4 | Y106: =IF(U106<>"",IF(C106="C4431",4*4*2/9,IF($U106<10,15,IF($U106<20,25,IF($U106<30,45,IF($U106<50,70,101))))),"") | AA106: =IF(U106<>"",IF($U106<10,1.5,IF($U106<30,1.75,2)),"") | AC106: =IFERROR(W106*Y106*AA106,"")
C107: D0030 | G107: =IFERROR(INDEX(#REF!,MATCH(C107,#REF!,0)),"") | U107: =IFERROR(MAX(INDEX(#REF!,MATCH('14312'!C107,#REF!,0)),INDEX(#REF!,MATCH('14312'!C107,#REF!,0))),"") | W107: =IF(U107<>"",IF(C107="C4431",SUMIFS(#REF!,#REF!,C107,#REF!,$C$95)/2,SUMIFS(#REF!,#REF!,C107,#REF!,$C$95)),"") | Y107: =IF(U107<>"",IF(C107="C4431",4*4*2/9,IF($U107<10,15,IF($U107<20,25,IF($U107<30,45,IF($U107<50,70,101))))),"") | AA107: =IF(U107<>"",IF($U107<10,1.5,IF($U107<30,1.75,2)),"") | AC107: =IFERROR(W107*Y107*AA107,"")
C108: D0031 | G108: =IFERROR(INDEX(#REF!,MATCH(C108,#REF!,0)),"") | U108: =IFERROR(MAX(INDEX(#REF!,MATCH('14312'!C108,#REF!,0)),INDEX(#REF!,MATCH('14312'!C108,#REF!,0))),"") | W108: =IF(U108<>"",IF(C108="C4431",SUMIFS(#REF!,#REF!,C108,#REF!,$C$95)/2,SUMIFS(#REF!,#REF!,C108,#REF!,$C$95)),"") | Y108: =IF(U108<>"",IF(C108="C4431",4*4*2/9,IF($U108<10,15,IF($U108<20,25,IF($U108<30,45,IF($U108<50,70,101))))),"") | AA108: =IF(U108<>"",IF($U108<10,1.5,IF($U108<30,1.75,2)),"") | AC108: =IFERROR(W108*Y108*AA108,"")
C109: D0033 | G109: =IFERROR(INDEX(#REF!,MATCH(C109,#REF!,0)),"") | U109: =IFERROR(MAX(INDEX(#REF!,MATCH('14312'!C109,#REF!,0)),INDEX(#REF!,MATCH('14312'!C109,#REF!,0))),"") | W109: =IF(U109<>"",IF(C109="C4431",SUMIFS(#REF!,#REF!,C109,#REF!,$C$95)/2,SUMIFS(#REF!,#REF!,C109,#REF!,$C$95)),"") | Y109: =IF(U109<>"",IF(C109="C4431",4*4*2/9,IF($U109<10,15,IF($U109<20,25,IF($U109<30,45,IF($U109<50,70,101))))),"") | AA109: =IF(U109<>"",IF($U109<10,1.5,IF($U109<30,1.75,2)),"") | AC109: =IFERROR(W109*Y109*AA109,"")
C110: D0034 | G110: =IFERROR(INDEX(#REF!,MATCH(C110,#REF!,0)),"") | U110: =IFERROR(MAX(INDEX(#REF!,MATCH('14312'!C110,#REF!,0)),INDEX(#REF!,MATCH('14312'!C110,#REF!,0))),"") | W110: =IF(U110<>"",IF(C110="C4431",SUMIFS(#REF!,#REF!,C110,#REF!,$C$95)/2,SUMIFS(#REF!,#REF!,C110,#REF!,$C$95)),"") | Y110: =IF(U110<>"",IF(C110="C4431",4*4*2/9,IF($U110<10,15,IF($U110<20,25,IF($U110<30,45,IF($U110<50,70,101))))),"") | AA110: =IF(U110<>"",IF($U110<10,1.5,IF($U110<30,1.75,2)),"") | AC110: =IFERROR(W110*Y110*AA110,"")
C111: D0045 | G111: =IFERROR(INDEX(#REF!,MATCH(C111,#REF!,0)),"") | U111: =IFERROR(MAX(INDEX(#REF!,MATCH('14312'!C111,#REF!,0)),INDEX(#REF!,MATCH('14312'!C111,#REF!,0))),"") | W111: =IF(U111<>"",IF(C111="C4431",SUMIFS(#REF!,#REF!,C111,#REF!,$C$95)/2,SUMIFS(#REF!,#REF!,C111,#REF!,$C$95)),"") | Y111: =IF(U111<>"",IF(C111="C4431",4*4*2/9,IF($U111<10,15,IF($U111<20,25,IF($U111<30,45,IF($U111<50,70,101))))),"") | AA111: =IF(U111<>"",IF($U111<10,1.5,IF($U111<30,1.75,2)),"") | AC111: =IFERROR(W111*Y111*AA111,"")
C112: D0046 | G112: =IFERROR(INDEX(#REF!,MATCH(C112,#REF!,0)),"") | U112: =IFERROR(MAX(INDEX(#REF!,MATCH('14312'!C112,#REF!,0)),INDEX(#REF!,MATCH('14312'!C112,#REF!,0))),"") | W112: =IF(U112<>"",IF(C112="C4431",SUMIFS(#REF!,#REF!,C112,#REF!,$C$95)/2,SUMIFS(#REF!,#REF!,C112,#REF!,$C$95)),"") | Y112: =IF(U112<>"",IF(C112="C4431",4*4*2/9,IF($U112<10,15,IF($U112<20,25,IF($U112<30,45,IF($U112<50,70,101))))),"") | AA112: =IF(U112<>"",IF($U112<10,1.5,IF($U112<30,1.75,2)),"") | AC112: =IFERROR(W112*Y112*AA112,"")
C113: D0048 | G113: =IFERROR(INDEX(#REF!,MATCH(C113,#REF!,0)),"") | U113: =IFERROR(MAX(INDEX(#REF!,MATCH('14312'!C113,#REF!,0)),INDEX(#REF!,MATCH('14312'!C113,#REF!,0))),"") | W113: =IF(U113<>"",IF(C113="C4431",SUMIFS(#REF!,#REF!,C113,#REF!,$C$95)/2,SUMIFS(#REF!,#REF!,C113,#REF!,$C$95)),"") | Y113: =IF(U113<>"",IF(C113="C4431",4*4*2/9,IF($U113<10,15,IF($U113<20,25,IF($U113<30,45,IF($U113<50,70,101))))),"") | AA113: =IF(U113<>"",IF($U113<10,1.5,IF($U113<30,1.75,2)),"") | AC113: =IFERROR(W113*Y113*AA113,"")
C114: D0058 | G114: =IFERROR(INDEX(#REF!,MATCH(C114,#REF!,0)),"") | U114: =IFERROR(MAX(INDEX(#REF!,MATCH('14312'!C114,#REF!,0)),INDEX(#REF!,MATCH('14312'!C114,#REF!,0))),"") | W114: =IF(U114<>"",IF(C114="C4431",SUMIFS(#REF!,#REF!,C114,#REF!,$C$95)/2,SUMIFS(#REF!,#REF!,C114,#REF!,$C$95)),"") | Y114: =IF(U114<>"",IF(C114="C4431",4*4*2/9,IF($U114<10,15,IF($U114<20,25,IF($U114<30,45,IF($U114<50,70,101))))),"") | AA114: =IF(U114<>"",IF($U114<10,1.5,IF($U114<30,1.75,2)),"") | AC114: =IFERROR(W114*Y114*AA114,"")
C115: D0862 | G115: =IFERROR(INDEX(#REF!,MATCH(C115,#REF!,0)),"") | U115: =IFERROR(MAX(INDEX(#REF!,MATCH('14312'!C115,#REF!,0)),INDEX(#REF!,MATCH('14312'!C115,#REF!,0))),"") | W115: =IF(U115<>"",IF(C115="C4431",SUMIFS(#REF!,#REF!,C115,#REF!,$C$95)/2,SUMIFS(#REF!,#REF!,C115,#REF!,$C$95)),"") | Y115: =IF(U115<>"",IF(C115="C4431",4*4*2/9,IF($U115<10,15,IF($U115<20,25,IF($U115<30,45,IF($U115<50,70,101))))),"") | AA115: =IF(U115<>"",IF($U115<10,1.5,IF($U115<30,1.75,2)),"") | AC115: =IFERROR(W115*Y115*AA115,"")
C116: D0880 | G116: =IFERROR(INDEX(#REF!,MATCH(C116,#REF!,0)),"") | U116: =IFERROR(MAX(INDEX(#REF!,MATCH('14312'!C116,#REF!,0)),INDEX(#REF!,MATCH('14312'!C116,#REF!,0))),"") | W116: =IF(U116<>"",IF(C116="C4431",SUMIFS(#REF!,#REF!,C116,#REF!,$C$95)/2,SUMIFS(#REF!,#REF!,C116,#REF!,$C$95)),"") | Y116: =IF(U116<>"",IF(C116="C4431",4*4*2/9,IF($U116<10,15,IF($U116<20,25,IF($U116<30,45,IF($U116<50,70,101))))),"") | AA116: =IF(U116<>"",IF($U116<10,1.5,IF($U116<30,1.75,2)),"") | AC116: =IFERROR(W116*Y116*AA116,"")
C117: D1001 | G117: =IFERROR(INDEX(#REF!,MATCH(C117,#REF!,0)),"") | U117: =IFERROR(MAX(INDEX(#REF!,MATCH('14312'!C117,#REF!,0)),INDEX(#REF!,MATCH('14312'!C117,#REF!,0))),"") | W117: =IF(U117<>"",IF(C117="C4431",SUMIFS(#REF!,#REF!,C117,#REF!,$C$95)/2,SUMIFS(#REF!,#REF!,C117,#REF!,$C$95)),"") | Y117: =IF(U117<>"",IF(C117="C4431",4*4*2/9,IF($U117<10,15,IF($U117<20,25,IF($U117<30,45,IF($U117<50,70,101))))),"") | AA117: =IF(U117<>"",IF($U117<10,1.5,IF($U117<30,1.75,2)),"") | AC117: =IFERROR(W117*Y117*AA117,"")
C118: D1002 | G118: =IFERROR(INDEX(#REF!,MATCH(C118,#REF!,0)),"") | U118: =IFERROR(MAX(INDEX(#REF!,MATCH('14312'!C118,#REF!,0)),INDEX(#REF!,MATCH('14312'!C118,#REF!,0))),"") | W118: =IF(U118<>"",IF(C118="C4431",SUMIFS(#REF!,#REF!,C118,#REF!,$C$95)/2,SUMIFS(#REF!,#REF!,C118,#REF!,$C$95)),"") | Y118: =IF(U118<>"",IF(C118="C4431",4*4*2/9,IF($U118<10,15,IF($U118<20,25,IF($U118<30,45,IF($U118<50,70,101))))),"") | AA118: =IF(U118<>"",IF($U118<10,1.5,IF($U118<30,1.75,2)),"") | AC118: =IFERROR(W118*Y118*AA118,"")
... C122: B0571 | G122: =IFERROR(INDEX(#REF!,MATCH(C122,#REF!,0)),"") | U122: =IFERROR(MAX(INDEX(#REF!,MATCH('14312'!C122,#REF!,0)),INDEX(#REF!,MATCH('14312'!C122,#REF!,0))),"") | W122: =IF(U122<>"",IF(C122="C4431",SUMIFS(#REF!,#REF!,C122,#REF!,$C$95)/2,SUMIFS(#REF!,#REF!,C122,#REF!,$C$95)),"") | Y122: =IF(U122<>"",IF(C122="C4431",4*4*2/9,IF($U122<10,15,IF($U122<20,25,IF($U122<30,45,IF($U122<50,70,101))))),"") | AA122: =IF(U122<>"",IF($U122<10,1.5,IF($U122<30,1.75,2)),"") | AC122: =IFERROR(W122*Y122*AA122,"")
G123: =IFERROR(INDEX(#REF!,MATCH(C123,#REF!,0)),"") | U123: =IFERROR(MAX(INDEX(#REF!,MATCH('14312'!C123,#REF!,0)),INDEX(#REF!,MATCH('14312'!C123,#REF!,0))),"") | W123: =IF(U123<>"",IF(C123="C4431",SUMIFS(#REF!,#REF!,C123,#REF!,$C$95)/2,SUMIFS(#REF!,#REF!,C123,#REF!,$C$95)),"") | Y123: =IF(U123<>"",IF(C123="C4431",4*4*2/9,IF($U123<10,15,IF($U123<20,25,IF($U123<30,45,IF($U123<50,70,101))))),"") | AA123: =IF(U123<>"",IF($U123<10,1.5,IF($U123<30,1.75,2)),"") | AC123: =IFERROR(W123*Y123*AA123,"")
C124: B0647 | G124: =IFERROR(INDEX(#REF!,MATCH(C124,#REF!,0)),"") | U124: =IFERROR(MAX(INDEX(#REF!,MATCH('14312'!C124,#REF!,0)),INDEX(#REF!,MATCH('14312'!C124,#REF!,0))),"") | W124: =IF(U124<>"",IF(C124="C4431",SUMIFS(#REF!,#REF!,C124,#REF!,$C$95)/2,SUMIFS(#REF!,#REF!,C124,#REF!,$C$95)),"") | Y124: =IF(U124<>"",IF(C124="C4431",4*4*2/9,IF($U124<10,15,IF($U124<20,25,IF($U124<30,45,IF($U124<50,70,101))))),"") | AA124: =IF(U124<>"",IF($U124<10,1.5,IF($U124<30,1.75,2)),"") | AC124: =IFERROR(W124*Y124*AA124,"")
C125: B2130 | G125: =IFERROR(INDEX(#REF!,MATCH(C125,#REF!,0)),"") | U125: =IFERROR(MAX(INDEX(#REF!,MATCH('14312'!C125,#REF!,0)),INDEX(#REF!,MATCH('14312'!C125,#REF!,0))),"") | W125: =IF(U125<>"",IF(C125="C4431",SUMIFS(#REF!,#REF!,C125,#REF!,$C$95)/2,SUMIFS(#REF!,#REF!,C125,#REF!,$C$95)),"") | Y125: =IF(U125<>"",IF(C125="C4431",4*4*2/9,IF($U125<10,15,IF($U125<20,25,IF($U125<30,45,IF($U125<50,70,101))))),"") | AA125: =IF(U125<>"",IF($U125<10,1.5,IF($U125<30,1.75,2)),"") | AC125: =IFERROR(W125*Y125*AA125,"")
G126: =IFERROR(INDEX(#REF!,MATCH(C126,#REF!,0)),"") | U126: =IFERROR(MAX(INDEX(#REF!,MATCH('14312'!C126,#REF!,0)),INDEX(#REF!,MATCH('14312'!C126,#REF!,0))),"") | W126: =IF(U126<>"",IF(C126="C4431",SUMIFS(#REF!,#REF!,C126,#REF!,$C$95)/2,SUMIFS(#REF!,#REF!,C126,#REF!,$C$95)),"") | Y126: =IF(U126<>"",IF(C126="C4431",4*4*2/9,IF($U126<10,15,IF($U126<20,25,IF($U126<30,45,IF($U126<50,70,101))))),"") | AA126: =IF(U126<>"",IF($U126<10,1.5,IF($U126<30,1.75,2)),"") | AC126: =IFERROR(W126*Y126*AA126,"")
G127: =IFERROR(INDEX(#REF!,MATCH(C127,#REF!,0)),"") | U127: =IFERROR(MAX(INDEX(#REF!,MATCH('14312'!C127,#REF!,0)),INDEX(#REF!,MATCH('14312'!C127,#REF!,0))),"") | W127: =IF(U127<>"",IF(C127="C4431",SUMIFS(#REF!,#REF!,C127,#REF!,$C$95)/2,SUMIFS(#REF!,#REF!,C127,#REF!,$C$95)),"") | Y127: =IF(U127<>"",IF(C127="C4431",4*4*2/9,IF($U127<10,15,IF($U127<20,25,IF($U127<30,45,IF($U127<50,70,101))))),"") | AA127: =IF(U127<>"",IF($U127<10,1.5,IF($U127<30,1.75,2)),"") | AC127: =IFERROR(W127*Y127*AA127,"")
G128: =IFERROR(INDEX(#REF!,MATCH(C128,#REF!,0)),"") | U128: =IFERROR(MAX(INDEX(#REF!,MATCH('14312'!C128,#REF!,0)),INDEX(#REF!,MATCH('14312'!C128,#REF!,0))),"") | W128: =IF(U128<>"",IF(C128="C4431",SUMIFS(#REF!,#REF!,C128,#REF!,$C$95)/2,SUMIFS(#REF!,#REF!,C128,#REF!,$C$95)),"") | Y128: =IF(U128<>"",IF(C128="C4431",4*4*2/9,IF($U128<10,15,IF($U128<20,25,IF($U128<30,45,IF($U128<50,70,101))))),"") | AA128: =IF(U128<>"",IF($U128<10,1.5,IF($U128<30,1.75,2)),"") | AC128: =IFERROR(W128*Y128*AA128,"")
G129: =IFERROR(INDEX(#REF!,MATCH(C129,#REF!,0)),"") | U129: =IFERROR(MAX(INDEX(#REF!,MATCH('14312'!C129,#REF!,0)),INDEX(#REF!,MATCH('14312'!C129,#REF!,0))),"") | W129: =IF(U129<>"",IF(C129="C4431",SUMIFS(#REF!,#REF!,C129,#REF!,$C$95)/2,SUMIFS(#REF!,#REF!,C129,#REF!,$C$95)),"") | Y129: =IF(U129<>"",IF(C129="C4431",4*4*2/9,IF($U129<10,15,IF($U129<20,25,IF($U129<30,45,IF($U129<50,70,101))))),"") | AA129: =IF(U129<>"",IF($U129<10,1.5,IF($U129<30,1.75,2)),"") | AC129: =IFERROR(W129*Y129*AA129,"")
G130: =IFERROR(INDEX(#REF!,MATCH(C130,#REF!,0)),"") | U130: =IFERROR(MAX(INDEX(#REF!,MATCH('14312'!C130,#REF!,0)),INDEX(#REF!,MATCH('14312'!C130,#REF!,0))),"") | W130: =IF(U130<>"",IF(C130="C4431",SUMIFS(#REF!,#REF!,C130,#REF!,$C$95)/2,SUMIFS(#REF!,#REF!,C130,#REF!,$C$95)),"") | Y130: =IF(U130<>"",IF(C130="C4431",4*4*2/9,IF($U130<10,15,IF($U130<20,25,IF($U130<30,45,IF($U130<50,70,101))))),"") | AA130: =IF(U130<>"",IF($U130<10,1.5,IF($U130<30,1.75,2)),"") | AC130: =IFERROR(W130*Y130*AA130,"")
G131: =IFERROR(INDEX(#REF!,MATCH(C131,#REF!,0)),"") | U131: =IFERROR(MAX(INDEX(#REF!,MATCH('14312'!C131,#REF!,0)),INDEX(#REF!,MATCH('14312'!C131,#REF!,0))),"") | W131: =IF(U131<>"",IF(C131="C4431",SUMIFS(#REF!,#REF!,C131,#REF!,$C$95)/2,SUMIFS(#REF!,#REF!,C131,#REF!,$C$95)),"") | Y131: =IF(U131<>"",IF(C131="C4431",4*4*2/9,IF($U131<10,15,IF($U131<20,25,IF($U131<30,45,IF($U131<50,70,101))))),"") | AA131: =IF(U131<>"",IF($U131<10,1.5,IF($U131<30,1.75,2)),"") | AC131: =IFERROR(W131*Y131*AA131,"")
G132: =IFERROR(INDEX(#REF!,MATCH(C132,#REF!,0)),"") | U132: =IFERROR(MAX(INDEX(#REF!,MATCH('14312'!C132,#REF!,0)),INDEX(#REF!,MATCH('14312'!C132,#REF!,0))),"") | W132: =IF(U132<>"",IF(C132="C4431",SUMIFS(#REF!,#REF!,C132,#REF!,$C$95)/2,SUMIFS(#REF!,#REF!,C132,#REF!,$C$95)),"") | Y132: =IF(U132<>"",IF(C132="C4431",4*4*2/9,IF($U132<10,15,IF($U132<20,25,IF($U132<30,45,IF($U132<50,70,101))))),"") | AA132: =IF(U132<>"",IF($U132<10,1.5,IF($U132<30,1.75,2)),"") | AC132: =IFERROR(W132*Y132*AA132,"")
G133: =IFERROR(INDEX(#REF!,MATCH(C133,#REF!,0)),"") | U133: =IFERROR(MAX(INDEX(#REF!,MATCH('14312'!C133,#REF!,0)),INDEX(#REF!,MATCH('14312'!C133,#REF!,0))),"") | W133: =IF(U133<>"",IF(C133="C4431",SUMIFS(#REF!,#REF!,C133,#REF!,$C$95)/2,SUMIFS(#REF!,#REF!,C133,#REF!,$C$95)),"") | Y133: =IF(U133<>"",IF(C133="C4431",4*4*2/9,IF($U133<10,15,IF($U133<20,25,IF($U133<30,45,IF($U133<50,70,101))))),"") | AA133: =IF(U133<>"",IF($U133<10,1.5,IF($U133<30,1.75,2)),"") | AC133: =IFERROR(W133*Y133*AA133,"")
G134: =IFERROR(INDEX(#REF!,MATCH(C134,#REF!,0)),"") | U134: =IFERROR(MAX(INDEX(#REF!,MATCH('14312'!C134,#REF!,0)),INDEX(#REF!,MATCH('14312'!C134,#REF!,0))),"") | W134: =IF(U134<>"",IF(C134="C4431",SUMIFS(#REF!,#REF!,C134,#REF!,$C$95)/2,SUMIFS(#REF!,#REF!,C134,#REF!,$C$95)),"") | Y134: =IF(U134<>"",IF(C134="C4431",4*4*2/9,IF($U134<10,15,IF($U134<20,25,IF($U134<30,45,IF($U134<50,70,101))))),"") | AA134: =IF(U134<>"",IF($U134<10,1.5,IF($U134<30,1.75,2)),"") | AC134: =IFERROR(W134*Y134*AA134,"")
AB135: Total = | AC135: =SUM(AC98:AE134) -> 0
AC136: Page | AD136: =AD91+1 -> 3 | AE136: of | AF136: 4
A137: CCN: | C137: =C92 -> 14312 | M137: Nomenclature: | R137: =R92 -> Operational Vehicle Laydown Area
C139: Operational Vehicle Laydown Area per P-80 Table 14312-1
C140: =B23 -> M29030 | F140: =E23 -> EOD Requirement
C141: TAMCN | G141: Description | U141: L, ft | W141: No. | Y141: Area (NSY) | AA141: NTG | AC141: GSY
C143: D0022 | G143: =IFERROR(INDEX(#REF!,MATCH(C143,#REF!,0)),"") | U143: =IFERROR(MAX(INDEX(#REF!,MATCH('14312'!C143,#REF!,0)),INDEX(#REF!,MATCH('14312'!C143,#REF!,0))),"") | W143: 4 | Y143: =IF(U143<>"",IF(C143="C4431",4*4*2/9,IF($U143<10,15,IF($U143<20,25,IF($U143<30,45,IF($U143<50,70,101))))),"") | AA143: =IF(U143<>"",IF($U143<10,1.5,IF($U143<30,1.75,2)),"") | AC143: =IFERROR(W143*Y143*AA143,"")
C144: D0187 | G144: =IFERROR(INDEX(#REF!,MATCH(C144,#REF!,0)),"") | U144: =IFERROR(MAX(INDEX(#REF!,MATCH('14312'!C144,#REF!,0)),INDEX(#REF!,MATCH('14312'!C144,#REF!,0))),"") | W144: =IF(U144<>"",IF(C144="C4431",SUMIFS(#REF!,#REF!,C144,#REF!,$C$140)/2,SUMIFS(#REF!,#REF!,C144,#REF!,$C$140)),"") | Y144: =IF(U144<>"",IF(C144="C4431",4*4*2/9,IF($U144<10,15,IF($U144<20,25,IF($U144<30,45,IF($U144<50,70,101))))),"") | AA144: =IF(U144<>"",IF($U144<10,1.5,IF($U144<30,1.75,2)),"") | AC144: =IFERROR(W144*Y144*AA144,"")
C145: D1158 | G145: =IFERROR(INDEX(#REF!,MATCH(C145,#REF!,0)),"") | U145: =IFERROR(MAX(INDEX(#REF!,MATCH('14312'!C145,#REF!,0)),INDEX(#REF!,MATCH('14312'!C145,#REF!,0))),"") | W145: =IF(U145<>"",IF(C145="C4431",SUMIFS(#REF!,#REF!,C145,#REF!,$C$140)/2,SUMIFS(#REF!,#REF!,C145,#REF!,$C$140)),"") | Y145: =IF(U145<>"",IF(C145="C4431",4*4*2/9,IF($U145<10,15,IF($U145<20,25,IF($U145<30,45,IF($U145<50,70,101))))),"") | AA145: =IF(U145<>"",IF($U145<10,1.5,IF($U145<30,1.75,2)),"") | AC145: =IFERROR(W145*Y145*AA145,"")
C146: E0070 | G146: =IFERROR(INDEX(#REF!,MATCH(C146,#REF!,0)),"") | U146: =IFERROR(MAX(INDEX(#REF!,MATCH('14312'!C146,#REF!,0)),INDEX(#REF!,MATCH('14312'!C146,#REF!,0))),"") | W146: =IF(U146<>"",IF(C146="C4431",SUMIFS(#REF!,#REF!,C146,#REF!,$C$140)/2,SUMIFS(#REF!,#REF!,C146,#REF!,$C$140)),"") | Y146: =IF(U146<>"",IF(C146="C4431",4*4*2/9,IF($U146<10,15,IF($U146<20,25,IF($U146<30,45,IF($U146<50,70,101))))),"") | AA146: =IF(U146<>"",IF($U146<10,1.5,IF($U146<30,1.75,2)),"") | AC146: =IFERROR(W146*Y146*AA146,"")
C147: E0070 | G147: =IFERROR(INDEX(#REF!,MATCH(C147,#REF!,0)),"") | U147: =IFERROR(MAX(INDEX(#REF!,MATCH('14312'!C147,#REF!,0)),INDEX(#REF!,MATCH('14312'!C147,#REF!,0))),"") | W147: =IF(U147<>"",IF(C147="C4431",SUMIFS(#REF!,#REF!,C147,#REF!,$C$140)/2,SUMIFS(#REF!,#REF!,C147,#REF!,$C$140)),"") | Y147: =IF(U147<>"",IF(C147="C4431",4*4*2/9,IF($U147<10,15,IF($U147<20,25,IF($U147<30,45,IF($U147<50,70,101))))),"") | AA147: =IF(U147<>"",IF($U147<10,1.5,IF($U147<30,1.75,2)),"") | AC147: =IFERROR(W147*Y147*AA147,"")
G148: =IFERROR(INDEX(#REF!,MATCH(C148,#REF!,0)),"") | U148: =IFERROR(MAX(INDEX(#REF!,MATCH('14312'!C148,#REF!,0)),INDEX(#REF!,MATCH('14312'!C148,#REF!,0))),"") | W148: =IF(U148<>"",IF(C148="C4431",SUMIFS(#REF!,#REF!,C148,#REF!,$C$140)/2,SUMIFS(#REF!,#REF!,C148,#REF!,$C$140)),"") | Y148: =IF(U148<>"",IF(C148="C4431",4*4*2/9,IF($U148<10,15,IF($U148<20,25,IF($U148<30,45,IF($U148<50,70,101))))),"") | AA148: =IF(U148<>"",IF($U148<10,1.5,IF($U148<30,1.75,2)),"") | AC148: =IFERROR(W148*Y148*AA148,"")
G149: =IFERROR(INDEX(#REF!,MATCH(C149,#REF!,0)),"") | U149: =IFERROR(MAX(INDEX(#REF!,MATCH('14312'!C149,#REF!,0)),INDEX(#REF!,MATCH('14312'!C149,#REF!,0))),"") | W149: =IF(U149<>"",IF(C149="C4431",SUMIFS(#REF!,#REF!,C149,#REF!,$C$140)/2,SUMIFS(#REF!,#REF!,C149,#REF!,$C$140)),"") | Y149: =IF(U149<>"",IF(C149="C4431",4*4*2/9,IF($U149<10,15,IF($U149<20,25,IF($U149<30,45,IF($U149<50,70,101))))),"") | AA149: =IF(U149<>"",IF($U149<10,1.5,IF($U149<30,1.75,2)),"") | AC149: =IFERROR(W149*Y149*AA149,"")
G150: =IFERROR(INDEX(#REF!,MATCH(C150,#REF!,0)),"") | U150: =IFERROR(MAX(INDEX(#REF!,MATCH('14312'!C150,#REF!,0)),INDEX(#REF!,MATCH('14312'!C150,#REF!,0))),"") | W150: =IF(U150<>"",IF(C150="C4431",SUMIFS(#REF!,#REF!,C150,#REF!,$C$140)/2,SUMIFS(#REF!,#REF!,C150,#REF!,$C$140)),"") | Y150: =IF(U150<>"",IF(C150="C4431",4*4*2/9,IF($U150<10,15,IF($U150<20,25,IF($U150<30,45,IF($U150<50,70,101))))),"") | AA150: =IF(U150<>"",IF($U150<10,1.5,IF($U150<30,1.75,2)),"") | AC150: =IFERROR(W150*Y150*AA150,"")
G151: =IFERROR(INDEX(#REF!,MATCH(C151,#REF!,0)),"") | U151: =IFERROR(MAX(INDEX(#REF!,MATCH('14312'!C151,#REF!,0)),INDEX(#REF!,MATCH('14312'!C151,#REF!,0))),"") | W151: =IF(U151<>"",IF(C151="C4431",SUMIFS(#REF!,#REF!,C151,#REF!,$C$140)/2,SUMIFS(#REF!,#REF!,C151,#REF!,$C$140)),"") | Y151: =IF(U151<>"",IF(C151="C4431",4*4*2/9,IF($U151<10,15,IF($U151<20,25,IF($U151<30,45,IF($U151<50,70,101))))),"") | AA151: =IF(U151<>"",IF($U151<10,1.5,IF($U151<30,1.75,2)),"") | AC151: =IFERROR(W151*Y151*AA151,"")
G152: =IFERROR(INDEX(#REF!,MATCH(C152,#REF!,0)),"") | U152: =IFERROR(MAX(INDEX(#REF!,MATCH('14312'!C152,#REF!,0)),INDEX(#REF!,MATCH('14312'!C152,#REF!,0))),"") | W152: =IF(U152<>"",IF(C152="C4431",SUMIFS(#REF!,#REF!,C152,#REF!,$C$140)/2,SUMIFS(#REF!,#REF!,C152,#REF!,$C$140)),"") | Y152: =IF(U152<>"",IF(C152="C4431",4*4*2/9,IF($U152<10,15,IF($U152<20,25,IF($U152<30,45,IF($U152<50,70,101))))),"") | AA152: =IF(U152<>"",IF($U152<10,1.5,IF($U152<30,1.75,2)),"") | AC152: =IFERROR(W152*Y152*AA152,"")
G153: =IFERROR(INDEX(#REF!,MATCH(C153,#REF!,0)),"") | U153: =IFERROR(MAX(INDEX(#REF!,MATCH('14312'!C153,#REF!,0)),INDEX(#REF!,MATCH('14312'!C153,#REF!,0))),"") | W153: =IF(U153<>"",IF(C153="C4431",SUMIFS(#REF!,#REF!,C153,#REF!,$C$140)/2,SUMIFS(#REF!,#REF!,C153,#REF!,$C$140)),"") | Y153: =IF(U153<>"",IF(C153="C4431",4*4*2/9,IF($U153<10,15,IF($U153<20,25,IF($U153<30,45,IF($U153<50,70,101))))),"") | AA153: =IF(U153<>"",IF($U153<10,1.5,IF($U153<30,1.75,2)),"") | AC153: =IFERROR(W153*Y153*AA153,"")
G154: =IFERROR(INDEX(#REF!,MATCH(C154,#REF!,0)),"") | U154: =IFERROR(MAX(INDEX(#REF!,MATCH('14312'!C154,#REF!,0)),INDEX(#REF!,MATCH('14312'!C154,#REF!,0))),"") | W154: =IF(U154<>"",IF(C154="C4431",SUMIFS(#REF!,#REF!,C154,#REF!,$C$140)/2,SUMIFS(#REF!,#REF!,C154,#REF!,$C$140)),"") | Y154: =IF(U154<>"",IF(C154="C4431",4*4*2/9,IF($U154<10,15,IF($U154<20,25,IF($U154<30,45,IF($U154<50,70,101))))),"") | AA154: =IF(U154<>"",IF($U154<10,1.5,IF($U154<30,1.75,2)),"") | AC154: =IFERROR(W154*Y154*AA154,"")
G155: =IFERROR(INDEX(#REF!,MATCH(C155,#REF!,0)),"") | U155: =IFERROR(MAX(INDEX(#REF!,MATCH('14312'!C155,#REF!,0)),INDEX(#REF!,MATCH('14312'!C155,#REF!,0))),"") | W155: =IF(U155<>"",IF(C155="C4431",SUMIFS(#REF!,#REF!,C155,#REF!,$C$140)/2,SUMIFS(#REF!,#REF!,C155,#REF!,$C$140)),"") | Y155: =IF(U155<>"",IF(C155="C4431",4*4*2/9,IF($U155<10,15,IF($U155<20,25,IF($U155<30,45,IF($U155<50,70,101))))),"") | AA155: =IF(U155<>"",IF($U155<10,1.5,IF($U155<30,1.75,2)),"") | AC155: =IFERROR(W155*Y155*AA155,"")
G156: =IFERROR(INDEX(#REF!,MATCH(C156,#REF!,0)),"") | U156: =IFERROR(MAX(INDEX(#REF!,MATCH('14312'!C156,#REF!,0)),INDEX(#REF!,MATCH('14312'!C156,#REF!,0))),"") | W156: =IF(U156<>"",IF(C156="C4431",SUMIFS(#REF!,#REF!,C156,#REF!,$C$140)/2,SUMIFS(#REF!,#REF!,C156,#REF!,$C$140)),"") | Y156: =IF(U156<>"",IF(C156="C4431",4*4*2/9,IF($U156<10,15,IF($U156<20,25,IF($U156<30,45,IF($U156<50,70,101))))),"") | AA156: =IF(U156<>"",IF($U156<10,1.5,IF($U156<30,1.75,2)),"") | AC156: =IFERROR(W156*Y156*AA156,"")
G157: =IFERROR(INDEX(#REF!,MATCH(C157,#REF!,0)),"") | U157: =IFERROR(MAX(INDEX(#REF!,MATCH('14312'!C157,#REF!,0)),INDEX(#REF!,MATCH('14312'!C157,#REF!,0))),"") | W157: =IF(U157<>"",IF(C157="C4431",SUMIFS(#REF!,#REF!,C157,#REF!,$C$140)/2,SUMIFS(#REF!,#REF!,C157,#REF!,$C$140)),"") | Y157: =IF(U157<>"",IF(C157="C4431",4*4*2/9,IF($U157<10,15,IF($U157<20,25,IF($U157<30,45,IF($U157<50,70,101))))),"") | AA157: =IF(U157<>"",IF($U157<10,1.5,IF($U157<30,1.75,2)),"") | AC157: =IFERROR(W157*Y157*AA157,"")
G158: =IFERROR(INDEX(#REF!,MATCH(C158,#REF!,0)),"") | U158: =IFERROR(MAX(INDEX(#REF!,MATCH('14312'!C158,#REF!,0)),INDEX(#REF!,MATCH('14312'!C158,#REF!,0))),"") | W158: =IF(U158<>"",IF(C158="C4431",SUMIFS(#REF!,#REF!,C158,#REF!,$C$140)/2,SUMIFS(#REF!,#REF!,C158,#REF!,$C$140)),"") | Y158: =IF(U158<>"",IF(C158="C4431",4*4*2/9,IF($U158<10,15,IF($U158<20,25,IF($U158<30,45,IF($U158<50,70,101))))),"") | AA158: =IF(U158<>"",IF($U158<10,1.5,IF($U158<30,1.75,2)),"") | AC158: =IFERROR(W158*Y158*AA158,"")
G159: =IFERROR(INDEX(#REF!,MATCH(C159,#REF!,0)),"") | U159: =IFERROR(MAX(INDEX(#REF!,MATCH('14312'!C159,#REF!,0)),INDEX(#REF!,MATCH('14312'!C159,#REF!,0))),"") | W159: =IF(U159<>"",IF(C159="C4431",SUMIFS(#REF!,#REF!,C159,#REF!,$C$140)/2,SUMIFS(#REF!,#REF!,C159,#REF!,$C$140)),"") | Y159: =IF(U159<>"",IF(C159="C4431",4*4*2/9,IF($U159<10,15,IF($U159<20,25,IF($U159<30,45,IF($U159<50,70,101))))),"") | AA159: =IF(U159<>"",IF($U159<10,1.5,IF($U159<30,1.75,2)),"") | AC159: =IFERROR(W159*Y159*AA159,"")
... G179: =IFERROR(INDEX(#REF!,MATCH(C179,#REF!,0)),"") | U179: =IFERROR(MAX(INDEX(#REF!,MATCH('14312'!C179,#REF!,0)),INDEX(#REF!,MATCH('14312'!C179,#REF!,0))),"") | W179: =IF(U179<>"",IF(C179="C4431",SUMIFS(#REF!,#REF!,C179,#REF!,$C$140)/2,SUMIFS(#REF!,#REF!,C179,#REF!,$C$140)),"") | Y179: =IF(U179<>"",IF(C179="C4431",4*4*2/9,IF($U179<10,15,IF($U179<20,25,IF($U179<30,45,IF($U179<50,70,101))))),"") | AA179: =IF(U179<>"",IF($U179<10,1.5,IF($U179<30,1.75,2)),"") | AC179: =IFERROR(W179*Y179*AA179,"")
AB180: Total = | AC180: =SUM(AC143:AE179) -> 0
...

Sheet 14326
A1: BASIC FACILITY REQUIREMENTS WORKSHEET
A3: Installation: | F3: ='Header '!B2 -> MCB Camp Butler | M3: Tenant: | R3: ='Header '!B4 -> CLB 4
A4: Installation UIC: | F4: ='Header '!A2 -> M67400 | M4: Tenant UIC: | R4: ='Header '!A4 -> M29030 | Y4: Planning Area: | AE4: =UNIT_ROLLUP!AE4 -> SW
A5: CCN: | C5: 14326 | M5: Nomenclature: | R5: MC Explosive Ordnance Disposal Platoon Facility
A6: LOADING ANALYSIS / JUSTIFICATION OF REQUIREMENT
A7: Description:
B8: Mission: The Engineering Support BN provides general engineering support to operational forces. Support includes mobility, counter mobility and survivability enhancements, Explosive Ordnance Disposal (EOD), and the handling, storage and distribution of bulk water and fuel. CCN: This facility is responsible for manning, equipping, and training for EOD operations in support of Fleet Marine Forces. It is scaled to match the EOD company of 9 officers and 97 enlisted. Justification: CLB 22 requires an EOD section, this section is maintained by 8th ESB, EOD Co aboard Camp Lejeune.
A16: Planning Criteria:
B17: UFC 2-000-05N
A18: Loading:
B19: FY2025 Table of Organization and Equipment
A20: Analysis:
B21: Unit | M21: Area
B22: ='Header '!A6 -> M29030 | E22: ='Header '!B6 -> CLB 4 | M22: =AB73 -> #REF!
B23: Total = | M23: =SUM(M22:P22) -> #REF!
K42: SEE THE ATTACHED PAGES FOR CALCULATIONS
A43: TOTAL REQUIREMENT: | H43: =M23 -> #REF! | L43: GSF | AC43: Page | AD43: 1 | AE43: of | AF43: 3
A44: CCN: | C44: =C5 -> 14326 | M44: Nomenclature: | R44: =R5 -> MC Explosive Ordnance Disposal Platoon Facility
B47: =B22 -> M29030 | E47: =E22 -> CLB 4
B48: Area | T48: SF per Unit | X48: PN or Qty | AB48: NSF
B50: Company Headquarters Administration | AB50: =T50*X50 -> 0
C51: Offices | T51: 90 | X51: =COUNTIF(#REF!,"14326o") -> #REF! | AB51: =T51*X51 -> #REF!
C52: Cubicles | T52: 45 | X52: =COUNTIF(#REF!,"14326c") -> #REF! | AB52: =T52*X52 -> #REF!
AB53: =T53*X53 -> 0
B54: Classified Publications Vault | T54: 811 | X54: 1 | AB54: =T54*X54 -> 811
B55: Bathroom/Shower (Male) | AB55: =T55*X55 -> 0
C56: Water Closet | T56: 15 | X56: 1 | AB56: =T56*X56 -> 15
C57: Urinal | T57: 6 | X57: 2 | AB57: =T57*X57 -> 12
C58: Lavatory | T58: 3 | X58: 1 | AB58: =T58*X58 -> 3
C59: Shower | T59: 20 | X59: 2 | AB59: =T59*X59 -> 40
B60: Bathroom/Shower (Female) | T60: 200 | X60: 0 | AB60: =T60*X60 -> 0
B61: Personnel Lockers | T61: 18 | X61: 5 | AB61: =T61*X61 -> 90
B62: Multi-Purpose/Conference Room | T62: 16 | X62: 0 | AB62: =T62*X62 -> 0
B63: Training Aids Library | T63: 2000 | X63: 0 | AB63: =T63*X63 -> 0
B64: Break Area | T64: 811 | X64: 0 | AB64: =T64*X64 -> 0
B65: Material and equipment work area | T65: 2000 | X65: 0 | AB65: =T65*X65 -> 0
AB66: =W117 -> 0
B67: Vehicle Maintenance Bay (see following worksheet) | AB67: =N105 -> #REF!
B68: Combat Service Support Teams (from Combat Logistics Battalion)
C69: Administration | T69: 1200 | X69: 0 | AB69: =T69*X69 -> 0
C70: Material, equipment, and storage | T70: 1000 | X70: 0 | AB70: =T70*X70 -> 0
Y72: Subtotal = | AB72: =SUM(AB50:AD70) -> #REF!
P73: Net to Gross Factor | Q73: 1.33 | Y73: Total = | AB73: =AB72*Q73 -> #REF!
AC84: Page | AD84: 2 | AE84: of | AF84: 3
A85: CCN: | C85: =C44 -> 14326 | M85: Nomenclature: | R85: =R44 -> MC Explosive Ordnance Disposal Platoon Facility
B86: Maintenance Bay Calculations - per UFC 2-000-05N, Tables 21420-1, 2, & 3
B87: =B47 -> M29030 | E87: =E47 -> CLB 4
B88: Type of Equipment | N88: Number | R88: Space Factor | V88: Repair Bays
B89: Automotive | C89: 0061-0099 | G89: Buses | N89: =SUMIFS(#REF!,#REF!,$B$87,#REF!,G89) -> #REF! | R89: 0.063 | V89: =N89*R89 -> #REF!
C90: 0102-0299 | G90: Sedans, ambulances | N90: =SUMIFS(#REF!,#REF!,$B$87,#REF!,G90) -> #REF! | R90: 0.015 | V90: =N90*R90 -> #REF!
C91: 0300-0745 | G91: Trucks | N91: =SUMIFS(#REF!,#REF!,$B$87,#REF!,G91) -> #REF! | R91: 0.023 | V91: =N91*R91 -> #REF!
C92: 0800-0897 | G92: Trailers | N92: =SUMIFS(#REF!,#REF!,$B$87,#REF!,G92) -> #REF! | R92: 0.016 | V92: =N92*R92 -> #REF!
C93: 0900-0905 | G93: Motorcycles | N93: =SUMIFS(#REF!,#REF!,$B$87,#REF!,G93) -> #REF! | R93: 0.004 | V93: =N93*R93 -> #REF!
B94: MH | C94: 1100-1900 | G94: Tractors, forklifts | N94: =SUMIFS(#REF!,#REF!,$B$87,#REF!,G94) -> #REF! | R94: 0.02 | V94: =N94*R94 -> #REF!
B95: Construction/other | C95: 2300-2840 | G95: Crushing, mixing | N95: =SUMIFS(#REF!,#REF!,$B$87,#REF!,G95) -> #REF! | R95: 0.016 | V95: =N95*R95 -> #REF!
C96: 3100-3720 | G96: Drilling, driving | N96: =SUMIFS(#REF!,#REF!,$B$87,#REF!,G96) -> #REF! | R96: 0.025 | V96: =N96*R96 -> #REF!
C97: 4210-4952 | G97: Excavating, Grading | N97: =SUMIFS(#REF!,#REF!,$B$87,#REF!,G97) -> #REF! | R97: 0.02 | V97: =N97*R97 -> #REF!
C98: 5110-5930 | G98: Generators, mowers | N98: =SUMIFS(#REF!,#REF!,$B$87,#REF!,G98) -> #REF! | R98: 0.016 | V98: =N98*R98 -> #REF!
C99: 7100-7501 | G99: Firefighting | N99: =SUMIFS(#REF!,#REF!,$B$87,#REF!,G99) -> #REF! | R99: 0.03 | V99: =N99*R99 -> #REF!
C100: 8120-8800 | G100: Weight handling | N100: =SUMIFS(#REF!,#REF!,$B$87,#REF!,G100) -> #REF! | R100: 0.092 | V100: =N100*R100 -> #REF!
U101: Total = | V101: =SUM(V89:Y100) -> #REF!
Q102: Rounded Total4 = | V102: =ROUNDUP(V101,0) -> #REF!
B104: Maint Bays | F104: Admin Sppt1 | J104: Direct Sppt1 | N104: Total | S104: SL3 Storage2 | W104: =W105*W106/2 -> 240
B105: =V102*((W105*W106)+W104)*W107 -> #REF! | F105: =414.36*V102^0.854 -> #REF! | J105: =IF(V102<=14,347.32*V102+1128.6,22.616*V102+5706.1) -> #REF! | N105: =SUM(B105:M105) -> #REF! | S105: Bay Length3 | W105: 30
S106: Bay Width3 | W106: 16
S107: Bay NTG | W107: 1.33
B110: 1 Support space requirements based on UFC 2-000-05N, Table 21420-4 (Space Requirements for Automotive Vehicle Maintenance Facility) and these equations were used to determine the admin and direct support spaces. 2 The 21420 criteria used here is intended for civilian motor transportation shops. The criteria does not account for component equipment (SL3) that must be removed, stored, and secured from operational unit vehicles. It was assumed that an extra half-bay is required for every calculated repair bay. 3 JLTV is the largest vehicle in the inventory and measures 21'x8' in its largest variant. A standard 30ft x 16ft (480sf) bay is adequate. 4 Repair bays are rounded up to the closest whole number.
AC130: Page | AD130: 3 | AE130: of | AF130: 3

Sheet 14345
A1: BASIC FACILITY REQUIREMENTS WORKSHEET
A3: Installation: | F3: H&S BN MCIPAC MCB CP BUTLER JA | M3: Tenant: | R3: CLB 4
A4: Installation UIC: | F4: M67400 | M4: Tenant UIC: | R4: M29030 | Y4: Planning Area: SW
A5: CCN: | C5: 14345 | M5: Nomenclature: | R5: ARMORY
A6: SPACE REQUIREMENT ANALYSIS · CCN 14345 · UFC 2-000-05N, TABLE 21510-1 | Planning Factor: 1.25 GSF per Sensitive Item
A7: Sensitive Item Category (Primary Items - All Four Companies) | V7: GSF / Item | Y7: Count | AB7: GSF
A8: Night Vision Devices (AN/PVS-14, AN/PVS-31D) | V8: 1.25 | Y8: 237 | AB8: =V8*Y8 -> 296.25
A9: Machine Guns (M240B, MK19 MOD 3) | V9: 1.25 | Y9: 14 | AB9: =V9*Y9 -> 17.5
A10: Rifles, Carbines, and Shotguns | V10: 1.25 | Y10: 19 | AB10: =V10*Y10 -> 23.75
A11: Grenade Launchers (M320A1) | V11: 1.25 | Y11: 4 | AB11: =V11*Y11 -> 5
A12: Thermal Sights (AN/PAS-13D) | V12: 1.25 | Y12: 4 | AB12: =V12*Y12 -> 5
A13: Other Sensitive Items (Optics, Accessories, Spare Barrels) | V13: 1.25 | Y13: 52 | AB13: =V13*Y13 -> 65
A15: Total Sensitive Items = 330 | Total NSF | AB15: =SUM(AB8:AB13) -> 412.5
A16: Required GSF = ROUNDUP(Total NSF, 0) = 413 GSF | AB16: =ROUNDUP(AB15,0) -> 413
A37: TOTAL REQUIREMENT: | H37: =AB16 -> 413 | L37: GSF | AB37: Page 1 of 1

Sheet 21451
A1: BASIC FACILITY REQUIREMENTS WORKSHEET
A3: Installation: | F3: H&S BN MCIPAC MCB CP BUTLER JA | M3: Tenant: | R3: CLB 4
A4: Installation UIC: | F4: M67400 | M4: Tenant UIC: | R4: M29030 | Y4: Planning Area: SW
A5: CCN: | C5: 21451 | M5: Nomenclature: | R5: AUTO ORGANIZATION SHOP
A6: SPACE REQUIREMENT ANALYSIS · CCN 21451 · UFC 2-000-05N / UFC 21440-1.1 | Net to Gross Factor: 1.33
A7: SECTION 1 - ADMINISTRATIVE SPACE (UFC 2-000-05N Chapter 21)
A8: Personnel Category | V8: SF / Person | Y8: Count | AB8: NSF
A9: Officers - Private Offices (1STLT Platoon Commanders) | V9: 120 | Y9: 2 | AB9: =V9*Y9 -> 240
A10: SNCOs and Staff - Cubicles (GYSGTs, SSGTs, Senior Enlisted) | V10: 60 | Y10: 11 | AB10: =V10*Y10 -> 660
A11: Administrative Subtotal | AB11: =SUM(AB9:AB10) -> 900
A13: SECTION 2 - MAINTENANCE BAYS (UFC 21440-1.1 | 1 Bay per 30 Self-Propelled Vehicles | 420 SF per Bay)
A14: Vehicle Category (Self-Propelled Only - Trailers and Ambulances Excluded) | V14: SF / Bay | Y14: Qty | AB14: NSF
A15: Light Utility Vehicles (JLTV-class: M1280, M1279, M1278, M1123) | V15: 420 | Y15: 33
A16: Medium / Heavy Cargo (AMK23A1, AMK27A1) | V16: 420 | Y16: 23
A17: Wrecker / Recovery (AMK36) | V17: 420 | Y17: 3
A18: Total Self-Propelled Vehicles = 59 | CEILING(59 / 30) = 2 Bays | AB18: =SUM(Y15:Y17) -> 59
A19: Maintenance Bays (2 Bays × 420 SF per bay per UFC 21440-1.1) | V19: 420 | Y19: 2 | AB19: =V19*Y19 -> 840
A20: Maintenance Bays Subtotal | AB20: =AB19 -> 840
A22: TOTAL SPACE REQUIREMENT
A23: Total NSF (Administrative + Maintenance Bays) | AB23: =AB11+AB20 -> 1740
A24: NTG Factor = 1.33 | Required GSF = ROUNDUP(1,740 × 1.33, 0) = 2,315 GSF | V24: 1.33 | AB24: =ROUNDUP(AB23*V24,0) -> 2315
A37: TOTAL REQUIREMENT: | H37: =AB24 -> 2315 | L37: GSF | Z37: Page 1 of 1 | AF37: 1

Sheet 21710
A1: BASIC FACILITY REQUIREMENTS WORKSHEET
A3: Installation: | F3: =UNIT_ROLLUP!F3 -> H&S BN MCIPAC MCB CP BUTLER JA | M3: Tenant: | R3: =UNIT_ROLLUP!R3 -> CLB 4
A4: Installation UIC: | F4: =UNIT_ROLLUP!F4 -> M67400 | M4: Tenant UIC: | R4: =UNIT_ROLLUP!R4 -> M29030 | Y4: Planning Area: | AE4: =UNIT_ROLLUP!AE4 -> SW
A5: CCN: | C5: 21710 | M5: Nomenclature: | R5: Electronic/Communications Maintenance Shop
A6: LOADING ANALYSIS / JUSTIFICATION OF REQUIREMENT
A7: Description:
B8: Mission: This Mission Statement defines the unit's role and responsibilities in support of the Marine air-ground task force (MAGTF), the supporting element (SE), and/or Joint operations and prescribes the unit's organizational structure and Capabilities in accordance with its tasks that manifests in the unit's table of organization and equipment (T/O&E). CCN: Provides for maintenance and repair of non-airborne equipment. It contains office and support spaces for the Equipment Maintenance Officer (EMO) and the EMO Staff, equipment maintenance and training areas, and a small storage area for parts and supplies directly under the control of the EMO Justification: CLR 27 requires a comm/elec shop to support/store their A TAMCN equipment and for outfitting their vehicles/Pn.
A17: Planning Criteria:
B18: UFC 2-000-05N (P-80)
A20: Loading:
B21: FY2025 Table of Organization / Equipment (attached)
A23: Analysis:
B24: Total Space Requirement
B25: Subordinate Unit | M25: Admin | P25: Storage | T25: Shop Space | X25: Maint Bays | AB25: Total
B26: ='Header '!A6 -> M29030 | E26: ='Header '!B6 -> CLB 4 | M26: =S32 -> #REF! | P26: =INDEX($Y$52:$Y$52,MATCH(B26,$B$52:$B$52,0)) -> #REF! | T26: =AD61-X26 -> #REF! | X26: =Y61*$Y$60*$AD$58 -> 638.4 | AB26: =SUM(M26:AA26) -> #REF!
AA27: Total = | AB27: =SUM(AB26:AE26) -> #REF!
B29: Admin Space see attached TO for billet breakdown
B30: Subordinate Unit | M30: Off & ≥ E61 | P30: ≤ E52 | S30: Total
M31: 120 | P31: 60
B32: =B26 -> M29030 | E32: =E26 -> CLB 4 | M32: =COUNTIFS(#REF!,"21710o",#REF!,B32) -> #REF! | P32: =COUNTIFS(#REF!,"21710c",#REF!,B32) -> #REF! | S32: =M32*M$31+P32*P$31 -> #REF!
L33: Totals = | M33: =SUM(M32:O32)*M31 -> #REF! | P33: =SUM(P32:R32)*P31 -> #REF! | S33: =SUM(S32:V32) -> #REF!
B34: 1Shown as 21710o (o = office) in TO. 120GSF = 90 NSF * 1.33 NTG
B35: 2Shown as 21710c (c = cubicle) in TO. 60 GSF = 45 NSF * 1.33 NTG. This label does NOT include marines in the shop spaces; it's intended for Data section type marines who sit at a computer full time.
A46: TOTAL REQUIREMENT: | H46: =AB27 -> #REF! | L46: GSF | AC46: Page | AD46: 1 | AE46: of | AF46: 2
A47: CCN: | C47: =C5 -> 21710 | M47: Nomenclature: | R47: =R5 -> Electronic/Communications Maintenance Shop
B49: Storage Space (4-Step Method of P-80 Section 440-2.2), see attached TE for item breakdown
B50: Subordinate Unit | M50: Net Volume | Q50: Packed Vol (1.96) | U50: NSF w/ 7ft1 SH | Y50: Gross SF
Y51: 2.5
B52: =B26 -> M29030 | E52: =E26 -> CLB 4 | M52: =SUMIFS(#REF!,#REF!,$C$5,#REF!,B52) -> #REF! | Q52: =1.96*M52 -> #REF! | U52: =Q52/7 -> #REF! | Y52: =U52*$Y$51 -> #REF!
X53: Total = | Y53: =SUM(Y52:AB52) -> #REF!
B54: 1 A 7ft stack height (a standard 6ft shelf with 1ft of storage above) was used as a warehouse type rack system is typically unavailable in a small comm/elec shop and normal garage type shelving is typically used
B57: Shop Spaces
B58: Subordinate Unit | M58: Section1 | Y58: Maint Bay2 | AA58: Total NSF | AD58: 1.33
M59: Radio | O59: Comm | Q59: Data | S59: Wire | U59: SHF | W59: Maint | AD59: Total GSF
M60: 600 | O60: 600 | Q60: 600 | S60: 600 | U60: 600 | W60: 950 | Y60: =F63*F64 -> 480
B61: =B26 -> M29030 | E61: =E26 -> CLB 4 | M61: =ROUNDUP(COUNTIFS(#REF!,"21710rs",#REF!,$B$61)/15,0) -> #REF! | O61: =ROUNDUP(COUNTIFS(#REF!,"21710cs",#REF!,B61)/15,0) -> #REF! | Q61: =ROUNDUP(COUNTIFS(#REF!,"21710ds",#REF!,B61)/15,0) -> #REF! | S61: =ROUNDUP(COUNTIFS(#REF!,"21710ws",#REF!,B61)/15,0) -> #REF! | U61: =ROUNDUP(COUNTIFS(#REF!,"21710shf",#REF!,B61)/15,0) -> #REF! | W61: =ROUNDUP(COUNTIFS(#REF!,"21710ms",#REF!,B61)/15,0) -> #REF! | Y61: 1 | AA61: =M61*$M$60+O61*$O$60+Q61*$Q$60+S61*$S$60+U61*U60+W61*$W$60+Y61*$Y$60 -> #REF! | AD61: =AA61*$AD$58 -> #REF!
AA62: Total = | AD62: =SUM(AD61:AF61) -> #REF!
B63: Bay Length2 | F63: 30
B64: Bay Width2 | F64: 16
B66: 1 All Sections will have a 600 NSF space allowance unless it is a Maintenance Section that will require 950 NSF. Each Section is sized for approximately 15 PN. 2 A standard 30ft x 16ft (480sf) bay is adequate.
AC84: Page | AD84: 2 | AE84: of | AF84: 2

Sheet 21730
A1: BASIC FACILITY REQUIREMENTS WORKSHEET
A3: Installation: | F3: =UNIT_ROLLUP!F3 -> H&S BN MCIPAC MCB CP BUTLER JA | M3: Tenant: | R3: =UNIT_ROLLUP!R3 -> CLB 4
A4: Installation UIC: | F4: =UNIT_ROLLUP!F4 -> M67400 | M4: Tenant UIC: | R4: =UNIT_ROLLUP!R4 -> M29030 | Y4: Planning Area: | AE4: =UNIT_ROLLUP!AE4 -> SW
A5: CCN: | C5: 21730 | M5: Nomenclature: | R5: Field Maintenance Shop (Comms/Elecs)
A6: LOADING ANALYSIS / JUSTIFICATION OF REQUIREMENT
A7: Description:
B8: Mission: This Mission Statement defines the unit's role and responsibilities in support of the Marine air-ground task force (MAGTF), the supporting element (SE), and/or Joint operations and prescribes the unit's organizational structure and Capabilities in accordance with its tasks that manifests in the unit's table of organization and equipment (T/O&E). CCN: Provides for maintenance and repair of non-airborne equipment. It contains office and support spaces for the Equipment Maintenance Officer (EMO) and the EMO Staff, equipment maintenance and training areas, and a small storage area for parts and supplies directly under the control of the EMO Justification: CLR 27 requires a comm/elec shop to support/store their A TAMCN equipment and for outfitting their vehicles/Pn.
A17: Planning Criteria:
B18: FC 2-000-05N (P-80)
A20: Loading:
B21: FY2029 Table of Organization / Equipment (attached)
A23: Analysis:
B24: Total Space Requirement
B25: Subordinate Unit | M25: Admin | P25: Storage | T25: Shop Space | X25: Maint Bays | AB25: Total
B26: ='Header '!A6 -> M29030 | E26: ='Header '!B6 -> CLB 4 | M26: =S32 -> #REF! | P26: =INDEX($Y$52:$Y$52,MATCH(B26,$B$52:$B$52,0)) -> #REF! | T26: =AD61-X26 -> #REF! | X26: =Y61*$Y$60*$AD$58 -> 638.4 | AB26: =SUM(M26:AA26) -> #REF!
AA27: Total = | AB27: =SUM(AB26:AE26) -> #REF!
B29: Admin Space see attached TO for billet breakdown
B30: Subordinate Unit | M30: Off & ≥ E61 | P30: ≤ E52 | S30: Total
M31: 120 | P31: 60
B32: =B26 -> M29030 | E32: =E26 -> CLB 4 | M32: =COUNTIFS(#REF!,"21710o",#REF!,B32) -> #REF! | P32: =COUNTIFS(#REF!,"21710c",#REF!,B32) -> #REF! | S32: =M32*M$31+P32*P$31 -> #REF!
L33: Totals = | M33: =SUM(M32:O32)*M31 -> #REF! | P33: =SUM(P32:R32)*P31 -> #REF! | S33: =SUM(S32:V32) -> #REF!
B34: 1Shown as 21710o (o = office) in TO. 120GSF = 90 NSF * 1.33 NTG
B35: 2Shown as 21710c (c = cubicle) in TO. 60 GSF = 45 NSF * 1.33 NTG. This label does NOT include marines in the shop spaces; it's intended for Data section type marines who sit at a computer full time.
A46: TOTAL REQUIREMENT: | H46: =AB27 -> #REF! | L46: GSF | AC46: Page | AD46: 1 | AE46: of | AF46: 2
A47: CCN: | C47: =C5 -> 21730 | M47: Nomenclature: | R47: =R5 -> Field Maintenance Shop (Comms/Elecs)
B49: Storage Space (4-Step Method of P-80 Section 440-2.2), see attached TE for item breakdown
B50: Subordinate Unit | M50: Net Volume | Q50: Packed Vol (1.96) | U50: NSF w/ 7ft1 SH | Y50: Gross SF
Y51: 2.5
B52: =B26 -> M29030 | E52: =E26 -> CLB 4 | M52: =SUMIFS(#REF!,#REF!,$C$5,#REF!,B52) -> #REF! | Q52: =1.96*M52 -> #REF! | U52: =Q52/7 -> #REF! | Y52: =U52*$Y$51 -> #REF!
X53: Total = | Y53: =SUM(Y52:AB52) -> #REF!
B54: 1 A 7ft stack height (a standard 6ft shelf with 1ft of storage above) was used as a warehouse type rack system is typically unavailable in a small comm/elec shop and normal garage type shelving is typically used
B57: Shop Spaces
B58: Subordinate Unit | M58: Section1 | Y58: Maint Bay2 | AA58: Total NSF | AD58: 1.33
M59: Radio | O59: Comm | Q59: Data | S59: Wire | U59: SHF | W59: Maint | AD59: Total GSF
M60: 600 | O60: 600 | Q60: 600 | S60: 600 | U60: 600 | W60: 950 | Y60: =F63*F64 -> 480
B61: =B26 -> M29030 | E61: =E26 -> CLB 4 | M61: =ROUNDUP(COUNTIFS(#REF!,"21710rs",#REF!,$B$61)/15,0) -> #REF! | O61: =ROUNDUP(COUNTIFS(#REF!,"21710cs",#REF!,B61)/15,0) -> #REF! | Q61: =ROUNDUP(COUNTIFS(#REF!,"21710ds",#REF!,B61)/15,0) -> #REF! | S61: =ROUNDUP(COUNTIFS(#REF!,"21710ws",#REF!,B61)/15,0) -> #REF! | U61: =ROUNDUP(COUNTIFS(#REF!,"21710shf",#REF!,B61)/15,0) -> #REF! | W61: =ROUNDUP(COUNTIFS(#REF!,"21710ms",#REF!,B61)/15,0) -> #REF! | Y61: 1 | AA61: =M61*$M$60+O61*$O$60+Q61*$Q$60+S61*$S$60+U61*U60+W61*$W$60+Y61*$Y$60 -> #REF! | AD61: =AA61*$AD$58 -> #REF!
AA62: Total = | AD62: =SUM(AD61:AF61) -> #REF!
B63: Bay Length2 | F63: 30
B64: Bay Width2 | F64: 16
B66: 1 All Sections will have a 600 NSF space allowance unless it is a Maintenance Section that will require 950 NSF. Each Section is sized for approximately 15 PN. 2 A standard 30ft x 16ft (480sf) bay is adequate.
AC84: Page | AD84: 2 | AE84: of | AF84: 2

Sheet 44112
A1: BASIC FACILITY REQUIREMENTS WORKSHEET
A3: Installation: | F3: =UNIT_ROLLUP!F3 -> H&S BN MCIPAC MCB CP BUTLER JA | M3: Tenant: | R3: =UNIT_ROLLUP!R3 -> CLB 4
A4: Installation UIC: | F4: =UNIT_ROLLUP!F4 -> M67400 | M4: Tenant UIC: | R4: =UNIT_ROLLUP!R4 -> M29030 | Y4: Planning Area: | AE4: SH
A5: CCN: | C5: 44112 | M5: Nomenclature: | R5: Storage of Air or Ground Organic Units - USMC
A6: LOADING ANALYSIS / JUSTIFICATION OF REQUIREMENT
A7: Description:
B8: Mission: This Mission Statement defines the unit's role and responsibilities in support of the Marine air-ground task force (MAGTF), the supporting element (SE), and/or Joint operations and prescribes the unit's organizational structure and Capabilities in accordance with its tasks that manifests in the unit's table of organization and equipment (T/O&E). CCN: Provides general purpose storage facilities assigned to Marine Corps bases, air installations and Fleet Marine Force (FMF) units for organic requirements Justification: CLR 27 requires organic supply.
A16: Planning Criteria:
B17: UFC 2-000-05N (P-80) 440 4-step method
A19: Loading:
B20: FY2025 Table of Organization / Equipment (attached)
A22: Analysis:
B23: Total Space Requirement
B24: Subordinate Unit | M24: Admin | P24: Warehouse Space | V24: Support | Y24: Pn Effects | AB24: Total
P25: On TE | S25: Non-TE
B26: ='Header '!A6 -> M29030 | E26: ='Header '!B6 -> CLB 4 | M26: =V31 | P26: =INDEX($AC$52:$AC$52,MATCH(B26,$B$52:$B$52,0)) -> #REF! | S26: =Z64 -> 0 | V26: =AA75 -> 1388.52 | Y26: =INDEX($P$81:$P$81,MATCH(B26,$B$81:$B$81,0)) -> #REF! | AB26: =SUM(M26:AA26) -> #REF!
AA27: Total = | AB27: =SUM(AB26:AE26) -> #REF!
B28: Warehouse Admin Space see attached TO for billet breakdown
B29: Subordinate Unit | M29: Off & ≥ E61 | P29: ≤ E52 | S29: Clerks3 | V29: Total
M30: 120 | P30: 60 | S30: 60
B31: =B26 -> M29030 | E31: =E26 -> CLB 4 | M31: =COUNTIFS(#REF!,"44112o",#REF!,B31) -> #REF! | P31: =COUNTIFS(#REF!,"44112c",#REF!,B31) -> #REF! | S31: =ROUNDUP((COUNTIFS(#REF!,"44112w",#REF!,B31))/3,0) -> #REF! | V31: =IFERROR($M$31*$M$30+$P$31*$P$30+($S$31*$S$32/SUM($S$31:$U$31)),"")
L32: Totals = | M32: =SUM(M31:O31)*M30 -> #REF! | P32: =SUM(P31:R31)*P30 -> #REF! | S32: =ROUNDUP(SUM(S31:U31)/3,0)*S30 -> #REF! | V32: =SUM(V31:Y31) -> 0
B33: 1Shown as 44112o (o = office) in TO.
B34: 2Shown as 44112c (c = cubicle) in TO.
B35: 3Shown as 44112w (w = warehouse) in TO. Assumes 1/3 of the warehouse clerks require a computer station for data entry within the warehouse. The total is calculated in the "Total SF" column and the number of admin spaces is rounded up. Ex. 4 clerks * 1/3 = 1.33 desks. Therefore round up to 2 desks.
A46: TOTAL REQUIREMENT: | H46: =AB27 -> #REF! | L46: GSF | AC46: Page | AD46: 1 | AE46: of | AF46: 2
A47: CCN: | C47: =C5 -> 44112 | M47: Nomenclature: | R47: =R5 -> Storage of Air or Ground Organic Units - USMC
B49: Warehouse Space TE (4-Step Method of P-80 Section 440-2.2), see attached TE for item breakdown
B50: Subordinate Unit | M50: Net Volume1 | Q50: Packed Vol (1.96) | U50: NSF w/ 12ft SH (CF) | Y50: Gross SF | AC50: Total SF2
Y51: 2.5 | AC51: 1.1
B52: =B26 -> M29030 | E52: =E26 -> CLB 4 | M52: =SUMIFS(#REF!,#REF!,$C$5,#REF!,B52) -> #REF! | Q52: =1.96*M52 -> #REF! | U52: =Q52/12 -> #REF! | Y52: =U52*$Y$51 -> #REF! | AC52: =Y52*$AC$51 -> #REF!
M53: TCF = | Q53: =SUM(Q52:T52) -> #REF! | X53: Total = | Y53: =SUM(Y52:AB52) -> #REF! | AC53: =SUM(AC52:XFD52) -> #REF!
B54: 1Each TAMCN on the TO tab with a 44112 in the CCN column is calculated in this table. The net volume was calculated using the organizational quantities shown on the TO and the dimensions listed in TFSMS, in USMC technical manuals, or through field verification. These dimensions are shown on the TO tab. Individual equipment was assumed to be supported by the LOGCOM Supply Program (IIF) or stored in the Armory.
B60: Warehouse Space Non-TE 1 (modified 4-Step Method of P-80 Section 440-2.2, measured packed volume)
B61: Description | I61: Qty | K61: L, in | M61: W, in | O61: H, in | Q61: Univ Fact | S61: Packed Vol CF | V61: NSF w/ 12ft SH | Z61: Gross SF
Z62: 2.5
S63: =I63*(K63*M63*O63/1728)*Q63 -> 0 | V63: =S63/12 -> 0 | Z63: =V63*Z62 -> 0
Y64: Total = | Z64: =SUM(Z63:AC63) -> 0
B65: 1 Unit Non TE equipment was assumed to be supported by the LOGCOM Supply Program (UIF) for FY2025.
B69: Support Space Headquarters Company only, Engineering Analysis
B70: Function | L70: Length | N70: Width | P70: Area Ea (NSF) | T70: Quantity | W70: Area (NSF) | AA70: 1.33
B71: Shipping and Receiving Area | L71: 20 | N71: 20 | P71: =L71*N71 -> 400 | T71: 1 | W71: =T71*P71 -> 400 | AA71: =$AA$70*W71 -> 532
B72: Security Cage | L72: 12 | N72: 12 | P72: =L72*N72 -> 144 | T72: 1 | W72: =T72*P72 -> 144 | AA72: =$AA$70*W72 -> 191.52
B73: Staging Area | L73: 20 | N73: 20 | P73: =L73*N73 -> 400 | T73: 1 | W73: =T73*P73 -> 400 | AA73: =$AA$70*W73 -> 532
B74: Forklift Charging Station | L74: 10 | N74: 10 | P74: =L74*N74 -> 100 | T74: 1 | W74: =T74*P74 -> 100 | AA74: =$AA$70*W74 -> 133
B75: Total = | AA75: =SUM(AA71:AC74) -> 1388.52
B79: Personal Effects Cages Engineering Analysis - 1.33 GSF per chargeable and deployable billet
B80: Subordinate Unit | M80: PN | P80: Area
B81: =B26 -> M29030 | E81: =E26 -> CLB 4 | M81: =COUNTIFS(#REF!,"1",#REF!,B81) -> #REF! | P81: =M81*1.33 -> #REF!
B82: Totals = | M82: =SUM(M81:O81) -> #REF! | P82: =SUM(P81:S81) -> #REF!
AC84: Page | AD84: 2 | AE84: of | AF84: 2

Sheet 45110
A1: BASIC FACILITY REQUIREMENTS WORKSHEET
A3: Installation: | F3: =UNIT_ROLLUP!F3 -> H&S BN MCIPAC MCB CP BUTLER JA | M3: Tenant: | R3: =UNIT_ROLLUP!R3 -> CLB 4
A4: Installation UIC: | F4: =UNIT_ROLLUP!F4 -> M67400 | M4: Tenant UIC: | R4: =UNIT_ROLLUP!R4 -> M29030 | Y4: Planning Area: | AE4: =UNIT_ROLLUP!AE4 -> SW
A5: CCN: | C5: 45110 | M5: Nomenclature: | R5: Open Storage Area
A6: LOADING ANALYSIS / JUSTIFICATION OF REQUIREMENT
A7: Description:
B8: Mission: This Mission Statement prescribes the organizational structure, billet authorization, personnel strength, and individual weapons for the Marine Expeditionary Unit (MEU) Combat Logistics Battalion (CLB), Marine Logistics Group (MLG). Provide tactical logistics support above the organic capabilities of supported elements of the MEU. CCN: This category group consists of non-covered storage areas, paved or otherwise established, for storage of General Supply Materials. Justification: Open Storage Areas are required by CLB 22 to provide laydown area for shipping containers.
A16: Planning Criteria:
B17: UFC 2-000-05N
A18: Loading:
B19: FY2025 Table of Organization / Equipment (attached)
A21: Analysis:
B23: Total Space Requirement
B24: Shipping Containers | G24: Additional Storage | M24: Total
B25: =R54*0.11111 -> #REF! | G25: =AA71*0.11111 -> 0 | M25: =SUM(B25:K25) -> #REF!
J46: SEE THE ATTACHED PAGES FOR CALCULATIONS
A47: TOTAL REQUIREMENT: | H47: =M25 -> #REF! | L47: GSY | AC47: Page | AD47: 1 | AE47: of | AF47: 2
A48: CCN: | C48: 45110 | M48: Nomenclature: | R48: Open Storage Area
B50: Summary of Shipping Container Space Requirement
B51: ITEM | F51: Total | J51: NSF | N51: Total NSF | R51: 2.5
B52: QUADCON | F52: =Q63+U63 -> #REF! | J52: 38 | N52: =F52*J52 -> #REF! | R52: =N52*R51 -> #REF!
B53: JMIC | F53: =Z63+M63 -> #REF! | J53: 15.89 | N53: =F53*J53 -> #REF! | R53: =N53*R51 -> #REF!
R54: =SUM(R52:T53) -> #REF!
B55: Calculation of Outdoor Shipping Container Stacks
B56: Subordinate Unit | M56: JMIC | Q56: QUADCON | U56: QUADCON | Z56: JMIC
M57: C00772EA | Q57: C44332E | U57: C44332EA | Z57: C00772E
B58: ='Header '!A6 -> M29030 | E58: ='Header '!B6 -> CLB 4 | M58: =SUMIFS(#REF!,#REF!,$M$57,#REF!,B58) -> #REF! | Q58: =SUMIFS(#REF!,#REF!,$Q$57,#REF!,B58) -> #REF! | U58: =SUMIFS(#REF!,#REF!,$U$57,#REF!,B58) -> #REF! | Z58: =SUMIFS(#REF!,#REF!,$Z$57,#REF!,B58) -> #REF!
L63: Total Containers = | M63: =SUM(M58:P62) -> #REF! | Q63: =SUM(Q58:T62) -> #REF! | U63: =SUM(U58:Y62) -> #REF! | Z63: =SUM(Z58:AD62) -> #REF!
B66: Additional Storage Requirements
B67: Function | L67: L | N67: W | P67: Area Ea. (NSF) | T67: Quantity | W67: Area (NSF) | AA67: 2.5
AA68: =$AA$95*W68 -> 0
AC90: Page | AD90: 2 | AE90: of | AF90: 2

Sheet 21455
A1: BASIC FACILITY REQUIREMENTS WORKSHEET
A3: Installation: | F3: H&S BN MCIPAC MCB CP BUTLER JA | M3: Tenant: | R3: CLB 4
A4: Installation UIC: | F4: M67400 | M4: Tenant UIC: | R4: M29030 | Y4: Planning Area: SW
A5: CCN: | C5: 21455 | M5: Nomenclature: | R5: VEHICLE WASH PLATFORM
A6: SPACE REQUIREMENT ANALYSIS · CCN 21455 · UFC 2-000-05N / UFC 21455-1 | Net to Gross Factor: 1.33
A7: NOTE: UFC 2-000-05N does not require a BFR for Vehicle Wash Platforms. This analysis is provided for planning purposes only. No billets assigned — operated by CCN 21451 personnel.
A9: VEHICLE COUNT — Self-Propelled Only (Trailers excluded per UFC 21455-1 | SABAR not present)
A10: Company / Unit | V10: UFC Factor (1 Space / 50 Vehicles) | Y10: Vehicle Count
A11: HQ CO (M29111) | Y11: 9
A12: CLC A (M29112) | Y12: 19
A13: CLC B (M29113) | Y13: 19
A14: GS CO (M29114) | Y14: 15
A15: Total Self-Propelled Vehicles | AB15: =SUM(Y11:Y14) -> 62
A17: WASH SPACE CALCULATION — UFC 21455-1: 1 Space per 50 Vehicles | 1,200 SF per Space | All wash racks on single pad (UFC 21455-2)
A18: Criterion | V18: SF / Space | Y18: Spaces Required | AB18: NSF
A19: Wash Spaces: CEILING(62 / 50) = 2 (wash bay, sediment basin, oil/water separator) | V19: 1200 | Y19: 2 | AB19: =V19*Y19 -> 2400
A20: Total NSF | AB20: =AB19 -> 2400
A22: TOTAL SPACE REQUIREMENT
A23: NTG Factor = 1.33 | Required GSF = ROUNDUP(2,400 × 1.33, 0) = 3,192 GSF | V23: 1.33 | AB23: =ROUNDUP(AB20*V23,0) -> 3192
A34: TOTAL REQUIREMENT: | H34: =AB23 -> 3192 | L34: GSF | AC34: Page | AD34: 1 | AE34: of | AF34: 1

Sheet 61072
A1: BASIC FACILITY REQUIREMENTS WORKSHEET
A3: Installation: | F3: H&S BN MCIPAC MCB CP BUTLER JA | M3: Tenant: | R3: CLB 4
A4: Installation UIC: | F4: M67400 | M4: Tenant UIC: | R4: M29030 | Y4: Planning Area: SW
A5: CCN: | C5: 61072 | M5: Nomenclature: | R5: BATTALION SQUADRON HEADQUARTERS, MARINE CORPS
A6: SPACE REQUIREMENT ANALYSIS · CCN 61072 · UFC 2-000-05N Chapter 61 (Administrative) | Net to Gross Factor: 1.33
A7: BILLETS EXCLUDED FROM THIS CCN (require separate facility CCNs - documented here for record):
A8: Medical / BAS billets (34) - medical facility CCN required
A9: EOD Section billets (13) - EOD facility CCN required
A10: Specialist shop billets (99) - maintenance shop CCN(s) required
A11: Ordnance repair billets (10) - ordnance shop CCN required
A13: ADMINISTRATIVE SPACE CALCULATION - 84 In-Scope Billets (UFC 2-000-05N Chapter 61)
A14: Space Type | V14: SF / Person | Y14: Count | AB14: NSF
A15: Private Offices - CO, XO, CSE, Chaplain, S-Staff OICs, Company CDRs/XOs, Warrant Officers (21 billets) | V15: 120 | Y15: 21 | AB15: =V15*Y15 -> 2520
A16: Cubicles - S-Staff NCOs, Company Admin, Supply, and Communications Support billets (63 billets) | V16: 60 | Y16: 63 | AB16: =V16*Y16 -> 3780
A17: Total NSF | AB17: =SUM(AB15:AB16) -> 6300
A19: TOTAL SPACE REQUIREMENT
A20: NTG Factor = 1.33 | Required GSF = ROUNDUP(6,300 × 1.33, 0) = 8,379 GSF | V20: 1.33 | AB20: =ROUNDUP(AB17*V20,0) -> 8379
A34: TOTAL REQUIREMENT: | H34: =AB20 -> 8379 | L34: GSF | Z34: Page 1 of 1 | AF34: 1

Sheet TAMCN Info
B1: TAMCN | C1: COLLOQUIAL_NAME | D1: PROGRAM_OFFICE | E1: NATIONAL_STOCK_NUMBER | F1: NIIN | G1: ITEM_EXIT_DATE | H1: TAM_STATUS | I1: DIMENSION_LENGTH_IN_INCHES | J1: DIMENSION_WIDTH_IN_INCHES | K1: DIMENSION_HEIGHT_IN_INCHES | L1: STD_PKG_LB_WT | M1: CIC | N1: CIIC | O1: TOS ARMY | P1: TOS | Q1: TOS COMBINED | R1: TOS EXPLANATION | S1: Vault/Armory
A2: =LEFT(B2,5) -> A0000 | B2: A00000 orig.
A3: =LEFT(B3,5) -> A0000 | B3: A000000 orig.
A4: =LEFT(B4,5) -> A0003 | B4: A00037G | C4: ALARM SET,ANTI-INTR - AN/PSQ-21A | I4: 14 | J4: 7 | K4: 3
A5: =LEFT(B5,5) -> A0003 | B5: A00037G | C5: ALARM SET,ANTI-INTR - AN/PSQ-21A | I5: 13.5 | J5: 6.24 | K5: 4.5
A6: =LEFT(B6,5) -> A0003 | B6: A00037G | C6: ALARM SET,ANTI-INTR - AN/PSQ-21A | I6: 3 | J6: 14 | K6: 7
A7: =LEFT(B7,5) -> A0003 | B7: A00037G | C7: ALARM SET,ANTI-INTR - AN/PSQ-21A | I7: 4.5 | J7: 13.5 | K7: 6.24
A8: =LEFT(B8,5) -> A0011 | B8: A001157G orig.
A9: =LEFT(B9,5) -> A0011 | B9: A001157G orig.
A10: =LEFT(B10,5) -> A0012 | B10: A00122B | C10: CHARGER, BATTERY (SOLDIER PORTABLE CHARGER) | D10: PMM-115.3 PdM EPS | E10: 6130014952839 | F10: 014952839 | G10: 44896 | H10: IS | I10: 22.8 | J10: 14.6 | K10: 9 | L10: 27.5 | M10: A | N10: U | O10: A | P10: A | Q10: A | R10: Heated General Purpose – Heated 40 F and above | S10: NO
A11: =LEFT(B11,5) -> A0012 | B11: A00122B | C11: CREW SPC W/REV K SOFTWARE | D11: PMM-115.3 PdM EPS | E11: 6130016516491 | F11: 016516491 | G11: 44896 | H11: PL | I11: 22.8 | J11: 14.6 | K11: 9 | L11: 27.5 | M11: A | N11: U | O11: A | P11: A | Q11: A | R11: Heated General Purpose – Heated 40 F and above | S11: NO
A12: =LEFT(B12,5) -> A0012 | B12: A00122B | C12: CHARGER, BATTERY (SOLDIER PORTABLE CHARGER) | D12: PMM-115.3 PdM EPS | E12: 6130014952839 | F12: 014952839 | G12: 44896 | H12: IS | I12: 9 | J12: 22.8 | K12: 14.6 | L12: 27.5 | M12: A | N12: U | O12: A | P12: A | Q12: A | R12: Heated General Purpose – Heated 40 F and above | S12: NO
A13: =LEFT(B13,5) -> A0012 | B13: A00122B | C13: CREW SPC W/REV K SOFTWARE | D13: PMM-115.3 PdM EPS | E13: 6130016516491 | F13: 016516491 | G13: 44896 | H13: PL | I13: 9 | J13: 22.8 | K13: 14.6 | L13: 27.5 | M13: A | N13: U | O13: A | P13: A | Q13: A | R13: Heated General Purpose – Heated 40 F and above | S13: NO
A14: =LEFT(B14,5) -> A0013 | B14: A00137G | C14: THEATER BATTLE MANAGEMENT CORE SYSTEMS | D14: PMM-202 PEOLS AC2SN | E14: 7010015346285 | F14: 015346285 | G14: 41944 | H14: AR | I14: 37 | J14: 27 | K14: 24 | L14: 4514 | M14: A | N14: J | S14: NO
A15: =LEFT(B15,5) -> A0013 | B15: A00137G | C15: TACTICAL COMMAND SYSTEM (TCS) | D15: PMM-202 PEOLS AC2SN | E15: 7010015346283 | F15: 015346283 | G15: 42005 | H15: AR | I15: 37 | J15: 27 | K15: 24 | L15: 4514 | M15: A | N15: J | S15: NO
A16: =LEFT(B16,5) -> A0013 | B16: A00137G | C16: THEATER BATTLE MANAGEMENT CORE SYSTEMS | D16: PMM-202 PEOLS AC2SN | E16: 7010016319168 | F16: 016319168 | G16: 44470 | H16: IS | I16: 37 | J16: 27 | K16: 24 | L16: 4514 | M16: A | N16: J | S16: NO
A17: =LEFT(B17,5) -> A0013 | B17: A00137G | C17: THEATER BATTLE MANAGEMENT CORE SYSTEMS | D17: PMM-202 PEOLS AC2SN | E17: 7010015346285 | F17: 015346285 | G17: 41944 | H17: AR | I17: 24 | J17: 37 | K17: 27 | L17: 4514 | M17: A | N17: J | S17: NO
A18: =LEFT(B18,5) -> A0013 | B18: A00137G | C18: TACTICAL COMMAND SYSTEM (TCS) | D18: PMM-202 PEOLS AC2SN | E18: 7010015346283 | F18: 015346283 | G18: 42005 | H18: AR | I18: 24 | J18: 37 | K18: 27 | L18: 4514 | M18: A | N18: J | S18: NO
A19: =LEFT(B19,5) -> A0013 | B19: A00137G | C19: THEATER BATTLE MANAGEMENT CORE SYSTEMS | D19: PMM-202 PEOLS AC2SN | E19: 7010016319168 | F19: 016319168 | G19: 44470 | H19: IS | I19: 24 | J19: 37 | K19: 27 | L19: 4514 | M19: A | N19: J | S19: NO
A20: =LEFT(B20,5) -> A0013 | B20: A00137G orig. | C20: TACTICAL COMMAND SYSTEM (TCS) | D20: PMM-202 PEOLS AC2SN | G20: 41306 | H20: AR | I20: 0 | J20: 0 | K20: 0 | L20: 4514 | M20: A | N20: J | S20: NO
A21: =LEFT(B21,5) -> A0015 | B21: A00157G | C21: VIDEO EXPLOITATION WORKSTATION (VEW) | D21: PMM-112.1 PdM P-ISR | E21: 5836016406831 | F21: 016406831 | G21: 45931 | H21: IS | I21: 32 | J21: 21 | K21: 16 | L21: 80 | M21: A | N21: U | S21: NO
A22: =LEFT(B22,5) -> A0015 | B22: A00157G | C22: WORKSTATION, CAPABILITY, VIDEO EXPLOITATION | D22: PMM-112.1 PdM P-ISR | E22: 5836015313140 | F22: 015313140 | G22: 40148 | H22: AR | I22: 87.2 | J22: 60.5 | K22: 36.1 | L22: 163 | N22: 7 | S22: NO
A23: =LEFT(B23,5) -> A0015 | B23: A00157G | C23: WORKSTATION, CAPABILITY, VIDEO EXPLOITATION | D23: PMM-112.1 PdM P-ISR | E23: 5836090004317 | F23: 090004317 | G23: 45931 | H23: DP | I23: 32 | J23: 21 | K23: 16 | L23: 63 | M23: A | N23: U | S23: NO
A24: =LEFT(B24,5) -> A0015 | B24: A00157G | C24: VIDEO EXPLOITATION WORKSTATION (VEW) | D24: PMM-112.1 PdM P-ISR | E24: 5836016406831 | F24: 016406831 | G24: 45931 | H24: IS | I24: 16 | J24: 32 | K24: 21 | L24: 80 | M24: A | N24: U | S24: NO
A25: =LEFT(B25,5) -> A0015 | B25: A00157G | C25: WORKSTATION, CAPABILITY, VIDEO EXPLOITATION | D25: PMM-112.1 PdM P-ISR | E25: 5836015313140 | F25: 015313140 | G25: 40148 | H25: AR | I25: 36.1 | J25: 87.2 | K25: 60.5 | L25: 163 | N25: 7 | S25: NO
A26: =LEFT(B26,5) -> A0015 | B26: A00157G | C26: WORKSTATION, CAPABILITY, VIDEO EXPLOITATION | D26: PMM-112.1 PdM P-ISR | E26: 5836090004317 | F26: 090004317 | G26: 45931 | H26: DP | I26: 16 | J26: 32 | K26: 21 | L26: 63 | M26: A | N26: U | S26: NO
A27: =LEFT(B27,5) -> A0016 | B27: A00167G | C27: SENSOR, COUNTER FIRE, GROUND | D27: PMM-114.1 PdM FSS | E27: 1290999580742 | F27: 999580742 | G27: 46813 | H27: IS | I27: 57 | J27: 96 | K27: 80 | L27: 3000 | M27: A | N27: 4 | S27: YES
A28: =LEFT(B28,5) -> A0016 | B28: A00167G | C28: SENSOR, COUNTER FIRE, GROUND | D28: PMM-114.1 PdM FSS | E28: 1290016562212 | F28: 016562212 | G28: 46813 | H28: IS | I28: 57 | J28: 96 | K28: 80 | L28: 3000 | M28: A | N28: 7 | S28: YES
A29: =LEFT(B29,5) -> A0016 | B29: A00167G | C29: SENSOR, COUNTER FIRE, GROUND | D29: PMM-114.1 PdM FSS | E29: 1290999580742 | F29: 999580742 | G29: 46813 | H29: IS | I29: 80 | J29: 57 | K29: 96 | L29: 3000 | M29: A | N29: 4 | S29: YES
A30: =LEFT(B30,5) -> A0016 | B30: A00167G | C30: SENSOR, COUNTER FIRE, GROUND | D30: PMM-114.1 PdM FSS | E30: 1290016562212 | F30: 016562212 | G30: 46813 | H30: IS | I30: 80 | J30: 57 | K30: 96 | L30: 3000 | M30: A | N30: 7 | S30: YES
A31: =LEFT(B31,5) -> A0016 | B31: A00167G orig. | C31: SENSOR, COUNTER FIRE, GROUND | D31: MCSC-PMM-141 | E31: 5895015313144 | F31: 015313144 | G31: 40238 | H31: AR | M31: A | N31: 7 | S31: YES
A32: =LEFT(B32,5) -> A0016 | B32: A00167G orig. | C32: SENSOR, COUNTER FIRE, GROUND | D32: MCSC-PMM-141 | E32: 5895015313144 | F32: 015313144 | G32: 40238 | H32: AR | M32: A | N32: 7 | S32: YES
A33: =LEFT(B33,5) -> A0021 | B33: A00217G | C33: COMM DATA LINK SYTEM (CDLS) | D33: PMM-202 PEOLS AC2SN | E33: 5895015128683 | F33: 015128683 | G33: 44440 | H33: IS | I33: 205 | J33: 92 | K33: 108 | L33: 11320 | M33: A | N33: 7 | S33: NO
A34: =LEFT(B34,5) -> A0021 | B34: A00217G | C34: COMM DATA LINK SYTEM (CDLS) | D34: PMM-202 PEOLS AC2SN | E34: 5895015128683 | F34: 015128683 | G34: 44440 | H34: IS | I34: 108 | J34: 205 | K34: 92 | L34: 11320 | M34: A | N34: 7 | S34: NO
A35: =LEFT(B35,5) -> A0026 | B35: A00267G | C35: RADIATION DETECTION SYSTEM | D35: PMM-113.2 PdM ICE | E35: 6665013476100 | F35: 013476100 | G35: 44409 | H35: IS | I35: 22 | J35: 15 | K35: 10 | L35: 28 | M35: A | N35: 7 | O35: A | P35: A | Q35: A | R35: Heated General Purpose – Heated 40 F and above | S35: NO
A36: =LEFT(B36,5) -> A0026 | B36: A00267G | C36: RADIATION DETECTION SYSTEM | D36: PMM-113.2 PdM ICE | E36: 6665013476100 | F36: 013476100 | G36: 44409 | H36: IS | I36: 10 | J36: 22 | K36: 15 | L36: 28 | M36: A | N36: 7 | O36: A | P36: A | Q36: A | R36: Heated General Purpose – Heated 40 F and above | S36: NO
A37: =LEFT(B37,5) -> A0031 | B37: A00317G orig. | C37: AIR COMMAND & CONTROL SYSTEM (AC2S) | D37: PMM-202 PEOLS AC2SN | E37: 5895016285884 | F37: 016285884 | G37: 49949 | H37: IS | I37: 0 | J37: 0 | K37: 0 | L37: 0 | M37: A | N37: 7 | S37: NO
A38: =LEFT(B38,5) -> A0031 | B38: A00317G orig. | C38: AIR COMMAND & CONTROL SYSTEM (AC2S) | D38: PMM-202 PEOLS AC2SN | E38: 5895016285884 | F38: 016285884 | G38: 49949 | H38: IS | I38: 0 | J38: 0 | K38: 0 | L38: 0 | M38: A | N38: 7 | S38: NO
A39: =LEFT(B39,5) -> A0032 | B39: A00327G | C39: COMMUNICATIONS SUB-SYSTEM | D39: PMM-202 PEOLS AC2SN | E39: 5895015477697 | F39: 015477697 | G39: 41671 | H39: AR | I39: 341 | J39: 95 | K39: 114 | L39: 14340 | M39: A | N39: 7 | S39: NO
A40: =LEFT(B40,5) -> A0032 | B40: A00327G | C40: COMMUNICATIONS SYSTEM | D40: PMM-202 PEOLS AC2SN | E40: 5895015928791 | F40: 015928791 | G40: 49949 | H40: IS | I40: 341 | J40: 95 | K40: 114 | L40: 14340 | M40: A | N40: 7 | S40: NO
A41: =LEFT(B41,5) -> A0032 | B41: A00327G | C41: COMMUNICATIONS SUB-SYSTEM | D41: PMM-202 PEOLS AC2SN | E41: 5895015477697 | F41: 015477697 | G41: 41671 | H41: AR | I41: 114 | J41: 341 | K41: 95 | L41: 14340 | M41: A | N41: 7 | S41: NO
A42: =LEFT(B42,5) -> A0032 | B42: A00327G | C42: COMMUNICATIONS SYSTEM | D42: PMM-202 PEOLS AC2SN | E42: 5895015928791 | F42: 015928791 | G42: 49949 | H42: IS | I42: 114 | J42: 341 | K42: 95 | L42: 14340 | M42: A | N42: 7 | S42: NO
